Workbook

Sheet Lisez-moi
A1: Helium, modèle financier 36 mois, V1
A3: Objet | B3: Prévision mensuelle de trésorerie sur 36 mois pour le projet Helium (ex Super Majordome IA), HEC GEMM Group 4. Trois scénarios, économie unitaire, sensibilités, KPI et plan de financement.
A4: Statut | B4: Document de travail. Toutes les hypothèses sont non validées par des mesures (voir colonne Source de l'onglet Hypothèses). Aucun chiffre n'est une dépense engagée ni un financement obtenu.
A5: Préparé par | B5: Assistant IA Direction, à la demande du CEO (Malik), le 27 octobre 2026, pour Sébastien (Finance).
A6: Légende | B6: Texte bleu = entrée modifiable. Fond jaune = levier clé. Texte noir = formule. Texte vert = lien vers un autre onglet. Ne rien saisir dans les onglets Modèle et S01 à S10 en dehors de la ligne de chocs.
A7: Onglets | B7: Hypothèses (toutes les entrées, trois scénarios, sélecteur F3) · Économie unitaire (par offre, grilles de sensibilité) · Modèle Prudent / Central / Ambitieux (36 mois) · Synthèse (comparaison) · Tornade (sensibilités du Central) · S01 à S11 (copies du Central avec un choc) · KPI · Financement.
A8: Mécanique | B8: Abonnés : ouverture + acquisition payante (budget / CAC) + pilote + organique − churn. Revenus TTC → TVA → CA HT. Coûts variables = missions × coût par mission + hébergement + support. Trésorerie : encaissements TTC, coûts HT, TVA nette réglée le mois suivant, financement optionnel.
A9: Simplifications | B9: Mix par offre appliqué au total des abonnés. TVA récupérable sur tous les coûts externes (fournisseurs étrangers en autoliquidation). Pas d'impôt sur les sociétés (pertes), pas de CIR/CII, pas de délai de paiement fournisseurs. Développement MVP passé en charges.
A10: Sensibilités | B10: Onglet Tornade : Churn 5 % (churn × 1,67 (3 % → 5 %)) ; Churn 2 % (churn × 0,67 (3 % → 2 %)) ; CAC 240 € (CAC × 1,6) ; CAC 105 € (CAC × 0,7) ; Coût IA +67 % (coût par mission × 1,67 (0,18 → 0,30 €)) ; Coût IA −33 % (coût par mission × 0,67 (0,18 → 0,12 €)) ; Prix −20 % (prix × 0,8 (Premium 79 → 63 €)) ; Prix +20 % (prix × 1,2 (Premium 79 → 95 €)) ; Lancement +3 mois (retard de lancement de 3 mois) ; Coûts fixes +30 % (coûts fixes × 1,3) ; Churn 8 % (type app store) (churn × 2,67 (3 % → 8 %)).
A11: Contrôles effectués | B11: Recalcul complet sous LibreOffice, zéro erreur de formule ; mix = 100 % ; cohérence avec les ordres de grandeur Finance V3 (point bas central −173 k€, prudent −580 k€) ; hypothèses de coût IA, churn et CAC confrontées aux benchmarks publics d'octobre 2026 (sources dans la colonne G de l'onglet Hypothèses et dans l'analyse de marché).
A12: À faire par Finance | B12: Remplacer les hypothèses de coût par mission et de missions par mois par les mesures de Produit/Opérations ; remplacer CAC, conversion et churn par les cohortes du pilote ; saisir les devis MVP réels ; valider le régime de TVA et les dates d'encaissement.
A13: Sources internes | B13: 0 INBOX/BMC V2 ; 2 FINANCE/PREVISIONS (Business plan Lean V1, Registre des hypothèses, Acquisition et économie unitaire) ; 2 FINANCE/TRESORERIE (Synthèse V3) ; 2 FINANCE/FINANCEMENT (Stratégie V1) ; 4 VENTES (Synthèse exécutive, Objectifs et dashboard) ; 5 PRODUIT (Contribution marketing au cadrage MVP).

Sheet Hypothèses
A1: Hypothèses par scénario
A2: Cellules bleues = entrées modifiables. Colonne F = scénario actif (sélecteur en F3). Chaque ligne cite sa source ou dit qu'elle est une hypothèse.
E3: Scénario actif (1 = Prudent, 2 = Central, 3 = Ambitieux) | F3: 2
A5: Hypothèse | B5: Unité | C5: Prudent | D5: Central | E5: Ambitieux | F5: Actif | G5: Source / commentaire
A6: Calendrier
A7: Date de début du modèle (M1) | B7: date | C7: 46327 | D7: 46327 | E7: 46327 | F7: =INDEX(C7:E7,1,$F$3) | G7: Hypothèse de calendrier : M1 = novembre 2026. Modifiable.
A8: Mois de démarrage du pilote payant | B8: mois | C8: 4 | D8: 3 | E8: 3 | F8: =INDEX(C8:E8,1,$F$3) | G8: Plan Ventes 90 jours : 10 pilotes payants entre J31 et J60 (4 VENTES/2026 1027 01 Synthese executive).
A9: Taille de la cohorte pilote payante | B9: abonnés | C9: 10 | D9: 10 | E9: 10 | F9: =INDEX(C9:E9,1,$F$3) | G9: Même source. Les pilotes paient le prix public.
A10: Mois de lancement commercial | B10: mois | C10: 10 | D10: 7 | E10: 6 | F10: =INDEX(C10:E10,1,$F$3) | G10: Finance V3 : lancement M7 (central) / M10 (prudent). Source : 2 FINANCE/TRESORERIE/2026 1027 Synthese tresorerie V3.
A11: Prix et mix (TTC par mois)
A12: Prix Personal TTC | B12: €/mois | C12: 29 | D12: 29 | E12: 29 | F12: =INDEX(C12:E12,1,$F$3) | G12: BMC V2, hypothèse H01 non validée. À tester (Van Westendorp).
A13: Prix Premium TTC | B13: €/mois | C13: 79 | D13: 79 | E13: 79 | F13: =INDEX(C13:E13,1,$F$3) | G13: BMC V2, hypothèse H01 non validée.
A14: Prix Family TTC | B14: €/mois | C14: 129 | D14: 129 | E14: 129 | F14: =INDEX(C14:E14,1,$F$3) | G14: BMC V2, hypothèse H01 non validée.
A15: TVA | B15: % | C15: 0.2 | D15: 0.2 | E15: 0.2 | F15: =INDEX(C15:E15,1,$F$3) | G15: Taux normal France (hypothèse H02). Ventes B2C UE hors France : TVA du pays du client (OSS).
A16: Part Personal dans les abonnés | B16: % | C16: 0.3 | D16: 0.25 | E16: 0.2 | F16: =INDEX(C16:E16,1,$F$3) | G16: Hypothèse de mix. Aucune donnée observée.
A17: Part Premium | B17: % | C17: 0.55 | D17: 0.6 | E17: 0.6 | F17: =INDEX(C17:E17,1,$F$3) | G17: Hypothèse de mix.
A18: Part Family | B18: % | C18: 0.15 | D18: 0.15 | E18: 0.2 | F18: =INDEX(C18:E18,1,$F$3) | G18: Hypothèse de mix. Doit sommer à 100 % avec les deux lignes précédentes.
A19: Acquisition
A20: Budget d'acquisition mensuel, du lancement à M12 | B20: € HT/mois | C20: 2000 | D20: 3000 | E20: 4000 | F20: =INDEX(C20:E20,1,$F$3) | G20: Hypothèse. Finance V3 : 24 188 € d'acquisition en A1 (central).
A21: Budget d'acquisition mensuel, M13 à M24 | B21: € HT/mois | C21: 6000 | D21: 10000 | E21: 12000 | F21: =INDEX(C21:E21,1,$F$3) | G21: Hypothèse. Finance V3 : 121 688 € en A2.
A22: Budget d'acquisition mensuel, M25 à M36 | B22: € HT/mois | C22: 12000 | D22: 25000 | E22: 25000 | F22: =INDEX(C22:E22,1,$F$3) | G22: Hypothèse. Finance V3 : 340 275 € en A3.
A23: CAC (coût par abonné payant acquis) | B23: € | C23: 240 | D23: 150 | E23: 110 | F23: =INDEX(C23:E23,1,$F$3) | G23: Hypothèse H04 (150 €) et prudent (240 €). Benchmarks : CPI iOS 4,70 $ (Adapty 2026) / conversion téléchargement → payant 2 % (RevenueCat 2026) ≈ 235 $ par abonné payant en acquisition payante ; 44 $ avec paywall et essai. Réseau et parrainage visés pour rester sous 150 €. Non mesuré.
A24: Acquisition organique (parrainage), % de la base par mois | B24: % | C24: 0.01 | D24: 0.02 | E24: 0.025 | F24: =INDEX(C24:E24,1,$F$3) | G24: Hypothèse. À mesurer pendant le pilote.
A25: Rétention et encaissement
A26: Churn mensuel (résiliations / abonnés début de mois) | B26: % | C26: 0.06 | D26: 0.03 | E26: 0.025 | F26: =INDEX(C26:E26,1,$F$3) | G26: Hypothèse H05 (3 %). Benchmarks : Recurly juillet 2026, ARPU 10 à 25 $ : 4,3 % par mois ; ProfitWell, ARPU 25 à 50 $ : 6,9 % par mois ; RevenueCat 2026, applications IA en plan mensuel : 6 % de rétention à 12 mois (churn précoce très élevé). Prudent fixé à 6 %. Non mesuré.
A27: Impayés, % de la facturation | B27: % | C27: 0.02 | D27: 0.01 | E27: 0.005 | F27: =INDEX(C27:E27,1,$F$3) | G27: Scénario prudent Finance : 2 %.
A28: Frais de paiement, % du montant encaissé | B28: % | C28: 0.015 | D28: 0.015 | E28: 0.015 | F28: =INDEX(C28:E28,1,$F$3) | G28: Ordre de grandeur Stripe cartes EEE : 1,5 % + 0,25 €. À vérifier sur la grille en vigueur.
A29: Frais de paiement fixes par transaction | B29: € | C29: 0.25 | D29: 0.25 | E29: 0.25 | F29: =INDEX(C29:E29,1,$F$3) | G29: Idem.
A30: Coûts variables (HT, par abonné et par mois)
A31: Missions exécutées par mois, Personal | B31: missions | C31: 20 | D31: 20 | E31: 20 | F31: =INDEX(C31:E31,1,$F$3) | G31: Hypothèse d'usage. À mesurer (demande de cadrage Finance → Produit).
A32: Missions exécutées par mois, Premium | B32: missions | C32: 60 | D32: 60 | E32: 60 | F32: =INDEX(C32:E32,1,$F$3) | G32: Hypothèse : 2 missions par jour ouvré.
A33: Missions exécutées par mois, Family | B33: missions | C33: 90 | D33: 90 | E33: 90 | F33: =INDEX(C33:E33,1,$F$3) | G33: Hypothèse.
A34: Coût IA et outils par mission (tokens, API, reprises) | B34: € HT | C34: 0.3 | D34: 0.18 | E34: 0.12 | F34: =INDEX(C34:E34,1,$F$3) | G34: Hypothèse conservée au-dessus de l'estimation ascendante : le classeur Technique/Helium_Cout_par_mission_V1.xlsx (28/10/2026, prix publics Mistral, Anthropic via Bedrock UE, Brave, Places, Browserbase) donne environ 0,07 € par mission visible pour un abonné Premium, socle nocturne réparti, et environ 1 € pour une prise de rendez-vous par navigateur piloté (support humain compris). 0,18 € (central) couvre 2,5 fois l'estimation ; 0,30 € (prudent) est le seuil au-delà duquel le plan prévoit limites d'usage et test de prix. Référence externe : tau2-bench 0,26 à 0,49 $ par trajectoire (classe Sonnet). À remplacer par les mesures des missions 1 et 5 (3 décembre) puis 3 et 4 (19 décembre).
A35: Hébergement, stockage, connecteurs | B35: € HT | C35: 2 | D35: 1.5 | E35: 1 | F35: =INDEX(C35:E35,1,$F$3) | G35: Hypothèse.
A36: Support humain (minutes × coût horaire) | B36: € HT | C36: 5 | D36: 3 | E36: 2 | F36: =INDEX(C36:E36,1,$F$3) | G36: Hypothèse.
A37: Coûts fixes (HT, par mois)
A38: Nombre de fondateurs rémunérés à partir du mois ci-dessous | B38: personnes | C38: 2 | D38: 2 | E38: 2 | F38: =INDEX(C38:E38,1,$F$3) | G38: Hypothèse Finance : fondateurs non rémunérés M1 à M12.
A39: Premier mois de rémunération des fondateurs | B39: mois | C39: 13 | D39: 13 | E39: 13 | F39: =INDEX(C39:E39,1,$F$3) | G39: Idem.
A40: Coût chargé mensuel par fondateur rémunéré | B40: € HT | C40: 5500 | D40: 5000 | E40: 5000 | F40: =INDEX(C40:E40,1,$F$3) | G40: Hypothèse modeste (≈ 3 000 € nets + charges, régime assimilé salarié).
A41: Embauche 1 (growth / customer success), premier mois | B41: mois | C41: 16 | D41: 13 | E41: 10 | F41: =INDEX(C41:E41,1,$F$3) | G41: Plan Ventes : growth 0,5 ETP puis customer success.
A42: Coût chargé mensuel, embauche 1 | B42: € HT | C42: 4500 | D42: 4500 | E42: 4500 | F42: =INDEX(C42:E42,1,$F$3) | G42: Hypothèse.
A43: Embauche 2 (ingénieur), premier mois | B43: mois | C43: 24 | D43: 19 | E43: 14 | F43: =INDEX(C43:E43,1,$F$3) | G43: Hypothèse.
A44: Coût chargé mensuel, embauche 2 | B44: € HT | C44: 6500 | D44: 6500 | E44: 6500 | F44: =INDEX(C44:E44,1,$F$3) | G44: Hypothèse.
A45: Budget MVP externe (développement, UX, sécurité, juridique) | B45: € HT | C45: 100000 | D45: 77050 | E45: 60000 | F45: =INDEX(C45:E45,1,$F$3) | G45: Business plan Lean V1 : 77 050 € HT (central), 100 000 € (prudent). Étalé de M1 au mois précédant le lancement.
A46: Outils et SaaS | B46: € HT/mois | C46: 400 | D46: 400 | E46: 400 | F46: =INDEX(C46:E46,1,$F$3) | G46: Hypothèse.
A47: Juridique et expertise comptable | B47: € HT/mois | C47: 1000 | D47: 800 | E47: 800 | F47: =INDEX(C47:E47,1,$F$3) | G47: Hypothèse.
A48: Assurance RC professionnelle (à partir du lancement) | B48: €/mois | C48: 150 | D48: 150 | E48: 150 | F48: =INDEX(C48:E48,1,$F$3) | G48: Hypothèse. Pas de TVA.
A49: Marketing fixe (marque, contenu), à partir du lancement | B49: € HT/mois | C49: 500 | D49: 1000 | E49: 1500 | F49: =INDEX(C49:E49,1,$F$3) | G49: Hypothèse.
... A54: Trésorerie initiale (apports déjà versés) | B54: € | C54: 0 | D54: 0 | E54: 0 | F54: =INDEX(C54:E54,1,$F$3) | G54: Non établi par les sources.
A55: Financement (désactivé par défaut : 0 = trésorerie avant financement)
A56: Inclure le financement dans la trésorerie (1 = oui, 0 = non) | B56: 0/1 | C56: 0 | D56: 0 | E56: 0 | F56: =INDEX(C56:E56,1,$F$3) | G56: Mettre 1 pour simuler le plan de financement de l'onglet Financement.
A57: Tranche 1, mois | B57: mois | C57: 2 | D57: 2 | E57: 2 | F57: =INDEX(C57:E57,1,$F$3) | G57: Voir onglet Financement.
A58: Tranche 1, montant | B58: € | C58: 15000 | D58: 15000 | E58: 15000 | F58: =INDEX(C58:E58,1,$F$3) | G58: Apports fondateurs, hypothèse.
A59: Tranche 2, mois | B59: mois | C59: 10 | D59: 7 | E59: 6 | F59: =INDEX(C59:E59,1,$F$3) | G59: À la création / au lancement.
A60: Tranche 2, montant | B60: € | C60: 150000 | D60: 150000 | E60: 150000 | F60: =INDEX(C60:E60,1,$F$3) | G60: Prêts d'honneur, Bourse French Tech, business angels : éligibilité non vérifiée.
A61: Tranche 3, mois | B61: mois | C61: 16 | D61: 13 | E61: 13 | F61: =INDEX(C61:E61,1,$F$3)
A62: Tranche 3, montant | B62: € | C62: 450000 | D62: 300000 | E62: 250000 | F62: =INDEX(C62:E62,1,$F$3) | G62: Amorçage, sous réserve de traction.
A64: Contrôle : somme du mix (doit être 100 %) | C64: =C16+C17+C18 | D64: =D16+D17+D18 | E64: =E16+E17+E18 | F64: =F16+F17+F18

Sheet Économie unitaire
A1: Économie unitaire (scénario actif)
A2: Par abonné et par mois, HT. Référence : colonne Actif de l'onglet Hypothèses.
A4: Ligne | B4: Personal | C4: Premium | D4: Family | E4: Mix pondéré
A5: Prix TTC | B5: =Hypothèses!$F$12 | C5: =Hypothèses!$F$13 | D5: =Hypothèses!$F$14 | E5: =B5*Hypothèses!$F$16+C5*Hypothèses!$F$17+D5*Hypothèses!$F$18
A6: Prix HT | B6: =Hypothèses!$F$12/(1+Hypothèses!$F$15) | C6: =Hypothèses!$F$13/(1+Hypothèses!$F$15) | D6: =Hypothèses!$F$14/(1+Hypothèses!$F$15) | E6: =B6*Hypothèses!$F$16+C6*Hypothèses!$F$17+D6*Hypothèses!$F$18
A7: Missions par mois | B7: =Hypothèses!$F$31 | C7: =Hypothèses!$F$32 | D7: =Hypothèses!$F$33 | E7: =B7*Hypothèses!$F$16+C7*Hypothèses!$F$17+D7*Hypothèses!$F$18
A8: Coût IA et outils | B8: =Hypothèses!$F$31*Hypothèses!$F$34 | C8: =Hypothèses!$F$32*Hypothèses!$F$34 | D8: =Hypothèses!$F$33*Hypothèses!$F$34 | E8: =B8*Hypothèses!$F$16+C8*Hypothèses!$F$17+D8*Hypothèses!$F$18
A9: Hébergement | B9: =Hypothèses!$F$35 | C9: =Hypothèses!$F$35 | D9: =Hypothèses!$F$35 | E9: =B9*Hypothèses!$F$16+C9*Hypothèses!$F$17+D9*Hypothèses!$F$18
A10: Support | B10: =Hypothèses!$F$36 | C10: =Hypothèses!$F$36 | D10: =Hypothèses!$F$36 | E10: =B10*Hypothèses!$F$16+C10*Hypothèses!$F$17+D10*Hypothèses!$F$18
A11: Frais de paiement | B11: =Hypothèses!$F$12*(1-Hypothèses!$F$27)*Hypothèses!$F$28+Hypothèses!$F$29 | C11: =Hypothèses!$F$13*(1-Hypothèses!$F$27)*Hypothèses!$F$28+Hypothèses!$F$29 | D11: =Hypothèses!$F$14*(1-Hypothèses!$F$27)*Hypothèses!$F$28+Hypothèses!$F$29 | E11: =B11*Hypothèses!$F$16+C11*Hypothèses!$F$17+D11*Hypothèses!$F$18
A12: Impayés (HT) | B12: =Hypothèses!$F$12*Hypothèses!$F$27/(1+Hypothèses!$F$15) | C12: =Hypothèses!$F$13*Hypothèses!$F$27/(1+Hypothèses!$F$15) | D12: =Hypothèses!$F$14*Hypothèses!$F$27/(1+Hypothèses!$F$15) | E12: =B12*Hypothèses!$F$16+C12*Hypothèses!$F$17+D12*Hypothèses!$F$18
A13: Contribution par abonné et par mois | B13: =B6-B8-B9-B10-B11-B12 | C13: =C6-C8-C9-C10-C11-C12 | D13: =D6-D8-D9-D10-D11-D12 | E13: =E6-E8-E9-E10-E11-E12
A14: Marge variable (% du prix HT) | B14: =IF(B6>0,B13/B6,0) | C14: =IF(C6>0,C13/C6,0) | D14: =IF(D6>0,D13/D6,0) | E14: =IF(E6>0,E13/E6,0)
A15: Payback du CAC (mois) | B15: =IF(B13>0,Hypothèses!$F$23/B13,0) | C15: =IF(C13>0,Hypothèses!$F$23/C13,0) | D15: =IF(D13>0,Hypothèses!$F$23/D13,0) | E15: =IF(E13>0,Hypothèses!$F$23/E13,0)
A16: LTV contributive simplifiée (contribution / churn) | B16: =IF(Hypothèses!$F$26>0,B13/Hypothèses!$F$26,0) | C16: =IF(Hypothèses!$F$26>0,C13/Hypothèses!$F$26,0) | D16: =IF(Hypothèses!$F$26>0,D13/Hypothèses!$F$26,0) | E16: =IF(Hypothèses!$F$26>0,E13/Hypothèses!$F$26,0)
A17: LTV / CAC | B17: =IF(Hypothèses!$F$23>0,B16/Hypothèses!$F$23,0) | C17: =IF(Hypothèses!$F$23>0,C16/Hypothèses!$F$23,0) | D17: =IF(Hypothèses!$F$23>0,D16/Hypothèses!$F$23,0) | E17: =IF(Hypothèses!$F$23>0,E16/Hypothèses!$F$23,0)
A20: Grille LTV / CAC, abonné Premium : churn mensuel (lignes) × CAC (colonnes)
A21: Churn \ CAC | B21: 100 | C21: 150 | D21: 200 | E21: 250 | F21: 300 | G21: 400
A22: 0.02 | B22: =IF(AND($A22>0,B$21>0),($C$13/$A22)/B$21,0) | C22: =IF(AND($A22>0,C$21>0),($C$13/$A22)/C$21,0) | D22: =IF(AND($A22>0,D$21>0),($C$13/$A22)/D$21,0) | E22: =IF(AND($A22>0,E$21>0),($C$13/$A22)/E$21,0) | F22: =IF(AND($A22>0,F$21>0),($C$13/$A22)/F$21,0) | G22: =IF(AND($A22>0,G$21>0),($C$13/$A22)/G$21,0)
A23: 0.03 | B23: =IF(AND($A23>0,B$21>0),($C$13/$A23)/B$21,0) | C23: =IF(AND($A23>0,C$21>0),($C$13/$A23)/C$21,0) | D23: =IF(AND($A23>0,D$21>0),($C$13/$A23)/D$21,0) | E23: =IF(AND($A23>0,E$21>0),($C$13/$A23)/E$21,0) | F23: =IF(AND($A23>0,F$21>0),($C$13/$A23)/F$21,0) | G23: =IF(AND($A23>0,G$21>0),($C$13/$A23)/G$21,0)
A24: 0.04 | B24: =IF(AND($A24>0,B$21>0),($C$13/$A24)/B$21,0) | C24: =IF(AND($A24>0,C$21>0),($C$13/$A24)/C$21,0) | D24: =IF(AND($A24>0,D$21>0),($C$13/$A24)/D$21,0) | E24: =IF(AND($A24>0,E$21>0),($C$13/$A24)/E$21,0) | F24: =IF(AND($A24>0,F$21>0),($C$13/$A24)/F$21,0) | G24: =IF(AND($A24>0,G$21>0),($C$13/$A24)/G$21,0)
A25: 0.05 | B25: =IF(AND($A25>0,B$21>0),($C$13/$A25)/B$21,0) | C25: =IF(AND($A25>0,C$21>0),($C$13/$A25)/C$21,0) | D25: =IF(AND($A25>0,D$21>0),($C$13/$A25)/D$21,0) | E25: =IF(AND($A25>0,E$21>0),($C$13/$A25)/E$21,0) | F25: =IF(AND($A25>0,F$21>0),($C$13/$A25)/F$21,0) | G25: =IF(AND($A25>0,G$21>0),($C$13/$A25)/G$21,0)
A26: 0.07 | B26: =IF(AND($A26>0,B$21>0),($C$13/$A26)/B$21,0) | C26: =IF(AND($A26>0,C$21>0),($C$13/$A26)/C$21,0) | D26: =IF(AND($A26>0,D$21>0),($C$13/$A26)/D$21,0) | E26: =IF(AND($A26>0,E$21>0),($C$13/$A26)/E$21,0) | F26: =IF(AND($A26>0,F$21>0),($C$13/$A26)/F$21,0) | G26: =IF(AND($A26>0,G$21>0),($C$13/$A26)/G$21,0)
A27: 0.1 | B27: =IF(AND($A27>0,B$21>0),($C$13/$A27)/B$21,0) | C27: =IF(AND($A27>0,C$21>0),($C$13/$A27)/C$21,0) | D27: =IF(AND($A27>0,D$21>0),($C$13/$A27)/D$21,0) | E27: =IF(AND($A27>0,E$21>0),($C$13/$A27)/E$21,0) | F27: =IF(AND($A27>0,F$21>0),($C$13/$A27)/F$21,0) | G27: =IF(AND($A27>0,G$21>0),($C$13/$A27)/G$21,0)
A30: Grille contribution Premium (€ HT/mois) : coût par mission (lignes) × missions par mois (colonnes)
A31: Coût/mission \ Missions | B31: 30 | C31: 45 | D31: 60 | E31: 90 | F31: 120
A32: 0.08 | B32: =$C$6-$A32*B$31-$C$9-$C$10-$C$11-$C$12 | C32: =$C$6-$A32*C$31-$C$9-$C$10-$C$11-$C$12 | D32: =$C$6-$A32*D$31-$C$9-$C$10-$C$11-$C$12 | E32: =$C$6-$A32*E$31-$C$9-$C$10-$C$11-$C$12 | F32: =$C$6-$A32*F$31-$C$9-$C$10-$C$11-$C$12
A33: 0.12 | B33: =$C$6-$A33*B$31-$C$9-$C$10-$C$11-$C$12 | C33: =$C$6-$A33*C$31-$C$9-$C$10-$C$11-$C$12 | D33: =$C$6-$A33*D$31-$C$9-$C$10-$C$11-$C$12 | E33: =$C$6-$A33*E$31-$C$9-$C$10-$C$11-$C$12 | F33: =$C$6-$A33*F$31-$C$9-$C$10-$C$11-$C$12
A34: 0.18 | B34: =$C$6-$A34*B$31-$C$9-$C$10-$C$11-$C$12 | C34: =$C$6-$A34*C$31-$C$9-$C$10-$C$11-$C$12 | D34: =$C$6-$A34*D$31-$C$9-$C$10-$C$11-$C$12 | E34: =$C$6-$A34*E$31-$C$9-$C$10-$C$11-$C$12 | F34: =$C$6-$A34*F$31-$C$9-$C$10-$C$11-$C$12
A35: 0.25 | B35: =$C$6-$A35*B$31-$C$9-$C$10-$C$11-$C$12 | C35: =$C$6-$A35*C$31-$C$9-$C$10-$C$11-$C$12 | D35: =$C$6-$A35*D$31-$C$9-$C$10-$C$11-$C$12 | E35: =$C$6-$A35*E$31-$C$9-$C$10-$C$11-$C$12 | F35: =$C$6-$A35*F$31-$C$9-$C$10-$C$11-$C$12
A36: 0.35 | B36: =$C$6-$A36*B$31-$C$9-$C$10-$C$11-$C$12 | C36: =$C$6-$A36*C$31-$C$9-$C$10-$C$11-$C$12 | D36: =$C$6-$A36*D$31-$C$9-$C$10-$C$11-$C$12 | E36: =$C$6-$A36*E$31-$C$9-$C$10-$C$11-$C$12 | F36: =$C$6-$A36*F$31-$C$9-$C$10-$C$11-$C$12
A37: 0.5 | B37: =$C$6-$A37*B$31-$C$9-$C$10-$C$11-$C$12 | C37: =$C$6-$A37*C$31-$C$9-$C$10-$C$11-$C$12 | D37: =$C$6-$A37*D$31-$C$9-$C$10-$C$11-$C$12 | E37: =$C$6-$A37*E$31-$C$9-$C$10-$C$11-$C$12 | F37: =$C$6-$A37*F$31-$C$9-$C$10-$C$11-$C$12

Sheet Modèle Prudent
A1: Modèle Prudent (36 mois)
A2: Flux en € HT sauf mention TTC. Formules vivantes ; ne saisir que dans l'onglet Hypothèses et la ligne de chocs ci-dessous.
A3: Chocs de sensibilité (1 = aucun ; retard en mois) | C3: Prix × | D3: Churn × | E3: CAC × | F3: Coût IA × | G3: Coûts fixes × | H3: Retard lancement (mois)
C4: 1 | D4: 1 | E4: 1 | F4: 1 | G4: 1 | H4: 0
A5: Mois de lancement effectif | B5: =Hypothèses!$C$10+$H$4
A6: Ligne | B6: Unité | C6: M1 | D6: M2 | E6: M3 | F6: M4 | G6: M5 | H6: M6 | I6: M7 | J6: M8 | K6: M9 | L6: M10 | M6: M11 | N6: M12 | O6: M13 | P6: M14 | Q6: M15 | R6: M16 | S6: M17 | T6: M18 | U6: M19 | V6: M20 | W6: M21 | X6: M22 | Y6: M23 | Z6: M24 | AA6: M25 | AB6: M26 | AC6: M27 | AD6: M28 | AE6: M29 | AF6: M30 | AG6: M31 | AH6: M32 | AI6: M33 | AJ6: M34 | AK6: M35 | AL6: M36 | AN6: Année 1 | AO6: Année 2 | AP6: Année 3
A7: Mois | B7: n° | C7: 1 | D7: 2 | E7: 3 | F7: 4 | G7: 5 | H7: 6 | I7: 7 | J7: 8 | K7: 9 | L7: 10 | M7: 11 | N7: 12 | O7: 13 | P7: 14 | Q7: 15 | R7: 16 | S7: 17 | T7: 18 | U7: 19 | V7: 20 | W7: 21 | X7: 22 | Y7: 23 | Z7: 24 | AA7: 25 | AB7: 26 | AC7: 27 | AD7: 28 | AE7: 29 | AF7: 30 | AG7: 31 | AH7: 32 | AI7: 33 | AJ7: 34 | AK7: 35 | AL7: 36
A8: Date | C8: =EDATE(Hypothèses!$C$7,C7-1) | D8: =EDATE(Hypothèses!$C$7,D7-1) | E8: =EDATE(Hypothèses!$C$7,E7-1) | F8: =EDATE(Hypothèses!$C$7,F7-1) | G8: =EDATE(Hypothèses!$C$7,G7-1) | H8: =EDATE(Hypothèses!$C$7,H7-1) | I8: =EDATE(Hypothèses!$C$7,I7-1) | J8: =EDATE(Hypothèses!$C$7,J7-1) | ... AL8: =EDATE(Hypothèses!$C$7,AL7-1)
A9: Lancé ? (1 = oui) | B9: 0/1 | C9: =IF(C7>=$B$5,1,0) | D9: =IF(D7>=$B$5,1,0) | E9: =IF(E7>=$B$5,1,0) | F9: =IF(F7>=$B$5,1,0) | G9: =IF(G7>=$B$5,1,0) | H9: =IF(H7>=$B$5,1,0) | I9: =IF(I7>=$B$5,1,0) | J9: =IF(J7>=$B$5,1,0) | ... AL9: =IF(AL7>=$B$5,1,0)
A10: Pilote en cours ? (1 = oui) | B10: 0/1 | C10: =IF(AND(C7>=Hypothèses!$C$8,C7<$B$5),1,0) | D10: =IF(AND(D7>=Hypothèses!$C$8,D7<$B$5),1,0) | E10: =IF(AND(E7>=Hypothèses!$C$8,E7<$B$5),1,0) | F10: =IF(AND(F7>=Hypothèses!$C$8,F7<$B$5),1,0) | G10: =IF(AND(G7>=Hypothèses!$C$8,G7<$B$5),1,0) | H10: =IF(AND(H7>=Hypothèses!$C$8,H7<$B$5),1,0) | I10: =IF(AND(I7>=Hypothèses!$C$8,I7<$B$5),1,0) | J10: =IF(AND(J7>=Hypothèses!$C$8,J7<$B$5),1,0) | ... AL10: =IF(AND(AL7>=Hypothèses!$C$8,AL7<$B$5),1,0)
A11: Budget d'acquisition du mois | B11: € HT | C11: =IF(C9=1,IF(C7<=12,Hypothèses!$C$20,IF(C7<=24,Hypothèses!$C$21,Hypothèses!$C$22)),0) | D11: =IF(D9=1,IF(D7<=12,Hypothèses!$C$20,IF(D7<=24,Hypothèses!$C$21,Hypothèses!$C$22)),0) | E11: =IF(E9=1,IF(E7<=12,Hypothèses!$C$20,IF(E7<=24,Hypothèses!$C$21,Hypothèses!$C$22)),0) | F11: =IF(F9=1,IF(F7<=12,Hypothèses!$C$20,IF(F7<=24,Hypothèses!$C$21,Hypothèses!$C$22)),0) | G11: =IF(G9=1,IF(G7<=12,Hypothèses!$C$20,IF(G7<=24,Hypothèses!$C$21,Hypothèses!$C$22)),0) | H11: =IF(H9=1,IF(H7<=12,Hypothèses!$C$20,IF(H7<=24,Hypothèses!$C$21,Hypothèses!$C$22)),0) | I11: =IF(I9=1,IF(I7<=12,Hypothèses!$C$20,IF(I7<=24,Hypothèses!$C$21,Hypothèses!$C$22)),0) | J11: =IF(J9=1,IF(J7<=12,Hypothèses!$C$20,IF(J7<=24,Hypothèses!$C$21,Hypothèses!$C$22)),0) | ... AL11: =IF(AL9=1,IF(AL7<=12,Hypothèses!$C$20,IF(AL7<=24,Hypothèses!$C$21,Hypothèses!$C$22)),0) | AN11: =SUM(C11:N11) | AO11: =SUM(O11:Z11) | AP11: =SUM(AA11:AL11)
A12: Abonnés
A13: Abonnés en début de mois | B13: abonnés | C13: =0 | D13: =C18 | E13: =D18 | F13: =E18 | G13: =F18 | H13: =G18 | I13: =H18 | J13: =I18 | K13: =J18 | ... AL13: =AK18
A14: Nouveaux abonnés par acquisition payante | B14: abonnés | C14: =C11/(Hypothèses!$C$23*$E$4) | D14: =D11/(Hypothèses!$C$23*$E$4) | E14: =E11/(Hypothèses!$C$23*$E$4) | F14: =F11/(Hypothèses!$C$23*$E$4) | G14: =G11/(Hypothèses!$C$23*$E$4) | H14: =H11/(Hypothèses!$C$23*$E$4) | I14: =I11/(Hypothèses!$C$23*$E$4) | J14: =J11/(Hypothèses!$C$23*$E$4) | ... AL14: =AL11/(Hypothèses!$C$23*$E$4) | AN14: =SUM(C14:N14) | AO14: =SUM(O14:Z14) | AP14: =SUM(AA14:AL14)
A15: Nouveaux abonnés pilote | B15: abonnés | C15: =IF(C7=Hypothèses!$C$8,Hypothèses!$C$9,0) | D15: =IF(D7=Hypothèses!$C$8,Hypothèses!$C$9,0) | E15: =IF(E7=Hypothèses!$C$8,Hypothèses!$C$9,0) | F15: =IF(F7=Hypothèses!$C$8,Hypothèses!$C$9,0) | G15: =IF(G7=Hypothèses!$C$8,Hypothèses!$C$9,0) | H15: =IF(H7=Hypothèses!$C$8,Hypothèses!$C$9,0) | I15: =IF(I7=Hypothèses!$C$8,Hypothèses!$C$9,0) | J15: =IF(J7=Hypothèses!$C$8,Hypothèses!$C$9,0) | ... AL15: =IF(AL7=Hypothèses!$C$8,Hypothèses!$C$9,0) | AN15: =SUM(C15:N15) | AO15: =SUM(O15:Z15) | AP15: =SUM(AA15:AL15)
A16: Nouveaux abonnés organiques (parrainage) | B16: abonnés | C16: =C9*C13*Hypothèses!$C$24 | D16: =D9*D13*Hypothèses!$C$24 | E16: =E9*E13*Hypothèses!$C$24 | F16: =F9*F13*Hypothèses!$C$24 | G16: =G9*G13*Hypothèses!$C$24 | H16: =H9*H13*Hypothèses!$C$24 | I16: =I9*I13*Hypothèses!$C$24 | J16: =J9*J13*Hypothèses!$C$24 | ... AL16: =AL9*AL13*Hypothèses!$C$24 | AN16: =SUM(C16:N16) | AO16: =SUM(O16:Z16) | AP16: =SUM(AA16:AL16)
A17: Résiliations | B17: abonnés | C17: =C13*Hypothèses!$C$26*$D$4 | D17: =D13*Hypothèses!$C$26*$D$4 | E17: =E13*Hypothèses!$C$26*$D$4 | F17: =F13*Hypothèses!$C$26*$D$4 | G17: =G13*Hypothèses!$C$26*$D$4 | H17: =H13*Hypothèses!$C$26*$D$4 | I17: =I13*Hypothèses!$C$26*$D$4 | J17: =J13*Hypothèses!$C$26*$D$4 | ... AL17: =AL13*Hypothèses!$C$26*$D$4 | AN17: =SUM(C17:N17) | AO17: =SUM(O17:Z17) | AP17: =SUM(AA17:AL17)
A18: Abonnés en fin de mois | B18: abonnés | C18: =C13+C14+C15+C16-C17 | D18: =D13+D14+D15+D16-D17 | E18: =E13+E14+E15+E16-E17 | F18: =F13+F14+F15+F16-F17 | G18: =G13+G14+G15+G16-G17 | H18: =H13+H14+H15+H16-H17 | I18: =I13+I14+I15+I16-I17 | J18: =J13+J14+J15+J16-J17 | ... AL18: =AL13+AL14+AL15+AL16-AL17 | AN18: =N18 | AO18: =Z18 | AP18: =AL18
A19: dont Personal | B19: abonnés | C19: =C18*Hypothèses!$C$16 | D19: =D18*Hypothèses!$C$16 | E19: =E18*Hypothèses!$C$16 | F19: =F18*Hypothèses!$C$16 | G19: =G18*Hypothèses!$C$16 | H19: =H18*Hypothèses!$C$16 | I19: =I18*Hypothèses!$C$16 | J19: =J18*Hypothèses!$C$16 | ... AL19: =AL18*Hypothèses!$C$16 | AN19: =N19 | AO19: =Z19 | AP19: =AL19
A20: dont Premium | B20: abonnés | C20: =C18*Hypothèses!$C$17 | D20: =D18*Hypothèses!$C$17 | E20: =E18*Hypothèses!$C$17 | F20: =F18*Hypothèses!$C$17 | G20: =G18*Hypothèses!$C$17 | H20: =H18*Hypothèses!$C$17 | I20: =I18*Hypothèses!$C$17 | J20: =J18*Hypothèses!$C$17 | ... AL20: =AL18*Hypothèses!$C$17 | AN20: =N20 | AO20: =Z20 | AP20: =AL20
A21: dont Family | B21: abonnés | C21: =C18*Hypothèses!$C$18 | D21: =D18*Hypothèses!$C$18 | E21: =E18*Hypothèses!$C$18 | F21: =F18*Hypothèses!$C$18 | G21: =G18*Hypothèses!$C$18 | H21: =H18*Hypothèses!$C$18 | I21: =I18*Hypothèses!$C$18 | J21: =J18*Hypothèses!$C$18 | ... AL21: =AL18*Hypothèses!$C$18 | AN21: =N21 | AO21: =Z21 | AP21: =AL21
A22: Revenus
A23: Facturation Personal TTC | B23: € TTC | C23: =C19*Hypothèses!$C$12*$C$4 | D23: =D19*Hypothèses!$C$12*$C$4 | E23: =E19*Hypothèses!$C$12*$C$4 | F23: =F19*Hypothèses!$C$12*$C$4 | G23: =G19*Hypothèses!$C$12*$C$4 | H23: =H19*Hypothèses!$C$12*$C$4 | I23: =I19*Hypothèses!$C$12*$C$4 | J23: =J19*Hypothèses!$C$12*$C$4 | ... AL23: =AL19*Hypothèses!$C$12*$C$4 | AN23: =SUM(C23:N23) | AO23: =SUM(O23:Z23) | AP23: =SUM(AA23:AL23)
A24: Facturation Premium TTC | B24: € TTC | C24: =C20*Hypothèses!$C$13*$C$4 | D24: =D20*Hypothèses!$C$13*$C$4 | E24: =E20*Hypothèses!$C$13*$C$4 | F24: =F20*Hypothèses!$C$13*$C$4 | G24: =G20*Hypothèses!$C$13*$C$4 | H24: =H20*Hypothèses!$C$13*$C$4 | I24: =I20*Hypothèses!$C$13*$C$4 | J24: =J20*Hypothèses!$C$13*$C$4 | ... AL24: =AL20*Hypothèses!$C$13*$C$4 | AN24: =SUM(C24:N24) | AO24: =SUM(O24:Z24) | AP24: =SUM(AA24:AL24)
A25: Facturation Family TTC | B25: € TTC | C25: =C21*Hypothèses!$C$14*$C$4 | D25: =D21*Hypothèses!$C$14*$C$4 | E25: =E21*Hypothèses!$C$14*$C$4 | F25: =F21*Hypothèses!$C$14*$C$4 | G25: =G21*Hypothèses!$C$14*$C$4 | H25: =H21*Hypothèses!$C$14*$C$4 | I25: =I21*Hypothèses!$C$14*$C$4 | J25: =J21*Hypothèses!$C$14*$C$4 | ... AL25: =AL21*Hypothèses!$C$14*$C$4 | AN25: =SUM(C25:N25) | AO25: =SUM(O25:Z25) | AP25: =SUM(AA25:AL25)
A26: Facturation totale TTC (MRR TTC) | B26: € TTC | C26: =C23+C24+C25 | D26: =D23+D24+D25 | E26: =E23+E24+E25 | F26: =F23+F24+F25 | G26: =G23+G24+G25 | H26: =H23+H24+H25 | I26: =I23+I24+I25 | J26: =J23+J24+J25 | ... AL26: =AL23+AL24+AL25 | AN26: =SUM(C26:N26) | AO26: =SUM(O26:Z26) | AP26: =SUM(AA26:AL26)
A27: TVA collectée | B27: € | C27: =C26*Hypothèses!$C$15/(1+Hypothèses!$C$15) | D27: =D26*Hypothèses!$C$15/(1+Hypothèses!$C$15) | E27: =E26*Hypothèses!$C$15/(1+Hypothèses!$C$15) | F27: =F26*Hypothèses!$C$15/(1+Hypothèses!$C$15) | G27: =G26*Hypothèses!$C$15/(1+Hypothèses!$C$15) | H27: =H26*Hypothèses!$C$15/(1+Hypothèses!$C$15) | I27: =I26*Hypothèses!$C$15/(1+Hypothèses!$C$15) | J27: =J26*Hypothèses!$C$15/(1+Hypothèses!$C$15) | ... AL27: =AL26*Hypothèses!$C$15/(1+Hypothèses!$C$15) | AN27: =SUM(C27:N27) | AO27: =SUM(O27:Z27) | AP27: =SUM(AA27:AL27)
A28: Chiffre d'affaires HT | B28: € HT | C28: =C26-C27 | D28: =D26-D27 | E28: =E26-E27 | F28: =F26-F27 | G28: =G26-G27 | H28: =H26-H27 | I28: =I26-I27 | J28: =J26-J27 | ... AL28: =AL26-AL27 | AN28: =SUM(C28:N28) | AO28: =SUM(O28:Z28) | AP28: =SUM(AA28:AL28)
A29: Impayés (TTC) | B29: € TTC | C29: =C26*Hypothèses!$C$27 | D29: =D26*Hypothèses!$C$27 | E29: =E26*Hypothèses!$C$27 | F29: =F26*Hypothèses!$C$27 | G29: =G26*Hypothèses!$C$27 | H29: =H26*Hypothèses!$C$27 | I29: =I26*Hypothèses!$C$27 | J29: =J26*Hypothèses!$C$27 | ... AL29: =AL26*Hypothèses!$C$27 | AN29: =SUM(C29:N29) | AO29: =SUM(O29:Z29) | AP29: =SUM(AA29:AL29)
A30: Frais de paiement | B30: € | C30: =(C26-C29)*Hypothèses!$C$28+C18*Hypothèses!$C$29 | D30: =(D26-D29)*Hypothèses!$C$28+D18*Hypothèses!$C$29 | E30: =(E26-E29)*Hypothèses!$C$28+E18*Hypothèses!$C$29 | F30: =(F26-F29)*Hypothèses!$C$28+F18*Hypothèses!$C$29 | G30: =(G26-G29)*Hypothèses!$C$28+G18*Hypothèses!$C$29 | H30: =(H26-H29)*Hypothèses!$C$28+H18*Hypothèses!$C$29 | I30: =(I26-I29)*Hypothèses!$C$28+I18*Hypothèses!$C$29 | J30: =(J26-J29)*Hypothèses!$C$28+J18*Hypothèses!$C$29 | ... AL30: =(AL26-AL29)*Hypothèses!$C$28+AL18*Hypothèses!$C$29 | AN30: =SUM(C30:N30) | AO30: =SUM(O30:Z30) | AP30: =SUM(AA30:AL30)
A31: Encaissements nets TTC | B31: € TTC | C31: =C26-C29-C30 | D31: =D26-D29-D30 | E31: =E26-E29-E30 | F31: =F26-F29-F30 | G31: =G26-G29-G30 | H31: =H26-H29-H30 | I31: =I26-I29-I30 | J31: =J26-J29-J30 | ... AL31: =AL26-AL29-AL30 | AN31: =SUM(C31:N31) | AO31: =SUM(O31:Z31) | AP31: =SUM(AA31:AL31)
A32: Coûts variables
A33: Coût IA et outils (missions × coût par mission) | B33: € HT | C33: =(C19*Hypothèses!$C$31+C20*Hypothèses!$C$32+C21*Hypothèses!$C$33)*Hypothèses!$C$34*$F$4 | D33: =(D19*Hypothèses!$C$31+D20*Hypothèses!$C$32+D21*Hypothèses!$C$33)*Hypothèses!$C$34*$F$4 | E33: =(E19*Hypothèses!$C$31+E20*Hypothèses!$C$32+E21*Hypothèses!$C$33)*Hypothèses!$C$34*$F$4 | F33: =(F19*Hypothèses!$C$31+F20*Hypothèses!$C$32+F21*Hypothèses!$C$33)*Hypothèses!$C$34*$F$4 | G33: =(G19*Hypothèses!$C$31+G20*Hypothèses!$C$32+G21*Hypothèses!$C$33)*Hypothèses!$C$34*$F$4 | H33: =(H19*Hypothèses!$C$31+H20*Hypothèses!$C$32+H21*Hypothèses!$C$33)*Hypothèses!$C$34*$F$4 | I33: =(I19*Hypothèses!$C$31+I20*Hypothèses!$C$32+I21*Hypothèses!$C$33)*Hypothèses!$C$34*$F$4 | J33: =(J19*Hypothèses!$C$31+J20*Hypothèses!$C$32+J21*Hypothèses!$C$33)*Hypothèses!$C$34*$F$4 | ... AL33: =(AL19*Hypothèses!$C$31+AL20*Hypothèses!$C$32+AL21*Hypothèses!$C$33)*Hypothèses!$C$34*$F$4 | AN33: =SUM(C33:N33) | AO33: =SUM(O33:Z33) | AP33: =SUM(AA33:AL33)
A34: Hébergement, stockage, connecteurs | B34: € HT | C34: =C18*Hypothèses!$C$35 | D34: =D18*Hypothèses!$C$35 | E34: =E18*Hypothèses!$C$35 | F34: =F18*Hypothèses!$C$35 | G34: =G18*Hypothèses!$C$35 | H34: =H18*Hypothèses!$C$35 | I34: =I18*Hypothèses!$C$35 | J34: =J18*Hypothèses!$C$35 | ... AL34: =AL18*Hypothèses!$C$35 | AN34: =SUM(C34:N34) | AO34: =SUM(O34:Z34) | AP34: =SUM(AA34:AL34)
A35: Support humain | B35: € HT | C35: =C18*Hypothèses!$C$36 | D35: =D18*Hypothèses!$C$36 | E35: =E18*Hypothèses!$C$36 | F35: =F18*Hypothèses!$C$36 | G35: =G18*Hypothèses!$C$36 | H35: =H18*Hypothèses!$C$36 | I35: =I18*Hypothèses!$C$36 | J35: =J18*Hypothèses!$C$36 | ... AL35: =AL18*Hypothèses!$C$36 | AN35: =SUM(C35:N35) | AO35: =SUM(O35:Z35) | AP35: =SUM(AA35:AL35)
A36: Total coûts variables | B36: € HT | C36: =C33+C34+C35 | D36: =D33+D34+D35 | E36: =E33+E34+E35 | F36: =F33+F34+F35 | G36: =G33+G34+G35 | H36: =H33+H34+H35 | I36: =I33+I34+I35 | J36: =J33+J34+J35 | ... AL36: =AL33+AL34+AL35 | AN36: =SUM(C36:N36) | AO36: =SUM(O36:Z36) | AP36: =SUM(AA36:AL36)
A37: Marge sur coûts variables (CA HT − variables − frais − impayés HT) | B37: € HT | C37: =C28-C36-C30-C29/(1+Hypothèses!$C$15) | D37: =D28-D36-D30-D29/(1+Hypothèses!$C$15) | E37: =E28-E36-E30-E29/(1+Hypothèses!$C$15) | F37: =F28-F36-F30-F29/(1+Hypothèses!$C$15) | G37: =G28-G36-G30-G29/(1+Hypothèses!$C$15) | H37: =H28-H36-H30-H29/(1+Hypothèses!$C$15) | I37: =I28-I36-I30-I29/(1+Hypothèses!$C$15) | J37: =J28-J36-J30-J29/(1+Hypothèses!$C$15) | ... AL37: =AL28-AL36-AL30-AL29/(1+Hypothèses!$C$15) | AN37: =SUM(C37:N37) | AO37: =SUM(O37:Z37) | AP37: =SUM(AA37:AL37)
A38: Acquisition et coûts fixes
A39: Dépenses d'acquisition | B39: € HT | C39: =C11 | D39: =D11 | E39: =E11 | F39: =F11 | G39: =G11 | H39: =H11 | I39: =I11 | J39: =J11 | ... AL39: =AL11 | AN39: =SUM(C39:N39) | AO39: =SUM(O39:Z39) | AP39: =SUM(AA39:AL39)
A40: Rémunération des fondateurs | B40: € HT | C40: =IF(C7>=Hypothèses!$C$39,Hypothèses!$C$38*Hypothèses!$C$40,0)*$G$4 | D40: =IF(D7>=Hypothèses!$C$39,Hypothèses!$C$38*Hypothèses!$C$40,0)*$G$4 | E40: =IF(E7>=Hypothèses!$C$39,Hypothèses!$C$38*Hypothèses!$C$40,0)*$G$4 | F40: =IF(F7>=Hypothèses!$C$39,Hypothèses!$C$38*Hypothèses!$C$40,0)*$G$4 | G40: =IF(G7>=Hypothèses!$C$39,Hypothèses!$C$38*Hypothèses!$C$40,0)*$G$4 | H40: =IF(H7>=Hypothèses!$C$39,Hypothèses!$C$38*Hypothèses!$C$40,0)*$G$4 | I40: =IF(I7>=Hypothèses!$C$39,Hypothèses!$C$38*Hypothèses!$C$40,0)*$G$4 | J40: =IF(J7>=Hypothèses!$C$39,Hypothèses!$C$38*Hypothèses!$C$40,0)*$G$4 | ... AL40: =IF(AL7>=Hypothèses!$C$39,Hypothèses!$C$38*Hypothèses!$C$40,0)*$G$4 | AN40: =SUM(C40:N40) | AO40: =SUM(O40:Z40) | AP40: =SUM(AA40:AL40)
A41: Salarié 1 (growth / customer success) | B41: € HT | C41: =IF(C7>=Hypothèses!$C$41,Hypothèses!$C$42,0)*$G$4 | D41: =IF(D7>=Hypothèses!$C$41,Hypothèses!$C$42,0)*$G$4 | E41: =IF(E7>=Hypothèses!$C$41,Hypothèses!$C$42,0)*$G$4 | F41: =IF(F7>=Hypothèses!$C$41,Hypothèses!$C$42,0)*$G$4 | G41: =IF(G7>=Hypothèses!$C$41,Hypothèses!$C$42,0)*$G$4 | H41: =IF(H7>=Hypothèses!$C$41,Hypothèses!$C$42,0)*$G$4 | I41: =IF(I7>=Hypothèses!$C$41,Hypothèses!$C$42,0)*$G$4 | J41: =IF(J7>=Hypothèses!$C$41,Hypothèses!$C$42,0)*$G$4 | ... AL41: =IF(AL7>=Hypothèses!$C$41,Hypothèses!$C$42,0)*$G$4 | AN41: =SUM(C41:N41) | AO41: =SUM(O41:Z41) | AP41: =SUM(AA41:AL41)
A42: Salarié 2 (ingénieur) | B42: € HT | C42: =IF(C7>=Hypothèses!$C$43,Hypothèses!$C$44,0)*$G$4 | D42: =IF(D7>=Hypothèses!$C$43,Hypothèses!$C$44,0)*$G$4 | E42: =IF(E7>=Hypothèses!$C$43,Hypothèses!$C$44,0)*$G$4 | F42: =IF(F7>=Hypothèses!$C$43,Hypothèses!$C$44,0)*$G$4 | G42: =IF(G7>=Hypothèses!$C$43,Hypothèses!$C$44,0)*$G$4 | H42: =IF(H7>=Hypothèses!$C$43,Hypothèses!$C$44,0)*$G$4 | I42: =IF(I7>=Hypothèses!$C$43,Hypothèses!$C$44,0)*$G$4 | J42: =IF(J7>=Hypothèses!$C$43,Hypothèses!$C$44,0)*$G$4 | ... AL42: =IF(AL7>=Hypothèses!$C$43,Hypothèses!$C$44,0)*$G$4 | AN42: =SUM(C42:N42) | AO42: =SUM(O42:Z42) | AP42: =SUM(AA42:AL42)
A43: Développement MVP externe (étalé jusqu'au lancement) | B43: € HT | C43: =IF(C7<$B$5,Hypothèses!$C$45/MAX(1,$B$5-1),0) | D43: =IF(D7<$B$5,Hypothèses!$C$45/MAX(1,$B$5-1),0) | E43: =IF(E7<$B$5,Hypothèses!$C$45/MAX(1,$B$5-1),0) | F43: =IF(F7<$B$5,Hypothèses!$C$45/MAX(1,$B$5-1),0) | G43: =IF(G7<$B$5,Hypothèses!$C$45/MAX(1,$B$5-1),0) | H43: =IF(H7<$B$5,Hypothèses!$C$45/MAX(1,$B$5-1),0) | I43: =IF(I7<$B$5,Hypothèses!$C$45/MAX(1,$B$5-1),0) | J43: =IF(J7<$B$5,Hypothèses!$C$45/MAX(1,$B$5-1),0) | ... AL43: =IF(AL7<$B$5,Hypothèses!$C$45/MAX(1,$B$5-1),0) | AN43: =SUM(C43:N43) | AO43: =SUM(O43:Z43) | AP43: =SUM(AA43:AL43)
A44: Outils et SaaS | B44: € HT | C44: =Hypothèses!$C$46*$G$4 | D44: =Hypothèses!$C$46*$G$4 | E44: =Hypothèses!$C$46*$G$4 | F44: =Hypothèses!$C$46*$G$4 | G44: =Hypothèses!$C$46*$G$4 | H44: =Hypothèses!$C$46*$G$4 | I44: =Hypothèses!$C$46*$G$4 | J44: =Hypothèses!$C$46*$G$4 | ... AL44: =Hypothèses!$C$46*$G$4 | AN44: =SUM(C44:N44) | AO44: =SUM(O44:Z44) | AP44: =SUM(AA44:AL44)
A45: Juridique et comptabilité | B45: € HT | C45: =Hypothèses!$C$47*$G$4 | D45: =Hypothèses!$C$47*$G$4 | E45: =Hypothèses!$C$47*$G$4 | F45: =Hypothèses!$C$47*$G$4 | G45: =Hypothèses!$C$47*$G$4 | H45: =Hypothèses!$C$47*$G$4 | I45: =Hypothèses!$C$47*$G$4 | J45: =Hypothèses!$C$47*$G$4 | ... AL45: =Hypothèses!$C$47*$G$4 | AN45: =SUM(C45:N45) | AO45: =SUM(O45:Z45) | AP45: =SUM(AA45:AL45)
A46: Assurance RC pro | B46: € | C46: =C9*Hypothèses!$C$48*$G$4 | D46: =D9*Hypothèses!$C$48*$G$4 | E46: =E9*Hypothèses!$C$48*$G$4 | F46: =F9*Hypothèses!$C$48*$G$4 | G46: =G9*Hypothèses!$C$48*$G$4 | H46: =H9*Hypothèses!$C$48*$G$4 | I46: =I9*Hypothèses!$C$48*$G$4 | J46: =J9*Hypothèses!$C$48*$G$4 | ... AL46: =AL9*Hypothèses!$C$48*$G$4 | AN46: =SUM(C46:N46) | AO46: =SUM(O46:Z46) | AP46: =SUM(AA46:AL46)
A47: Marketing fixe | B47: € HT | C47: =C9*Hypothèses!$C$49*$G$4 | D47: =D9*Hypothèses!$C$49*$G$4 | E47: =E9*Hypothèses!$C$49*$G$4 | F47: =F9*Hypothèses!$C$49*$G$4 | G47: =G9*Hypothèses!$C$49*$G$4 | H47: =H9*Hypothèses!$C$49*$G$4 | I47: =I9*Hypothèses!$C$49*$G$4 | J47: =J9*Hypothèses!$C$49*$G$4 | ... AL47: =AL9*Hypothèses!$C$49*$G$4 | AN47: =SUM(C47:N47) | AO47: =SUM(O47:Z47) | AP47: =SUM(AA47:AL47)
A48: Frais généraux | B48: € HT | C48: =Hypothèses!$C$50*$G$4 | D48: =Hypothèses!$C$50*$G$4 | E48: =Hypothèses!$C$50*$G$4 | F48: =Hypothèses!$C$50*$G$4 | G48: =Hypothèses!$C$50*$G$4 | H48: =Hypothèses!$C$50*$G$4 | I48: =Hypothèses!$C$50*$G$4 | J48: =Hypothèses!$C$50*$G$4 | ... AL48: =Hypothèses!$C$50*$G$4 | AN48: =SUM(C48:N48) | AO48: =SUM(O48:Z48) | AP48: =SUM(AA48:AL48)
A49: Audit de sécurité (annuel, à partir du lancement) | B49: € HT | C49: =IF(AND(C9=1,MOD(C7-$B$5,12)=0),Hypothèses!$C$51,0)*$G$4 | D49: =IF(AND(D9=1,MOD(D7-$B$5,12)=0),Hypothèses!$C$51,0)*$G$4 | E49: =IF(AND(E9=1,MOD(E7-$B$5,12)=0),Hypothèses!$C$51,0)*$G$4 | F49: =IF(AND(F9=1,MOD(F7-$B$5,12)=0),Hypothèses!$C$51,0)*$G$4 | G49: =IF(AND(G9=1,MOD(G7-$B$5,12)=0),Hypothèses!$C$51,0)*$G$4 | H49: =IF(AND(H9=1,MOD(H7-$B$5,12)=0),Hypothèses!$C$51,0)*$G$4 | I49: =IF(AND(I9=1,MOD(I7-$B$5,12)=0),Hypothèses!$C$51,0)*$G$4 | J49: =IF(AND(J9=1,MOD(J7-$B$5,12)=0),Hypothèses!$C$51,0)*$G$4 | ... AL49: =IF(AND(AL9=1,MOD(AL7-$B$5,12)=0),Hypothèses!$C$51,0)*$G$4 | AN49: =SUM(C49:N49) | AO49: =SUM(O49:Z49) | AP49: =SUM(AA49:AL49)
A50: Frais de constitution | B50: € HT | C50: =IF(C7=2,Hypothèses!$C$52,0) | D50: =IF(D7=2,Hypothèses!$C$52,0) | E50: =IF(E7=2,Hypothèses!$C$52,0) | F50: =IF(F7=2,Hypothèses!$C$52,0) | G50: =IF(G7=2,Hypothèses!$C$52,0) | H50: =IF(H7=2,Hypothèses!$C$52,0) | I50: =IF(I7=2,Hypothèses!$C$52,0) | J50: =IF(J7=2,Hypothèses!$C$52,0) | ... AL50: =IF(AL7=2,Hypothèses!$C$52,0) | AN50: =SUM(C50:N50) | AO50: =SUM(O50:Z50) | AP50: =SUM(AA50:AL50)
A51: Total coûts fixes | B51: € HT | C51: =SUM(C40:C50) | D51: =SUM(D40:D50) | E51: =SUM(E40:E50) | F51: =SUM(F40:F50) | G51: =SUM(G40:G50) | H51: =SUM(H40:H50) | I51: =SUM(I40:I50) | J51: =SUM(J40:J50) | ... AL51: =SUM(AL40:AL50) | AN51: =SUM(C51:N51) | AO51: =SUM(O51:Z51) | AP51: =SUM(AA51:AL51)
A52: EBITDA (marge variable − acquisition − fixes) | B52: € HT | C52: =C37-C39-C51 | D52: =D37-D39-D51 | E52: =E37-E39-E51 | F52: =F37-F39-F51 | G52: =G37-G39-G51 | H52: =H37-H39-H51 | I52: =I37-I39-I51 | J52: =J37-J39-J51 | ... AL52: =AL37-AL39-AL51 | AN52: =SUM(C52:N52) | AO52: =SUM(O52:Z52) | AP52: =SUM(AA52:AL52)
A53: EBITDA positif ? (1 = oui) | B53: 0/1 | C53: =IF(C52>0,1,0) | D53: =IF(D52>0,1,0) | E53: =IF(E52>0,1,0) | F53: =IF(F52>0,1,0) | G53: =IF(G52>0,1,0) | H53: =IF(H52>0,1,0) | I53: =IF(I52>0,1,0) | J53: =IF(J52>0,1,0) | ... AL53: =IF(AL52>0,1,0)
A54: Trésorerie
A55: TVA collectée reversée (mois suivant) | B55: € | C55: =0 | D55: =C27 | E55: =D27 | F55: =E27 | G55: =F27 | H55: =G27 | I55: =H27 | J55: =I27 | K55: =J27 | ... AL55: =AK27 | AN55: =SUM(C55:N55) | AO55: =SUM(O55:Z55) | AP55: =SUM(AA55:AL55)
A56: TVA déductible récupérée (mois suivant, coûts externes) | B56: € | C56: =0 | D56: =(C36+C39+C43+C44+C45+C47+C48+C49+C50)*Hypothèses!$C$15 | E56: =(D36+D39+D43+D44+D45+D47+D48+D49+D50)*Hypothèses!$C$15 | F56: =(E36+E39+E43+E44+E45+E47+E48+E49+E50)*Hypothèses!$C$15 | G56: =(F36+F39+F43+F44+F45+F47+F48+F49+F50)*Hypothèses!$C$15 | H56: =(G36+G39+G43+G44+G45+G47+G48+G49+G50)*Hypothèses!$C$15 | I56: =(H36+H39+H43+H44+H45+H47+H48+H49+H50)*Hypothèses!$C$15 | J56: =(I36+I39+I43+I44+I45+I47+I48+I49+I50)*Hypothèses!$C$15 | K56: =(J36+J39+J43+J44+J45+J47+J48+J49+J50)*Hypothèses!$C$15 | ... AL56: =(AK36+AK39+AK43+AK44+AK45+AK47+AK48+AK49+AK50)*Hypothèses!$C$15 | AN56: =SUM(C56:N56) | AO56: =SUM(O56:Z56) | AP56: =SUM(AA56:AL56)
A57: Financement reçu | B57: € | C57: =Hypothèses!$C$56*(IF(C7=Hypothèses!$C$57,Hypothèses!$C$58,0)+IF(C7=Hypothèses!$C$59,Hypothèses!$C$60,0)+IF(C7=Hypothèses!$C$61,Hypothèses!$C$62,0)) | D57: =Hypothèses!$C$56*(IF(D7=Hypothèses!$C$57,Hypothèses!$C$58,0)+IF(D7=Hypothèses!$C$59,Hypothèses!$C$60,0)+IF(D7=Hypothèses!$C$61,Hypothèses!$C$62,0)) | E57: =Hypothèses!$C$56*(IF(E7=Hypothèses!$C$57,Hypothèses!$C$58,0)+IF(E7=Hypothèses!$C$59,Hypothèses!$C$60,0)+IF(E7=Hypothèses!$C$61,Hypothèses!$C$62,0)) | F57: =Hypothèses!$C$56*(IF(F7=Hypothèses!$C$57,Hypothèses!$C$58,0)+IF(F7=Hypothèses!$C$59,Hypothèses!$C$60,0)+IF(F7=Hypothèses!$C$61,Hypothèses!$C$62,0)) | G57: =Hypothèses!$C$56*(IF(G7=Hypothèses!$C$57,Hypothèses!$C$58,0)+IF(G7=Hypothèses!$C$59,Hypothèses!$C$60,0)+IF(G7=Hypothèses!$C$61,Hypothèses!$C$62,0)) | H57: =Hypothèses!$C$56*(IF(H7=Hypothèses!$C$57,Hypothèses!$C$58,0)+IF(H7=Hypothèses!$C$59,Hypothèses!$C$60,0)+IF(H7=Hypothèses!$C$61,Hypothèses!$C$62,0)) | I57: =Hypothèses!$C$56*(IF(I7=Hypothèses!$C$57,Hypothèses!$C$58,0)+IF(I7=Hypothèses!$C$59,Hypothèses!$C$60,0)+IF(I7=Hypothèses!$C$61,Hypothèses!$C$62,0)) | J57: =Hypothèses!$C$56*(IF(J7=Hypothèses!$C$57,Hypothèses!$C$58,0)+IF(J7=Hypothèses!$C$59,Hypothèses!$C$60,0)+IF(J7=Hypothèses!$C$61,Hypothèses!$C$62,0)) | ... AL57: =Hypothèses!$C$56*(IF(AL7=Hypothèses!$C$57,Hypothèses!$C$58,0)+IF(AL7=Hypothèses!$C$59,Hypothèses!$C$60,0)+IF(AL7=Hypothèses!$C$61,Hypothèses!$C$62,0)) | AN57: =SUM(C57:N57) | AO57: =SUM(O57:Z57) | AP57: =SUM(AA57:AL57)
A58: Trésorerie d'ouverture | B58: € | C58: =Hypothèses!$C$54 | D58: =C60 | E58: =D60 | F58: =E60 | G58: =F60 | H58: =G60 | I58: =H60 | J58: =I60 | K58: =J60 | ... AL58: =AK60
A59: Flux de trésorerie du mois | B59: € | C59: =C31-C36-C39-C51-C55+C56+C57 | D59: =D31-D36-D39-D51-D55+D56+D57 | E59: =E31-E36-E39-E51-E55+E56+E57 | F59: =F31-F36-F39-F51-F55+F56+F57 | G59: =G31-G36-G39-G51-G55+G56+G57 | H59: =H31-H36-H39-H51-H55+H56+H57 | I59: =I31-I36-I39-I51-I55+I56+I57 | J59: =J31-J36-J39-J51-J55+J56+J57 | ... AL59: =AL31-AL36-AL39-AL51-AL55+AL56+AL57 | AN59: =SUM(C59:N59) | AO59: =SUM(O59:Z59) | AP59: =SUM(AA59:AL59)
A60: Trésorerie de clôture | B60: € | C60: =C58+C59 | D60: =D58+D59 | E60: =E58+E59 | F60: =F58+F59 | G60: =G58+G59 | H60: =H58+H59 | I60: =I58+I59 | J60: =J58+J59 | ... AL60: =AL58+AL59 | AN60: =N60 | AO60: =Z60 | AP60: =AL60
A61: Financement cumulé | B61: € | C61: =0+C57 | D61: =C61+D57 | E61: =D61+E57 | F61: =E61+F57 | G61: =F61+G57 | H61: =G61+H57 | I61: =H61+I57 | J61: =I61+J57 | K61: =J61+K57 | ... AL61: =AK61+AL57 | AN61: =N61 | AO61: =Z61 | AP61: =AL61
A62: Trésorerie cumulée hors financement | B62: € | C62: =C60-C61 | D62: =D60-D61 | E62: =E60-E61 | F62: =F60-F61 | G62: =G60-G61 | H62: =H60-H61 | I62: =I60-I61 | J62: =J60-J61 | ... AL62: =AL60-AL61 | AN62: =N62 | AO62: =Z62 | AP62: =AL62
A63: Point bas glissant hors financement | B63: € | C63: =C62 | D63: =MIN(C63,D62) | E63: =MIN(D63,E62) | F63: =MIN(E63,F62) | G63: =MIN(F63,G62) | H63: =MIN(G63,H62) | I63: =MIN(H63,I62) | J63: =MIN(I63,J62) | K63: =MIN(J63,K62) | ... AL63: =MIN(AK63,AL62) | AN63: =N63 | AO63: =Z63 | AP63: =AL63
A64: Trésorerie cumulée hors financement positive après lancement ? (1 = oui) | B64: 0/1 | C64: =IF(AND(C9=1,C62>0),1,0) | D64: =IF(AND(D9=1,D62>0),1,0) | E64: =IF(AND(E9=1,E62>0),1,0) | F64: =IF(AND(F9=1,F62>0),1,0) | G64: =IF(AND(G9=1,G62>0),1,0) | H64: =IF(AND(H9=1,H62>0),1,0) | I64: =IF(AND(I9=1,I62>0),1,0) | J64: =IF(AND(J9=1,J62>0),1,0) | ... AL64: =IF(AND(AL9=1,AL62>0),1,0)
A65: Indicateurs
A66: ARR HT instantané (CA HT × 12) | B66: € HT | C66: =C28*12 | D66: =D28*12 | E66: =E28*12 | F66: =F28*12 | G66: =G28*12 | H66: =H28*12 | I66: =I28*12 | J66: =J28*12 | ... AL66: =AL28*12 | AN66: =N66 | AO66: =Z66 | AP66: =AL66
A67: ARPA HT (CA HT / abonnés) | B67: € HT | C67: =IF(C18>0,C28/C18,0) | D67: =IF(D18>0,D28/D18,0) | E67: =IF(E18>0,E28/E18,0) | F67: =IF(F18>0,F28/F18,0) | G67: =IF(G18>0,G28/G18,0) | H67: =IF(H18>0,H28/H18,0) | I67: =IF(I18>0,I28/I18,0) | J67: =IF(J18>0,J28/J18,0) | ... AL67: =IF(AL18>0,AL28/AL18,0) | AN67: =N67 | AO67: =Z67 | AP67: =AL67
A68: Coût variable par abonné | B68: € HT | C68: =IF(C18>0,C36/C18,0) | D68: =IF(D18>0,D36/D18,0) | E68: =IF(E18>0,E36/E18,0) | F68: =IF(F18>0,F36/F18,0) | G68: =IF(G18>0,G36/G18,0) | H68: =IF(H18>0,H36/H18,0) | I68: =IF(I18>0,I36/I18,0) | J68: =IF(J18>0,J36/J18,0) | ... AL68: =IF(AL18>0,AL36/AL18,0) | AN68: =N68 | AO68: =Z68 | AP68: =AL68
A69: Contribution par abonné | B69: € HT | C69: =IF(C18>0,C37/C18,0) | D69: =IF(D18>0,D37/D18,0) | E69: =IF(E18>0,E37/E18,0) | F69: =IF(F18>0,F37/F18,0) | G69: =IF(G18>0,G37/G18,0) | H69: =IF(H18>0,H37/H18,0) | I69: =IF(I18>0,I37/I18,0) | J69: =IF(J18>0,J37/J18,0) | ... AL69: =IF(AL18>0,AL37/AL18,0) | AN69: =N69 | AO69: =Z69 | AP69: =AL69
A70: Marge variable (% du CA HT) | B70: % | C70: =IF(C28>0,C37/C28,0) | D70: =IF(D28>0,D37/D28,0) | E70: =IF(E28>0,E37/E28,0) | F70: =IF(F28>0,F37/F28,0) | G70: =IF(G28>0,G37/G28,0) | H70: =IF(H28>0,H37/H28,0) | I70: =IF(I28>0,I37/I28,0) | J70: =IF(J28>0,J37/J28,0) | ... AL70: =IF(AL28>0,AL37/AL28,0) | AN70: =N70 | AO70: =Z70 | AP70: =AL70
A71: CAC effectif | B71: € | C71: =IF(C14>0,C39/C14,0) | D71: =IF(D14>0,D39/D14,0) | E71: =IF(E14>0,E39/E14,0) | F71: =IF(F14>0,F39/F14,0) | G71: =IF(G14>0,G39/G14,0) | H71: =IF(H14>0,H39/H14,0) | I71: =IF(I14>0,I39/I14,0) | J71: =IF(J14>0,J39/J14,0) | ... AL71: =IF(AL14>0,AL39/AL14,0) | AN71: =N71 | AO71: =Z71 | AP71: =AL71
A72: Payback du CAC (mois) | B72: mois | C72: =IF(C69>0,Hypothèses!$C$23*$E$4/C69,0) | D72: =IF(D69>0,Hypothèses!$C$23*$E$4/D69,0) | E72: =IF(E69>0,Hypothèses!$C$23*$E$4/E69,0) | F72: =IF(F69>0,Hypothèses!$C$23*$E$4/F69,0) | G72: =IF(G69>0,Hypothèses!$C$23*$E$4/G69,0) | H72: =IF(H69>0,Hypothèses!$C$23*$E$4/H69,0) | I72: =IF(I69>0,Hypothèses!$C$23*$E$4/I69,0) | J72: =IF(J69>0,Hypothèses!$C$23*$E$4/J69,0) | ... AL72: =IF(AL69>0,Hypothèses!$C$23*$E$4/AL69,0) | AN72: =N72 | AO72: =Z72 | AP72: =AL72
A73: LTV contributive simplifiée (contribution / churn) | B73: € HT | C73: =IF(Hypothèses!$C$26*$D$4>0,C69/(Hypothèses!$C$26*$D$4),0) | D73: =IF(Hypothèses!$C$26*$D$4>0,D69/(Hypothèses!$C$26*$D$4),0) | E73: =IF(Hypothèses!$C$26*$D$4>0,E69/(Hypothèses!$C$26*$D$4),0) | F73: =IF(Hypothèses!$C$26*$D$4>0,F69/(Hypothèses!$C$26*$D$4),0) | G73: =IF(Hypothèses!$C$26*$D$4>0,G69/(Hypothèses!$C$26*$D$4),0) | H73: =IF(Hypothèses!$C$26*$D$4>0,H69/(Hypothèses!$C$26*$D$4),0) | I73: =IF(Hypothèses!$C$26*$D$4>0,I69/(Hypothèses!$C$26*$D$4),0) | J73: =IF(Hypothèses!$C$26*$D$4>0,J69/(Hypothèses!$C$26*$D$4),0) | ... AL73: =IF(Hypothèses!$C$26*$D$4>0,AL69/(Hypothèses!$C$26*$D$4),0) | AN73: =N73 | AO73: =Z73 | AP73: =AL73
A74: LTV / CAC | B74: x | C74: =IF(Hypothèses!$C$23*$E$4>0,C73/(Hypothèses!$C$23*$E$4),0) | D74: =IF(Hypothèses!$C$23*$E$4>0,D73/(Hypothèses!$C$23*$E$4),0) | E74: =IF(Hypothèses!$C$23*$E$4>0,E73/(Hypothèses!$C$23*$E$4),0) | F74: =IF(Hypothèses!$C$23*$E$4>0,F73/(Hypothèses!$C$23*$E$4),0) | G74: =IF(Hypothèses!$C$23*$E$4>0,G73/(Hypothèses!$C$23*$E$4),0) | H74: =IF(Hypothèses!$C$23*$E$4>0,H73/(Hypothèses!$C$23*$E$4),0) | I74: =IF(Hypothèses!$C$23*$E$4>0,I73/(Hypothèses!$C$23*$E$4),0) | J74: =IF(Hypothèses!$C$23*$E$4>0,J73/(Hypothèses!$C$23*$E$4),0) | ... AL74: =IF(Hypothèses!$C$23*$E$4>0,AL73/(Hypothèses!$C$23*$E$4),0) | AN74: =N74 | AO74: =Z74 | AP74: =AL74

Sheet Modèle Central
A1: Modèle Central (36 mois)
A2: Flux en € HT sauf mention TTC. Formules vivantes ; ne saisir que dans l'onglet Hypothèses et la ligne de chocs ci-dessous.
A3: Chocs de sensibilité (1 = aucun ; retard en mois) | C3: Prix × | D3: Churn × | E3: CAC × | F3: Coût IA × | G3: Coûts fixes × | H3: Retard lancement (mois)
C4: 1 | D4: 1 | E4: 1 | F4: 1 | G4: 1 | H4: 0
A5: Mois de lancement effectif | B5: =Hypothèses!$D$10+$H$4
A6: Ligne | B6: Unité | C6: M1 | D6: M2 | E6: M3 | F6: M4 | G6: M5 | H6: M6 | I6: M7 | J6: M8 | K6: M9 | L6: M10 | M6: M11 | N6: M12 | O6: M13 | P6: M14 | Q6: M15 | R6: M16 | S6: M17 | T6: M18 | U6: M19 | V6: M20 | W6: M21 | X6: M22 | Y6: M23 | Z6: M24 | AA6: M25 | AB6: M26 | AC6: M27 | AD6: M28 | AE6: M29 | AF6: M30 | AG6: M31 | AH6: M32 | AI6: M33 | AJ6: M34 | AK6: M35 | AL6: M36 | AN6: Année 1 | AO6: Année 2 | AP6: Année 3
A7: Mois | B7: n° | C7: 1 | D7: 2 | E7: 3 | F7: 4 | G7: 5 | H7: 6 | I7: 7 | J7: 8 | K7: 9 | L7: 10 | M7: 11 | N7: 12 | O7: 13 | P7: 14 | Q7: 15 | R7: 16 | S7: 17 | T7: 18 | U7: 19 | V7: 20 | W7: 21 | X7: 22 | Y7: 23 | Z7: 24 | AA7: 25 | AB7: 26 | AC7: 27 | AD7: 28 | AE7: 29 | AF7: 30 | AG7: 31 | AH7: 32 | AI7: 33 | AJ7: 34 | AK7: 35 | AL7: 36
A8: Date | C8: =EDATE(Hypothèses!$D$7,C7-1) | D8: =EDATE(Hypothèses!$D$7,D7-1) | E8: =EDATE(Hypothèses!$D$7,E7-1) | F8: =EDATE(Hypothèses!$D$7,F7-1) | G8: =EDATE(Hypothèses!$D$7,G7-1) | H8: =EDATE(Hypothèses!$D$7,H7-1) | I8: =EDATE(Hypothèses!$D$7,I7-1) | J8: =EDATE(Hypothèses!$D$7,J7-1) | ... AL8: =EDATE(Hypothèses!$D$7,AL7-1)
A9: Lancé ? (1 = oui) | B9: 0/1 | C9: =IF(C7>=$B$5,1,0) | D9: =IF(D7>=$B$5,1,0) | E9: =IF(E7>=$B$5,1,0) | F9: =IF(F7>=$B$5,1,0) | G9: =IF(G7>=$B$5,1,0) | H9: =IF(H7>=$B$5,1,0) | I9: =IF(I7>=$B$5,1,0) | J9: =IF(J7>=$B$5,1,0) | ... AL9: =IF(AL7>=$B$5,1,0)
A10: Pilote en cours ? (1 = oui) | B10: 0/1 | C10: =IF(AND(C7>=Hypothèses!$D$8,C7<$B$5),1,0) | D10: =IF(AND(D7>=Hypothèses!$D$8,D7<$B$5),1,0) | E10: =IF(AND(E7>=Hypothèses!$D$8,E7<$B$5),1,0) | F10: =IF(AND(F7>=Hypothèses!$D$8,F7<$B$5),1,0) | G10: =IF(AND(G7>=Hypothèses!$D$8,G7<$B$5),1,0) | H10: =IF(AND(H7>=Hypothèses!$D$8,H7<$B$5),1,0) | I10: =IF(AND(I7>=Hypothèses!$D$8,I7<$B$5),1,0) | J10: =IF(AND(J7>=Hypothèses!$D$8,J7<$B$5),1,0) | ... AL10: =IF(AND(AL7>=Hypothèses!$D$8,AL7<$B$5),1,0)
A11: Budget d'acquisition du mois | B11: € HT | C11: =IF(C9=1,IF(C7<=12,Hypothèses!$D$20,IF(C7<=24,Hypothèses!$D$21,Hypothèses!$D$22)),0) | D11: =IF(D9=1,IF(D7<=12,Hypothèses!$D$20,IF(D7<=24,Hypothèses!$D$21,Hypothèses!$D$22)),0) | E11: =IF(E9=1,IF(E7<=12,Hypothèses!$D$20,IF(E7<=24,Hypothèses!$D$21,Hypothèses!$D$22)),0) | F11: =IF(F9=1,IF(F7<=12,Hypothèses!$D$20,IF(F7<=24,Hypothèses!$D$21,Hypothèses!$D$22)),0) | G11: =IF(G9=1,IF(G7<=12,Hypothèses!$D$20,IF(G7<=24,Hypothèses!$D$21,Hypothèses!$D$22)),0) | H11: =IF(H9=1,IF(H7<=12,Hypothèses!$D$20,IF(H7<=24,Hypothèses!$D$21,Hypothèses!$D$22)),0) | I11: =IF(I9=1,IF(I7<=12,Hypothèses!$D$20,IF(I7<=24,Hypothèses!$D$21,Hypothèses!$D$22)),0) | J11: =IF(J9=1,IF(J7<=12,Hypothèses!$D$20,IF(J7<=24,Hypothèses!$D$21,Hypothèses!$D$22)),0) | ... AL11: =IF(AL9=1,IF(AL7<=12,Hypothèses!$D$20,IF(AL7<=24,Hypothèses!$D$21,Hypothèses!$D$22)),0) | AN11: =SUM(C11:N11) | AO11: =SUM(O11:Z11) | AP11: =SUM(AA11:AL11)
A12: Abonnés
A13: Abonnés en début de mois | B13: abonnés | C13: =0 | D13: =C18 | E13: =D18 | F13: =E18 | G13: =F18 | H13: =G18 | I13: =H18 | J13: =I18 | K13: =J18 | ... AL13: =AK18
A14: Nouveaux abonnés par acquisition payante | B14: abonnés | C14: =C11/(Hypothèses!$D$23*$E$4) | D14: =D11/(Hypothèses!$D$23*$E$4) | E14: =E11/(Hypothèses!$D$23*$E$4) | F14: =F11/(Hypothèses!$D$23*$E$4) | G14: =G11/(Hypothèses!$D$23*$E$4) | H14: =H11/(Hypothèses!$D$23*$E$4) | I14: =I11/(Hypothèses!$D$23*$E$4) | J14: =J11/(Hypothèses!$D$23*$E$4) | ... AL14: =AL11/(Hypothèses!$D$23*$E$4) | AN14: =SUM(C14:N14) | AO14: =SUM(O14:Z14) | AP14: =SUM(AA14:AL14)
A15: Nouveaux abonnés pilote | B15: abonnés | C15: =IF(C7=Hypothèses!$D$8,Hypothèses!$D$9,0) | D15: =IF(D7=Hypothèses!$D$8,Hypothèses!$D$9,0) | E15: =IF(E7=Hypothèses!$D$8,Hypothèses!$D$9,0) | F15: =IF(F7=Hypothèses!$D$8,Hypothèses!$D$9,0) | G15: =IF(G7=Hypothèses!$D$8,Hypothèses!$D$9,0) | H15: =IF(H7=Hypothèses!$D$8,Hypothèses!$D$9,0) | I15: =IF(I7=Hypothèses!$D$8,Hypothèses!$D$9,0) | J15: =IF(J7=Hypothèses!$D$8,Hypothèses!$D$9,0) | ... AL15: =IF(AL7=Hypothèses!$D$8,Hypothèses!$D$9,0) | AN15: =SUM(C15:N15) | AO15: =SUM(O15:Z15) | AP15: =SUM(AA15:AL15)
A16: Nouveaux abonnés organiques (parrainage) | B16: abonnés | C16: =C9*C13*Hypothèses!$D$24 | D16: =D9*D13*Hypothèses!$D$24 | E16: =E9*E13*Hypothèses!$D$24 | F16: =F9*F13*Hypothèses!$D$24 | G16: =G9*G13*Hypothèses!$D$24 | H16: =H9*H13*Hypothèses!$D$24 | I16: =I9*I13*Hypothèses!$D$24 | J16: =J9*J13*Hypothèses!$D$24 | ... AL16: =AL9*AL13*Hypothèses!$D$24 | AN16: =SUM(C16:N16) | AO16: =SUM(O16:Z16) | AP16: =SUM(AA16:AL16)
A17: Résiliations | B17: abonnés | C17: =C13*Hypothèses!$D$26*$D$4 | D17: =D13*Hypothèses!$D$26*$D$4 | E17: =E13*Hypothèses!$D$26*$D$4 | F17: =F13*Hypothèses!$D$26*$D$4 | G17: =G13*Hypothèses!$D$26*$D$4 | H17: =H13*Hypothèses!$D$26*$D$4 | I17: =I13*Hypothèses!$D$26*$D$4 | J17: =J13*Hypothèses!$D$26*$D$4 | ... AL17: =AL13*Hypothèses!$D$26*$D$4 | AN17: =SUM(C17:N17) | AO17: =SUM(O17:Z17) | AP17: =SUM(AA17:AL17)
A18: Abonnés en fin de mois | B18: abonnés | C18: =C13+C14+C15+C16-C17 | D18: =D13+D14+D15+D16-D17 | E18: =E13+E14+E15+E16-E17 | F18: =F13+F14+F15+F16-F17 | G18: =G13+G14+G15+G16-G17 | H18: =H13+H14+H15+H16-H17 | I18: =I13+I14+I15+I16-I17 | J18: =J13+J14+J15+J16-J17 | ... AL18: =AL13+AL14+AL15+AL16-AL17 | AN18: =N18 | AO18: =Z18 | AP18: =AL18
A19: dont Personal | B19: abonnés | C19: =C18*Hypothèses!$D$16 | D19: =D18*Hypothèses!$D$16 | E19: =E18*Hypothèses!$D$16 | F19: =F18*Hypothèses!$D$16 | G19: =G18*Hypothèses!$D$16 | H19: =H18*Hypothèses!$D$16 | I19: =I18*Hypothèses!$D$16 | J19: =J18*Hypothèses!$D$16 | ... AL19: =AL18*Hypothèses!$D$16 | AN19: =N19 | AO19: =Z19 | AP19: =AL19
A20: dont Premium | B20: abonnés | C20: =C18*Hypothèses!$D$17 | D20: =D18*Hypothèses!$D$17 | E20: =E18*Hypothèses!$D$17 | F20: =F18*Hypothèses!$D$17 | G20: =G18*Hypothèses!$D$17 | H20: =H18*Hypothèses!$D$17 | I20: =I18*Hypothèses!$D$17 | J20: =J18*Hypothèses!$D$17 | ... AL20: =AL18*Hypothèses!$D$17 | AN20: =N20 | AO20: =Z20 | AP20: =AL20
A21: dont Family | B21: abonnés | C21: =C18*Hypothèses!$D$18 | D21: =D18*Hypothèses!$D$18 | E21: =E18*Hypothèses!$D$18 | F21: =F18*Hypothèses!$D$18 | G21: =G18*Hypothèses!$D$18 | H21: =H18*Hypothèses!$D$18 | I21: =I18*Hypothèses!$D$18 | J21: =J18*Hypothèses!$D$18 | ... AL21: =AL18*Hypothèses!$D$18 | AN21: =N21 | AO21: =Z21 | AP21: =AL21
A22: Revenus
A23: Facturation Personal TTC | B23: € TTC | C23: =C19*Hypothèses!$D$12*$C$4 | D23: =D19*Hypothèses!$D$12*$C$4 | E23: =E19*Hypothèses!$D$12*$C$4 | F23: =F19*Hypothèses!$D$12*$C$4 | G23: =G19*Hypothèses!$D$12*$C$4 | H23: =H19*Hypothèses!$D$12*$C$4 | I23: =I19*Hypothèses!$D$12*$C$4 | J23: =J19*Hypothèses!$D$12*$C$4 | ... AL23: =AL19*Hypothèses!$D$12*$C$4 | AN23: =SUM(C23:N23) | AO23: =SUM(O23:Z23) | AP23: =SUM(AA23:AL23)
A24: Facturation Premium TTC | B24: € TTC | C24: =C20*Hypothèses!$D$13*$C$4 | D24: =D20*Hypothèses!$D$13*$C$4 | E24: =E20*Hypothèses!$D$13*$C$4 | F24: =F20*Hypothèses!$D$13*$C$4 | G24: =G20*Hypothèses!$D$13*$C$4 | H24: =H20*Hypothèses!$D$13*$C$4 | I24: =I20*Hypothèses!$D$13*$C$4 | J24: =J20*Hypothèses!$D$13*$C$4 | ... AL24: =AL20*Hypothèses!$D$13*$C$4 | AN24: =SUM(C24:N24) | AO24: =SUM(O24:Z24) | AP24: =SUM(AA24:AL24)
A25: Facturation Family TTC | B25: € TTC | C25: =C21*Hypothèses!$D$14*$C$4 | D25: =D21*Hypothèses!$D$14*$C$4 | E25: =E21*Hypothèses!$D$14*$C$4 | F25: =F21*Hypothèses!$D$14*$C$4 | G25: =G21*Hypothèses!$D$14*$C$4 | H25: =H21*Hypothèses!$D$14*$C$4 | I25: =I21*Hypothèses!$D$14*$C$4 | J25: =J21*Hypothèses!$D$14*$C$4 | ... AL25: =AL21*Hypothèses!$D$14*$C$4 | AN25: =SUM(C25:N25) | AO25: =SUM(O25:Z25) | AP25: =SUM(AA25:AL25)
A26: Facturation totale TTC (MRR TTC) | B26: € TTC | C26: =C23+C24+C25 | D26: =D23+D24+D25 | E26: =E23+E24+E25 | F26: =F23+F24+F25 | G26: =G23+G24+G25 | H26: =H23+H24+H25 | I26: =I23+I24+I25 | J26: =J23+J24+J25 | ... AL26: =AL23+AL24+AL25 | AN26: =SUM(C26:N26) | AO26: =SUM(O26:Z26) | AP26: =SUM(AA26:AL26)
A27: TVA collectée | B27: € | C27: =C26*Hypothèses!$D$15/(1+Hypothèses!$D$15) | D27: =D26*Hypothèses!$D$15/(1+Hypothèses!$D$15) | E27: =E26*Hypothèses!$D$15/(1+Hypothèses!$D$15) | F27: =F26*Hypothèses!$D$15/(1+Hypothèses!$D$15) | G27: =G26*Hypothèses!$D$15/(1+Hypothèses!$D$15) | H27: =H26*Hypothèses!$D$15/(1+Hypothèses!$D$15) | I27: =I26*Hypothèses!$D$15/(1+Hypothèses!$D$15) | J27: =J26*Hypothèses!$D$15/(1+Hypothèses!$D$15) | ... AL27: =AL26*Hypothèses!$D$15/(1+Hypothèses!$D$15) | AN27: =SUM(C27:N27) | AO27: =SUM(O27:Z27) | AP27: =SUM(AA27:AL27)
A28: Chiffre d'affaires HT | B28: € HT | C28: =C26-C27 | D28: =D26-D27 | E28: =E26-E27 | F28: =F26-F27 | G28: =G26-G27 | H28: =H26-H27 | I28: =I26-I27 | J28: =J26-J27 | ... AL28: =AL26-AL27 | AN28: =SUM(C28:N28) | AO28: =SUM(O28:Z28) | AP28: =SUM(AA28:AL28)
A29: Impayés (TTC) | B29: € TTC | C29: =C26*Hypothèses!$D$27 | D29: =D26*Hypothèses!$D$27 | E29: =E26*Hypothèses!$D$27 | F29: =F26*Hypothèses!$D$27 | G29: =G26*Hypothèses!$D$27 | H29: =H26*Hypothèses!$D$27 | I29: =I26*Hypothèses!$D$27 | J29: =J26*Hypothèses!$D$27 | ... AL29: =AL26*Hypothèses!$D$27 | AN29: =SUM(C29:N29) | AO29: =SUM(O29:Z29) | AP29: =SUM(AA29:AL29)
A30: Frais de paiement | B30: € | C30: =(C26-C29)*Hypothèses!$D$28+C18*Hypothèses!$D$29 | D30: =(D26-D29)*Hypothèses!$D$28+D18*Hypothèses!$D$29 | E30: =(E26-E29)*Hypothèses!$D$28+E18*Hypothèses!$D$29 | F30: =(F26-F29)*Hypothèses!$D$28+F18*Hypothèses!$D$29 | G30: =(G26-G29)*Hypothèses!$D$28+G18*Hypothèses!$D$29 | H30: =(H26-H29)*Hypothèses!$D$28+H18*Hypothèses!$D$29 | I30: =(I26-I29)*Hypothèses!$D$28+I18*Hypothèses!$D$29 | J30: =(J26-J29)*Hypothèses!$D$28+J18*Hypothèses!$D$29 | ... AL30: =(AL26-AL29)*Hypothèses!$D$28+AL18*Hypothèses!$D$29 | AN30: =SUM(C30:N30) | AO30: =SUM(O30:Z30) | AP30: =SUM(AA30:AL30)
A31: Encaissements nets TTC | B31: € TTC | C31: =C26-C29-C30 | D31: =D26-D29-D30 | E31: =E26-E29-E30 | F31: =F26-F29-F30 | G31: =G26-G29-G30 | H31: =H26-H29-H30 | I31: =I26-I29-I30 | J31: =J26-J29-J30 | ... AL31: =AL26-AL29-AL30 | AN31: =SUM(C31:N31) | AO31: =SUM(O31:Z31) | AP31: =SUM(AA31:AL31)
A32: Coûts variables
A33: Coût IA et outils (missions × coût par mission) | B33: € HT | C33: =(C19*Hypothèses!$D$31+C20*Hypothèses!$D$32+C21*Hypothèses!$D$33)*Hypothèses!$D$34*$F$4 | D33: =(D19*Hypothèses!$D$31+D20*Hypothèses!$D$32+D21*Hypothèses!$D$33)*Hypothèses!$D$34*$F$4 | E33: =(E19*Hypothèses!$D$31+E20*Hypothèses!$D$32+E21*Hypothèses!$D$33)*Hypothèses!$D$34*$F$4 | F33: =(F19*Hypothèses!$D$31+F20*Hypothèses!$D$32+F21*Hypothèses!$D$33)*Hypothèses!$D$34*$F$4 | G33: =(G19*Hypothèses!$D$31+G20*Hypothèses!$D$32+G21*Hypothèses!$D$33)*Hypothèses!$D$34*$F$4 | H33: =(H19*Hypothèses!$D$31+H20*Hypothèses!$D$32+H21*Hypothèses!$D$33)*Hypothèses!$D$34*$F$4 | I33: =(I19*Hypothèses!$D$31+I20*Hypothèses!$D$32+I21*Hypothèses!$D$33)*Hypothèses!$D$34*$F$4 | J33: =(J19*Hypothèses!$D$31+J20*Hypothèses!$D$32+J21*Hypothèses!$D$33)*Hypothèses!$D$34*$F$4 | ... AL33: =(AL19*Hypothèses!$D$31+AL20*Hypothèses!$D$32+AL21*Hypothèses!$D$33)*Hypothèses!$D$34*$F$4 | AN33: =SUM(C33:N33) | AO33: =SUM(O33:Z33) | AP33: =SUM(AA33:AL33)
A34: Hébergement, stockage, connecteurs | B34: € HT | C34: =C18*Hypothèses!$D$35 | D34: =D18*Hypothèses!$D$35 | E34: =E18*Hypothèses!$D$35 | F34: =F18*Hypothèses!$D$35 | G34: =G18*Hypothèses!$D$35 | H34: =H18*Hypothèses!$D$35 | I34: =I18*Hypothèses!$D$35 | J34: =J18*Hypothèses!$D$35 | ... AL34: =AL18*Hypothèses!$D$35 | AN34: =SUM(C34:N34) | AO34: =SUM(O34:Z34) | AP34: =SUM(AA34:AL34)
A35: Support humain | B35: € HT | C35: =C18*Hypothèses!$D$36 | D35: =D18*Hypothèses!$D$36 | E35: =E18*Hypothèses!$D$36 | F35: =F18*Hypothèses!$D$36 | G35: =G18*Hypothèses!$D$36 | H35: =H18*Hypothèses!$D$36 | I35: =I18*Hypothèses!$D$36 | J35: =J18*Hypothèses!$D$36 | ... AL35: =AL18*Hypothèses!$D$36 | AN35: =SUM(C35:N35) | AO35: =SUM(O35:Z35) | AP35: =SUM(AA35:AL35)
A36: Total coûts variables | B36: € HT | C36: =C33+C34+C35 | D36: =D33+D34+D35 | E36: =E33+E34+E35 | F36: =F33+F34+F35 | G36: =G33+G34+G35 | H36: =H33+H34+H35 | I36: =I33+I34+I35 | J36: =J33+J34+J35 | ... AL36: =AL33+AL34+AL35 | AN36: =SUM(C36:N36) | AO36: =SUM(O36:Z36) | AP36: =SUM(AA36:AL36)
A37: Marge sur coûts variables (CA HT − variables − frais − impayés HT) | B37: € HT | C37: =C28-C36-C30-C29/(1+Hypothèses!$D$15) | D37: =D28-D36-D30-D29/(1+Hypothèses!$D$15) | E37: =E28-E36-E30-E29/(1+Hypothèses!$D$15) | F37: =F28-F36-F30-F29/(1+Hypothèses!$D$15) | G37: =G28-G36-G30-G29/(1+Hypothèses!$D$15) | H37: =H28-H36-H30-H29/(1+Hypothèses!$D$15) | I37: =I28-I36-I30-I29/(1+Hypothèses!$D$15) | J37: =J28-J36-J30-J29/(1+Hypothèses!$D$15) | ... AL37: =AL28-AL36-AL30-AL29/(1+Hypothèses!$D$15) | AN37: =SUM(C37:N37) | AO37: =SUM(O37:Z37) | AP37: =SUM(AA37:AL37)
A38: Acquisition et coûts fixes
A39: Dépenses d'acquisition | B39: € HT | C39: =C11 | D39: =D11 | E39: =E11 | F39: =F11 | G39: =G11 | H39: =H11 | I39: =I11 | J39: =J11 | ... AL39: =AL11 | AN39: =SUM(C39:N39) | AO39: =SUM(O39:Z39) | AP39: =SUM(AA39:AL39)
A40: Rémunération des fondateurs | B40: € HT | C40: =IF(C7>=Hypothèses!$D$39,Hypothèses!$D$38*Hypothèses!$D$40,0)*$G$4 | D40: =IF(D7>=Hypothèses!$D$39,Hypothèses!$D$38*Hypothèses!$D$40,0)*$G$4 | E40: =IF(E7>=Hypothèses!$D$39,Hypothèses!$D$38*Hypothèses!$D$40,0)*$G$4 | F40: =IF(F7>=Hypothèses!$D$39,Hypothèses!$D$38*Hypothèses!$D$40,0)*$G$4 | G40: =IF(G7>=Hypothèses!$D$39,Hypothèses!$D$38*Hypothèses!$D$40,0)*$G$4 | H40: =IF(H7>=Hypothèses!$D$39,Hypothèses!$D$38*Hypothèses!$D$40,0)*$G$4 | I40: =IF(I7>=Hypothèses!$D$39,Hypothèses!$D$38*Hypothèses!$D$40,0)*$G$4 | J40: =IF(J7>=Hypothèses!$D$39,Hypothèses!$D$38*Hypothèses!$D$40,0)*$G$4 | ... AL40: =IF(AL7>=Hypothèses!$D$39,Hypothèses!$D$38*Hypothèses!$D$40,0)*$G$4 | AN40: =SUM(C40:N40) | AO40: =SUM(O40:Z40) | AP40: =SUM(AA40:AL40)
A41: Salarié 1 (growth / customer success) | B41: € HT | C41: =IF(C7>=Hypothèses!$D$41,Hypothèses!$D$42,0)*$G$4 | D41: =IF(D7>=Hypothèses!$D$41,Hypothèses!$D$42,0)*$G$4 | E41: =IF(E7>=Hypothèses!$D$41,Hypothèses!$D$42,0)*$G$4 | F41: =IF(F7>=Hypothèses!$D$41,Hypothèses!$D$42,0)*$G$4 | G41: =IF(G7>=Hypothèses!$D$41,Hypothèses!$D$42,0)*$G$4 | H41: =IF(H7>=Hypothèses!$D$41,Hypothèses!$D$42,0)*$G$4 | I41: =IF(I7>=Hypothèses!$D$41,Hypothèses!$D$42,0)*$G$4 | J41: =IF(J7>=Hypothèses!$D$41,Hypothèses!$D$42,0)*$G$4 | ... AL41: =IF(AL7>=Hypothèses!$D$41,Hypothèses!$D$42,0)*$G$4 | AN41: =SUM(C41:N41) | AO41: =SUM(O41:Z41) | AP41: =SUM(AA41:AL41)
A42: Salarié 2 (ingénieur) | B42: € HT | C42: =IF(C7>=Hypothèses!$D$43,Hypothèses!$D$44,0)*$G$4 | D42: =IF(D7>=Hypothèses!$D$43,Hypothèses!$D$44,0)*$G$4 | E42: =IF(E7>=Hypothèses!$D$43,Hypothèses!$D$44,0)*$G$4 | F42: =IF(F7>=Hypothèses!$D$43,Hypothèses!$D$44,0)*$G$4 | G42: =IF(G7>=Hypothèses!$D$43,Hypothèses!$D$44,0)*$G$4 | H42: =IF(H7>=Hypothèses!$D$43,Hypothèses!$D$44,0)*$G$4 | I42: =IF(I7>=Hypothèses!$D$43,Hypothèses!$D$44,0)*$G$4 | J42: =IF(J7>=Hypothèses!$D$43,Hypothèses!$D$44,0)*$G$4 | ... AL42: =IF(AL7>=Hypothèses!$D$43,Hypothèses!$D$44,0)*$G$4 | AN42: =SUM(C42:N42) | AO42: =SUM(O42:Z42) | AP42: =SUM(AA42:AL42)
A43: Développement MVP externe (étalé jusqu'au lancement) | B43: € HT | C43: =IF(C7<$B$5,Hypothèses!$D$45/MAX(1,$B$5-1),0) | D43: =IF(D7<$B$5,Hypothèses!$D$45/MAX(1,$B$5-1),0) | E43: =IF(E7<$B$5,Hypothèses!$D$45/MAX(1,$B$5-1),0) | F43: =IF(F7<$B$5,Hypothèses!$D$45/MAX(1,$B$5-1),0) | G43: =IF(G7<$B$5,Hypothèses!$D$45/MAX(1,$B$5-1),0) | H43: =IF(H7<$B$5,Hypothèses!$D$45/MAX(1,$B$5-1),0) | I43: =IF(I7<$B$5,Hypothèses!$D$45/MAX(1,$B$5-1),0) | J43: =IF(J7<$B$5,Hypothèses!$D$45/MAX(1,$B$5-1),0) | ... AL43: =IF(AL7<$B$5,Hypothèses!$D$45/MAX(1,$B$5-1),0) | AN43: =SUM(C43:N43) | AO43: =SUM(O43:Z43) | AP43: =SUM(AA43:AL43)
A44: Outils et SaaS | B44: € HT | C44: =Hypothèses!$D$46*$G$4 | D44: =Hypothèses!$D$46*$G$4 | E44: =Hypothèses!$D$46*$G$4 | F44: =Hypothèses!$D$46*$G$4 | G44: =Hypothèses!$D$46*$G$4 | H44: =Hypothèses!$D$46*$G$4 | I44: =Hypothèses!$D$46*$G$4 | J44: =Hypothèses!$D$46*$G$4 | ... AL44: =Hypothèses!$D$46*$G$4 | AN44: =SUM(C44:N44) | AO44: =SUM(O44:Z44) | AP44: =SUM(AA44:AL44)
A45: Juridique et comptabilité | B45: € HT | C45: =Hypothèses!$D$47*$G$4 | D45: =Hypothèses!$D$47*$G$4 | E45: =Hypothèses!$D$47*$G$4 | F45: =Hypothèses!$D$47*$G$4 | G45: =Hypothèses!$D$47*$G$4 | H45: =Hypothèses!$D$47*$G$4 | I45: =Hypothèses!$D$47*$G$4 | J45: =Hypothèses!$D$47*$G$4 | ... AL45: =Hypothèses!$D$47*$G$4 | AN45: =SUM(C45:N45) | AO45: =SUM(O45:Z45) | AP45: =SUM(AA45:AL45)
A46: Assurance RC pro | B46: € | C46: =C9*Hypothèses!$D$48*$G$4 | D46: =D9*Hypothèses!$D$48*$G$4 | E46: =E9*Hypothèses!$D$48*$G$4 | F46: =F9*Hypothèses!$D$48*$G$4 | G46: =G9*Hypothèses!$D$48*$G$4 | H46: =H9*Hypothèses!$D$48*$G$4 | I46: =I9*Hypothèses!$D$48*$G$4 | J46: =J9*Hypothèses!$D$48*$G$4 | ... AL46: =AL9*Hypothèses!$D$48*$G$4 | AN46: =SUM(C46:N46) | AO46: =SUM(O46:Z46) | AP46: =SUM(AA46:AL46)
A47: Marketing fixe | B47: € HT | C47: =C9*Hypothèses!$D$49*$G$4 | D47: =D9*Hypothèses!$D$49*$G$4 | E47: =E9*Hypothèses!$D$49*$G$4 | F47: =F9*Hypothèses!$D$49*$G$4 | G47: =G9*Hypothèses!$D$49*$G$4 | H47: =H9*Hypothèses!$D$49*$G$4 | I47: =I9*Hypothèses!$D$49*$G$4 | J47: =J9*Hypothèses!$D$49*$G$4 | ... AL47: =AL9*Hypothèses!$D$49*$G$4 | AN47: =SUM(C47:N47) | AO47: =SUM(O47:Z47) | AP47: =SUM(AA47:AL47)
A48: Frais généraux | B48: € HT | C48: =Hypothèses!$D$50*$G$4 | D48: =Hypothèses!$D$50*$G$4 | E48: =Hypothèses!$D$50*$G$4 | F48: =Hypothèses!$D$50*$G$4 | G48: =Hypothèses!$D$50*$G$4 | H48: =Hypothèses!$D$50*$G$4 | I48: =Hypothèses!$D$50*$G$4 | J48: =Hypothèses!$D$50*$G$4 | ... AL48: =Hypothèses!$D$50*$G$4 | AN48: =SUM(C48:N48) | AO48: =SUM(O48:Z48) | AP48: =SUM(AA48:AL48)
A49: Audit de sécurité (annuel, à partir du lancement) | B49: € HT | C49: =IF(AND(C9=1,MOD(C7-$B$5,12)=0),Hypothèses!$D$51,0)*$G$4 | D49: =IF(AND(D9=1,MOD(D7-$B$5,12)=0),Hypothèses!$D$51,0)*$G$4 | E49: =IF(AND(E9=1,MOD(E7-$B$5,12)=0),Hypothèses!$D$51,0)*$G$4 | F49: =IF(AND(F9=1,MOD(F7-$B$5,12)=0),Hypothèses!$D$51,0)*$G$4 | G49: =IF(AND(G9=1,MOD(G7-$B$5,12)=0),Hypothèses!$D$51,0)*$G$4 | H49: =IF(AND(H9=1,MOD(H7-$B$5,12)=0),Hypothèses!$D$51,0)*$G$4 | I49: =IF(AND(I9=1,MOD(I7-$B$5,12)=0),Hypothèses!$D$51,0)*$G$4 | J49: =IF(AND(J9=1,MOD(J7-$B$5,12)=0),Hypothèses!$D$51,0)*$G$4 | ... AL49: =IF(AND(AL9=1,MOD(AL7-$B$5,12)=0),Hypothèses!$D$51,0)*$G$4 | AN49: =SUM(C49:N49) | AO49: =SUM(O49:Z49) | AP49: =SUM(AA49:AL49)
A50: Frais de constitution | B50: € HT | C50: =IF(C7=2,Hypothèses!$D$52,0) | D50: =IF(D7=2,Hypothèses!$D$52,0) | E50: =IF(E7=2,Hypothèses!$D$52,0) | F50: =IF(F7=2,Hypothèses!$D$52,0) | G50: =IF(G7=2,Hypothèses!$D$52,0) | H50: =IF(H7=2,Hypothèses!$D$52,0) | I50: =IF(I7=2,Hypothèses!$D$52,0) | J50: =IF(J7=2,Hypothèses!$D$52,0) | ... AL50: =IF(AL7=2,Hypothèses!$D$52,0) | AN50: =SUM(C50:N50) | AO50: =SUM(O50:Z50) | AP50: =SUM(AA50:AL50)
A51: Total coûts fixes | B51: € HT | C51: =SUM(C40:C50) | D51: =SUM(D40:D50) | E51: =SUM(E40:E50) | F51: =SUM(F40:F50) | G51: =SUM(G40:G50) | H51: =SUM(H40:H50) | I51: =SUM(I40:I50) | J51: =SUM(J40:J50) | ... AL51: =SUM(AL40:AL50) | AN51: =SUM(C51:N51) | AO51: =SUM(O51:Z51) | AP51: =SUM(AA51:AL51)
A52: EBITDA (marge variable − acquisition − fixes) | B52: € HT | C52: =C37-C39-C51 | D52: =D37-D39-D51 | E52: =E37-E39-E51 | F52: =F37-F39-F51 | G52: =G37-G39-G51 | H52: =H37-H39-H51 | I52: =I37-I39-I51 | J52: =J37-J39-J51 | ... AL52: =AL37-AL39-AL51 | AN52: =SUM(C52:N52) | AO52: =SUM(O52:Z52) | AP52: =SUM(AA52:AL52)
A53: EBITDA positif ? (1 = oui) | B53: 0/1 | C53: =IF(C52>0,1,0) | D53: =IF(D52>0,1,0) | E53: =IF(E52>0,1,0) | F53: =IF(F52>0,1,0) | G53: =IF(G52>0,1,0) | H53: =IF(H52>0,1,0) | I53: =IF(I52>0,1,0) | J53: =IF(J52>0,1,0) | ... AL53: =IF(AL52>0,1,0)
A54: Trésorerie
A55: TVA collectée reversée (mois suivant) | B55: € | C55: =0 | D55: =C27 | E55: =D27 | F55: =E27 | G55: =F27 | H55: =G27 | I55: =H27 | J55: =I27 | K55: =J27 | ... AL55: =AK27 | AN55: =SUM(C55:N55) | AO55: =SUM(O55:Z55) | AP55: =SUM(AA55:AL55)
A56: TVA déductible récupérée (mois suivant, coûts externes) | B56: € | C56: =0 | D56: =(C36+C39+C43+C44+C45+C47+C48+C49+C50)*Hypothèses!$D$15 | E56: =(D36+D39+D43+D44+D45+D47+D48+D49+D50)*Hypothèses!$D$15 | F56: =(E36+E39+E43+E44+E45+E47+E48+E49+E50)*Hypothèses!$D$15 | G56: =(F36+F39+F43+F44+F45+F47+F48+F49+F50)*Hypothèses!$D$15 | H56: =(G36+G39+G43+G44+G45+G47+G48+G49+G50)*Hypothèses!$D$15 | I56: =(H36+H39+H43+H44+H45+H47+H48+H49+H50)*Hypothèses!$D$15 | J56: =(I36+I39+I43+I44+I45+I47+I48+I49+I50)*Hypothèses!$D$15 | K56: =(J36+J39+J43+J44+J45+J47+J48+J49+J50)*Hypothèses!$D$15 | ... AL56: =(AK36+AK39+AK43+AK44+AK45+AK47+AK48+AK49+AK50)*Hypothèses!$D$15 | AN56: =SUM(C56:N56) | AO56: =SUM(O56:Z56) | AP56: =SUM(AA56:AL56)
A57: Financement reçu | B57: € | C57: =Hypothèses!$D$56*(IF(C7=Hypothèses!$D$57,Hypothèses!$D$58,0)+IF(C7=Hypothèses!$D$59,Hypothèses!$D$60,0)+IF(C7=Hypothèses!$D$61,Hypothèses!$D$62,0)) | D57: =Hypothèses!$D$56*(IF(D7=Hypothèses!$D$57,Hypothèses!$D$58,0)+IF(D7=Hypothèses!$D$59,Hypothèses!$D$60,0)+IF(D7=Hypothèses!$D$61,Hypothèses!$D$62,0)) | E57: =Hypothèses!$D$56*(IF(E7=Hypothèses!$D$57,Hypothèses!$D$58,0)+IF(E7=Hypothèses!$D$59,Hypothèses!$D$60,0)+IF(E7=Hypothèses!$D$61,Hypothèses!$D$62,0)) | F57: =Hypothèses!$D$56*(IF(F7=Hypothèses!$D$57,Hypothèses!$D$58,0)+IF(F7=Hypothèses!$D$59,Hypothèses!$D$60,0)+IF(F7=Hypothèses!$D$61,Hypothèses!$D$62,0)) | G57: =Hypothèses!$D$56*(IF(G7=Hypothèses!$D$57,Hypothèses!$D$58,0)+IF(G7=Hypothèses!$D$59,Hypothèses!$D$60,0)+IF(G7=Hypothèses!$D$61,Hypothèses!$D$62,0)) | H57: =Hypothèses!$D$56*(IF(H7=Hypothèses!$D$57,Hypothèses!$D$58,0)+IF(H7=Hypothèses!$D$59,Hypothèses!$D$60,0)+IF(H7=Hypothèses!$D$61,Hypothèses!$D$62,0)) | I57: =Hypothèses!$D$56*(IF(I7=Hypothèses!$D$57,Hypothèses!$D$58,0)+IF(I7=Hypothèses!$D$59,Hypothèses!$D$60,0)+IF(I7=Hypothèses!$D$61,Hypothèses!$D$62,0)) | J57: =Hypothèses!$D$56*(IF(J7=Hypothèses!$D$57,Hypothèses!$D$58,0)+IF(J7=Hypothèses!$D$59,Hypothèses!$D$60,0)+IF(J7=Hypothèses!$D$61,Hypothèses!$D$62,0)) | ... AL57: =Hypothèses!$D$56*(IF(AL7=Hypothèses!$D$57,Hypothèses!$D$58,0)+IF(AL7=Hypothèses!$D$59,Hypothèses!$D$60,0)+IF(AL7=Hypothèses!$D$61,Hypothèses!$D$62,0)) | AN57: =SUM(C57:N57) | AO57: =SUM(O57:Z57) | AP57: =SUM(AA57:AL57)
A58: Trésorerie d'ouverture | B58: € | C58: =Hypothèses!$D$54 | D58: =C60 | E58: =D60 | F58: =E60 | G58: =F60 | H58: =G60 | I58: =H60 | J58: =I60 | K58: =J60 | ... AL58: =AK60
A59: Flux de trésorerie du mois | B59: € | C59: =C31-C36-C39-C51-C55+C56+C57 | D59: =D31-D36-D39-D51-D55+D56+D57 | E59: =E31-E36-E39-E51-E55+E56+E57 | F59: =F31-F36-F39-F51-F55+F56+F57 | G59: =G31-G36-G39-G51-G55+G56+G57 | H59: =H31-H36-H39-H51-H55+H56+H57 | I59: =I31-I36-I39-I51-I55+I56+I57 | J59: =J31-J36-J39-J51-J55+J56+J57 | ... AL59: =AL31-AL36-AL39-AL51-AL55+AL56+AL57 | AN59: =SUM(C59:N59) | AO59: =SUM(O59:Z59) | AP59: =SUM(AA59:AL59)
A60: Trésorerie de clôture | B60: € | C60: =C58+C59 | D60: =D58+D59 | E60: =E58+E59 | F60: =F58+F59 | G60: =G58+G59 | H60: =H58+H59 | I60: =I58+I59 | J60: =J58+J59 | ... AL60: =AL58+AL59 | AN60: =N60 | AO60: =Z60 | AP60: =AL60
A61: Financement cumulé | B61: € | C61: =0+C57 | D61: =C61+D57 | E61: =D61+E57 | F61: =E61+F57 | G61: =F61+G57 | H61: =G61+H57 | I61: =H61+I57 | J61: =I61+J57 | K61: =J61+K57 | ... AL61: =AK61+AL57 | AN61: =N61 | AO61: =Z61 | AP61: =AL61
A62: Trésorerie cumulée hors financement | B62: € | C62: =C60-C61 | D62: =D60-D61 | E62: =E60-E61 | F62: =F60-F61 | G62: =G60-G61 | H62: =H60-H61 | I62: =I60-I61 | J62: =J60-J61 | ... AL62: =AL60-AL61 | AN62: =N62 | AO62: =Z62 | AP62: =AL62
A63: Point bas glissant hors financement | B63: € | C63: =C62 | D63: =MIN(C63,D62) | E63: =MIN(D63,E62) | F63: =MIN(E63,F62) | G63: =MIN(F63,G62) | H63: =MIN(G63,H62) | I63: =MIN(H63,I62) | J63: =MIN(I63,J62) | K63: =MIN(J63,K62) | ... AL63: =MIN(AK63,AL62) | AN63: =N63 | AO63: =Z63 | AP63: =AL63
A64: Trésorerie cumulée hors financement positive après lancement ? (1 = oui) | B64: 0/1 | C64: =IF(AND(C9=1,C62>0),1,0) | D64: =IF(AND(D9=1,D62>0),1,0) | E64: =IF(AND(E9=1,E62>0),1,0) | F64: =IF(AND(F9=1,F62>0),1,0) | G64: =IF(AND(G9=1,G62>0),1,0) | H64: =IF(AND(H9=1,H62>0),1,0) | I64: =IF(AND(I9=1,I62>0),1,0) | J64: =IF(AND(J9=1,J62>0),1,0) | ... AL64: =IF(AND(AL9=1,AL62>0),1,0)
A65: Indicateurs
A66: ARR HT instantané (CA HT × 12) | B66: € HT | C66: =C28*12 | D66: =D28*12 | E66: =E28*12 | F66: =F28*12 | G66: =G28*12 | H66: =H28*12 | I66: =I28*12 | J66: =J28*12 | ... AL66: =AL28*12 | AN66: =N66 | AO66: =Z66 | AP66: =AL66
A67: ARPA HT (CA HT / abonnés) | B67: € HT | C67: =IF(C18>0,C28/C18,0) | D67: =IF(D18>0,D28/D18,0) | E67: =IF(E18>0,E28/E18,0) | F67: =IF(F18>0,F28/F18,0) | G67: =IF(G18>0,G28/G18,0) | H67: =IF(H18>0,H28/H18,0) | I67: =IF(I18>0,I28/I18,0) | J67: =IF(J18>0,J28/J18,0) | ... AL67: =IF(AL18>0,AL28/AL18,0) | AN67: =N67 | AO67: =Z67 | AP67: =AL67
A68: Coût variable par abonné | B68: € HT | C68: =IF(C18>0,C36/C18,0) | D68: =IF(D18>0,D36/D18,0) | E68: =IF(E18>0,E36/E18,0) | F68: =IF(F18>0,F36/F18,0) | G68: =IF(G18>0,G36/G18,0) | H68: =IF(H18>0,H36/H18,0) | I68: =IF(I18>0,I36/I18,0) | J68: =IF(J18>0,J36/J18,0) | ... AL68: =IF(AL18>0,AL36/AL18,0) | AN68: =N68 | AO68: =Z68 | AP68: =AL68
A69: Contribution par abonné | B69: € HT | C69: =IF(C18>0,C37/C18,0) | D69: =IF(D18>0,D37/D18,0) | E69: =IF(E18>0,E37/E18,0) | F69: =IF(F18>0,F37/F18,0) | G69: =IF(G18>0,G37/G18,0) | H69: =IF(H18>0,H37/H18,0) | I69: =IF(I18>0,I37/I18,0) | J69: =IF(J18>0,J37/J18,0) | ... AL69: =IF(AL18>0,AL37/AL18,0) | AN69: =N69 | AO69: =Z69 | AP69: =AL69
A70: Marge variable (% du CA HT) | B70: % | C70: =IF(C28>0,C37/C28,0) | D70: =IF(D28>0,D37/D28,0) | E70: =IF(E28>0,E37/E28,0) | F70: =IF(F28>0,F37/F28,0) | G70: =IF(G28>0,G37/G28,0) | H70: =IF(H28>0,H37/H28,0) | I70: =IF(I28>0,I37/I28,0) | J70: =IF(J28>0,J37/J28,0) | ... AL70: =IF(AL28>0,AL37/AL28,0) | AN70: =N70 | AO70: =Z70 | AP70: =AL70
A71: CAC effectif | B71: € | C71: =IF(C14>0,C39/C14,0) | D71: =IF(D14>0,D39/D14,0) | E71: =IF(E14>0,E39/E14,0) | F71: =IF(F14>0,F39/F14,0) | G71: =IF(G14>0,G39/G14,0) | H71: =IF(H14>0,H39/H14,0) | I71: =IF(I14>0,I39/I14,0) | J71: =IF(J14>0,J39/J14,0) | ... AL71: =IF(AL14>0,AL39/AL14,0) | AN71: =N71 | AO71: =Z71 | AP71: =AL71
A72: Payback du CAC (mois) | B72: mois | C72: =IF(C69>0,Hypothèses!$D$23*$E$4/C69,0) | D72: =IF(D69>0,Hypothèses!$D$23*$E$4/D69,0) | E72: =IF(E69>0,Hypothèses!$D$23*$E$4/E69,0) | F72: =IF(F69>0,Hypothèses!$D$23*$E$4/F69,0) | G72: =IF(G69>0,Hypothèses!$D$23*$E$4/G69,0) | H72: =IF(H69>0,Hypothèses!$D$23*$E$4/H69,0) | I72: =IF(I69>0,Hypothèses!$D$23*$E$4/I69,0) | J72: =IF(J69>0,Hypothèses!$D$23*$E$4/J69,0) | ... AL72: =IF(AL69>0,Hypothèses!$D$23*$E$4/AL69,0) | AN72: =N72 | AO72: =Z72 | AP72: =AL72
A73: LTV contributive simplifiée (contribution / churn) | B73: € HT | C73: =IF(Hypothèses!$D$26*$D$4>0,C69/(Hypothèses!$D$26*$D$4),0) | D73: =IF(Hypothèses!$D$26*$D$4>0,D69/(Hypothèses!$D$26*$D$4),0) | E73: =IF(Hypothèses!$D$26*$D$4>0,E69/(Hypothèses!$D$26*$D$4),0) | F73: =IF(Hypothèses!$D$26*$D$4>0,F69/(Hypothèses!$D$26*$D$4),0) | G73: =IF(Hypothèses!$D$26*$D$4>0,G69/(Hypothèses!$D$26*$D$4),0) | H73: =IF(Hypothèses!$D$26*$D$4>0,H69/(Hypothèses!$D$26*$D$4),0) | I73: =IF(Hypothèses!$D$26*$D$4>0,I69/(Hypothèses!$D$26*$D$4),0) | J73: =IF(Hypothèses!$D$26*$D$4>0,J69/(Hypothèses!$D$26*$D$4),0) | ... AL73: =IF(Hypothèses!$D$26*$D$4>0,AL69/(Hypothèses!$D$26*$D$4),0) | AN73: =N73 | AO73: =Z73 | AP73: =AL73
A74: LTV / CAC | B74: x | C74: =IF(Hypothèses!$D$23*$E$4>0,C73/(Hypothèses!$D$23*$E$4),0) | D74: =IF(Hypothèses!$D$23*$E$4>0,D73/(Hypothèses!$D$23*$E$4),0) | E74: =IF(Hypothèses!$D$23*$E$4>0,E73/(Hypothèses!$D$23*$E$4),0) | F74: =IF(Hypothèses!$D$23*$E$4>0,F73/(Hypothèses!$D$23*$E$4),0) | G74: =IF(Hypothèses!$D$23*$E$4>0,G73/(Hypothèses!$D$23*$E$4),0) | H74: =IF(Hypothèses!$D$23*$E$4>0,H73/(Hypothèses!$D$23*$E$4),0) | I74: =IF(Hypothèses!$D$23*$E$4>0,I73/(Hypothèses!$D$23*$E$4),0) | J74: =IF(Hypothèses!$D$23*$E$4>0,J73/(Hypothèses!$D$23*$E$4),0) | ... AL74: =IF(Hypothèses!$D$23*$E$4>0,AL73/(Hypothèses!$D$23*$E$4),0) | AN74: =N74 | AO74: =Z74 | AP74: =AL74

Sheet Modèle Ambitieux
A1: Modèle Ambitieux (36 mois)
A2: Flux en € HT sauf mention TTC. Formules vivantes ; ne saisir que dans l'onglet Hypothèses et la ligne de chocs ci-dessous.
A3: Chocs de sensibilité (1 = aucun ; retard en mois) | C3: Prix × | D3: Churn × | E3: CAC × | F3: Coût IA × | G3: Coûts fixes × | H3: Retard lancement (mois)
C4: 1 | D4: 1 | E4: 1 | F4: 1 | G4: 1 | H4: 0
A5: Mois de lancement effectif | B5: =Hypothèses!$E$10+$H$4
A6: Ligne | B6: Unité | C6: M1 | D6: M2 | E6: M3 | F6: M4 | G6: M5 | H6: M6 | I6: M7 | J6: M8 | K6: M9 | L6: M10 | M6: M11 | N6: M12 | O6: M13 | P6: M14 | Q6: M15 | R6: M16 | S6: M17 | T6: M18 | U6: M19 | V6: M20 | W6: M21 | X6: M22 | Y6: M23 | Z6: M24 | AA6: M25 | AB6: M26 | AC6: M27 | AD6: M28 | AE6: M29 | AF6: M30 | AG6: M31 | AH6: M32 | AI6: M33 | AJ6: M34 | AK6: M35 | AL6: M36 | AN6: Année 1 | AO6: Année 2 | AP6: Année 3
A7: Mois | B7: n° | C7: 1 | D7: 2 | E7: 3 | F7: 4 | G7: 5 | H7: 6 | I7: 7 | J7: 8 | K7: 9 | L7: 10 | M7: 11 | N7: 12 | O7: 13 | P7: 14 | Q7: 15 | R7: 16 | S7: 17 | T7: 18 | U7: 19 | V7: 20 | W7: 21 | X7: 22 | Y7: 23 | Z7: 24 | AA7: 25 | AB7: 26 | AC7: 27 | AD7: 28 | AE7: 29 | AF7: 30 | AG7: 31 | AH7: 32 | AI7: 33 | AJ7: 34 | AK7: 35 | AL7: 36
A8: Date | C8: =EDATE(Hypothèses!$E$7,C7-1) | D8: =EDATE(Hypothèses!$E$7,D7-1) | E8: =EDATE(Hypothèses!$E$7,E7-1) | F8: =EDATE(Hypothèses!$E$7,F7-1) | G8: =EDATE(Hypothèses!$E$7,G7-1) | H8: =EDATE(Hypothèses!$E$7,H7-1) | I8: =EDATE(Hypothèses!$E$7,I7-1) | J8: =EDATE(Hypothèses!$E$7,J7-1) | ... AL8: =EDATE(Hypothèses!$E$7,AL7-1)
A9: Lancé ? (1 = oui) | B9: 0/1 | C9: =IF(C7>=$B$5,1,0) | D9: =IF(D7>=$B$5,1,0) | E9: =IF(E7>=$B$5,1,0) | F9: =IF(F7>=$B$5,1,0) | G9: =IF(G7>=$B$5,1,0) | H9: =IF(H7>=$B$5,1,0) | I9: =IF(I7>=$B$5,1,0) | J9: =IF(J7>=$B$5,1,0) | ... AL9: =IF(AL7>=$B$5,1,0)
A10: Pilote en cours ? (1 = oui) | B10: 0/1 | C10: =IF(AND(C7>=Hypothèses!$E$8,C7<$B$5),1,0) | D10: =IF(AND(D7>=Hypothèses!$E$8,D7<$B$5),1,0) | E10: =IF(AND(E7>=Hypothèses!$E$8,E7<$B$5),1,0) | F10: =IF(AND(F7>=Hypothèses!$E$8,F7<$B$5),1,0) | G10: =IF(AND(G7>=Hypothèses!$E$8,G7<$B$5),1,0) | H10: =IF(AND(H7>=Hypothèses!$E$8,H7<$B$5),1,0) | I10: =IF(AND(I7>=Hypothèses!$E$8,I7<$B$5),1,0) | J10: =IF(AND(J7>=Hypothèses!$E$8,J7<$B$5),1,0) | ... AL10: =IF(AND(AL7>=Hypothèses!$E$8,AL7<$B$5),1,0)
A11: Budget d'acquisition du mois | B11: € HT | C11: =IF(C9=1,IF(C7<=12,Hypothèses!$E$20,IF(C7<=24,Hypothèses!$E$21,Hypothèses!$E$22)),0) | D11: =IF(D9=1,IF(D7<=12,Hypothèses!$E$20,IF(D7<=24,Hypothèses!$E$21,Hypothèses!$E$22)),0) | E11: =IF(E9=1,IF(E7<=12,Hypothèses!$E$20,IF(E7<=24,Hypothèses!$E$21,Hypothèses!$E$22)),0) | F11: =IF(F9=1,IF(F7<=12,Hypothèses!$E$20,IF(F7<=24,Hypothèses!$E$21,Hypothèses!$E$22)),0) | G11: =IF(G9=1,IF(G7<=12,Hypothèses!$E$20,IF(G7<=24,Hypothèses!$E$21,Hypothèses!$E$22)),0) | H11: =IF(H9=1,IF(H7<=12,Hypothèses!$E$20,IF(H7<=24,Hypothèses!$E$21,Hypothèses!$E$22)),0) | I11: =IF(I9=1,IF(I7<=12,Hypothèses!$E$20,IF(I7<=24,Hypothèses!$E$21,Hypothèses!$E$22)),0) | J11: =IF(J9=1,IF(J7<=12,Hypothèses!$E$20,IF(J7<=24,Hypothèses!$E$21,Hypothèses!$E$22)),0) | ... AL11: =IF(AL9=1,IF(AL7<=12,Hypothèses!$E$20,IF(AL7<=24,Hypothèses!$E$21,Hypothèses!$E$22)),0) | AN11: =SUM(C11:N11) | AO11: =SUM(O11:Z11) | AP11: =SUM(AA11:AL11)
A12: Abonnés
A13: Abonnés en début de mois | B13: abonnés | C13: =0 | D13: =C18 | E13: =D18 | F13: =E18 | G13: =F18 | H13: =G18 | I13: =H18 | J13: =I18 | K13: =J18 | ... AL13: =AK18
A14: Nouveaux abonnés par acquisition payante | B14: abonnés | C14: =C11/(Hypothèses!$E$23*$E$4) | D14: =D11/(Hypothèses!$E$23*$E$4) | E14: =E11/(Hypothèses!$E$23*$E$4) | F14: =F11/(Hypothèses!$E$23*$E$4) | G14: =G11/(Hypothèses!$E$23*$E$4) | H14: =H11/(Hypothèses!$E$23*$E$4) | I14: =I11/(Hypothèses!$E$23*$E$4) | J14: =J11/(Hypothèses!$E$23*$E$4) | ... AL14: =AL11/(Hypothèses!$E$23*$E$4) | AN14: =SUM(C14:N14) | AO14: =SUM(O14:Z14) | AP14: =SUM(AA14:AL14)
A15: Nouveaux abonnés pilote | B15: abonnés | C15: =IF(C7=Hypothèses!$E$8,Hypothèses!$E$9,0) | D15: =IF(D7=Hypothèses!$E$8,Hypothèses!$E$9,0) | E15: =IF(E7=Hypothèses!$E$8,Hypothèses!$E$9,0) | F15: =IF(F7=Hypothèses!$E$8,Hypothèses!$E$9,0) | G15: =IF(G7=Hypothèses!$E$8,Hypothèses!$E$9,0) | H15: =IF(H7=Hypothèses!$E$8,Hypothèses!$E$9,0) | I15: =IF(I7=Hypothèses!$E$8,Hypothèses!$E$9,0) | J15: =IF(J7=Hypothèses!$E$8,Hypothèses!$E$9,0) | ... AL15: =IF(AL7=Hypothèses!$E$8,Hypothèses!$E$9,0) | AN15: =SUM(C15:N15) | AO15: =SUM(O15:Z15) | AP15: =SUM(AA15:AL15)
A16: Nouveaux abonnés organiques (parrainage) | B16: abonnés | C16: =C9*C13*Hypothèses!$E$24 | D16: =D9*D13*Hypothèses!$E$24 | E16: =E9*E13*Hypothèses!$E$24 | F16: =F9*F13*Hypothèses!$E$24 | G16: =G9*G13*Hypothèses!$E$24 | H16: =H9*H13*Hypothèses!$E$24 | I16: =I9*I13*Hypothèses!$E$24 | J16: =J9*J13*Hypothèses!$E$24 | ... AL16: =AL9*AL13*Hypothèses!$E$24 | AN16: =SUM(C16:N16) | AO16: =SUM(O16:Z16) | AP16: =SUM(AA16:AL16)
A17: Résiliations | B17: abonnés | C17: =C13*Hypothèses!$E$26*$D$4 | D17: =D13*Hypothèses!$E$26*$D$4 | E17: =E13*Hypothèses!$E$26*$D$4 | F17: =F13*Hypothèses!$E$26*$D$4 | G17: =G13*Hypothèses!$E$26*$D$4 | H17: =H13*Hypothèses!$E$26*$D$4 | I17: =I13*Hypothèses!$E$26*$D$4 | J17: =J13*Hypothèses!$E$26*$D$4 | ... AL17: =AL13*Hypothèses!$E$26*$D$4 | AN17: =SUM(C17:N17) | AO17: =SUM(O17:Z17) | AP17: =SUM(AA17:AL17)
A18: Abonnés en fin de mois | B18: abonnés | C18: =C13+C14+C15+C16-C17 | D18: =D13+D14+D15+D16-D17 | E18: =E13+E14+E15+E16-E17 | F18: =F13+F14+F15+F16-F17 | G18: =G13+G14+G15+G16-G17 | H18: =H13+H14+H15+H16-H17 | I18: =I13+I14+I15+I16-I17 | J18: =J13+J14+J15+J16-J17 | ... AL18: =AL13+AL14+AL15+AL16-AL17 | AN18: =N18 | AO18: =Z18 | AP18: =AL18
A19: dont Personal | B19: abonnés | C19: =C18*Hypothèses!$E$16 | D19: =D18*Hypothèses!$E$16 | E19: =E18*Hypothèses!$E$16 | F19: =F18*Hypothèses!$E$16 | G19: =G18*Hypothèses!$E$16 | H19: =H18*Hypothèses!$E$16 | I19: =I18*Hypothèses!$E$16 | J19: =J18*Hypothèses!$E$16 | ... AL19: =AL18*Hypothèses!$E$16 | AN19: =N19 | AO19: =Z19 | AP19: =AL19
A20: dont Premium | B20: abonnés | C20: =C18*Hypothèses!$E$17 | D20: =D18*Hypothèses!$E$17 | E20: =E18*Hypothèses!$E$17 | F20: =F18*Hypothèses!$E$17 | G20: =G18*Hypothèses!$E$17 | H20: =H18*Hypothèses!$E$17 | I20: =I18*Hypothèses!$E$17 | J20: =J18*Hypothèses!$E$17 | ... AL20: =AL18*Hypothèses!$E$17 | AN20: =N20 | AO20: =Z20 | AP20: =AL20
A21: dont Family | B21: abonnés | C21: =C18*Hypothèses!$E$18 | D21: =D18*Hypothèses!$E$18 | E21: =E18*Hypothèses!$E$18 | F21: =F18*Hypothèses!$E$18 | G21: =G18*Hypothèses!$E$18 | H21: =H18*Hypothèses!$E$18 | I21: =I18*Hypothèses!$E$18 | J21: =J18*Hypothèses!$E$18 | ... AL21: =AL18*Hypothèses!$E$18 | AN21: =N21 | AO21: =Z21 | AP21: =AL21
A22: Revenus
A23: Facturation Personal TTC | B23: € TTC | C23: =C19*Hypothèses!$E$12*$C$4 | D23: =D19*Hypothèses!$E$12*$C$4 | E23: =E19*Hypothèses!$E$12*$C$4 | F23: =F19*Hypothèses!$E$12*$C$4 | G23: =G19*Hypothèses!$E$12*$C$4 | H23: =H19*Hypothèses!$E$12*$C$4 | I23: =I19*Hypothèses!$E$12*$C$4 | J23: =J19*Hypothèses!$E$12*$C$4 | ... AL23: =AL19*Hypothèses!$E$12*$C$4 | AN23: =SUM(C23:N23) | AO23: =SUM(O23:Z23) | AP23: =SUM(AA23:AL23)
A24: Facturation Premium TTC | B24: € TTC | C24: =C20*Hypothèses!$E$13*$C$4 | D24: =D20*Hypothèses!$E$13*$C$4 | E24: =E20*Hypothèses!$E$13*$C$4 | F24: =F20*Hypothèses!$E$13*$C$4 | G24: =G20*Hypothèses!$E$13*$C$4 | H24: =H20*Hypothèses!$E$13*$C$4 | I24: =I20*Hypothèses!$E$13*$C$4 | J24: =J20*Hypothèses!$E$13*$C$4 | ... AL24: =AL20*Hypothèses!$E$13*$C$4 | AN24: =SUM(C24:N24) | AO24: =SUM(O24:Z24) | AP24: =SUM(AA24:AL24)
A25: Facturation Family TTC | B25: € TTC | C25: =C21*Hypothèses!$E$14*$C$4 | D25: =D21*Hypothèses!$E$14*$C$4 | E25: =E21*Hypothèses!$E$14*$C$4 | F25: =F21*Hypothèses!$E$14*$C$4 | G25: =G21*Hypothèses!$E$14*$C$4 | H25: =H21*Hypothèses!$E$14*$C$4 | I25: =I21*Hypothèses!$E$14*$C$4 | J25: =J21*Hypothèses!$E$14*$C$4 | ... AL25: =AL21*Hypothèses!$E$14*$C$4 | AN25: =SUM(C25:N25) | AO25: =SUM(O25:Z25) | AP25: =SUM(AA25:AL25)
A26: Facturation totale TTC (MRR TTC) | B26: € TTC | C26: =C23+C24+C25 | D26: =D23+D24+D25 | E26: =E23+E24+E25 | F26: =F23+F24+F25 | G26: =G23+G24+G25 | H26: =H23+H24+H25 | I26: =I23+I24+I25 | J26: =J23+J24+J25 | ... AL26: =AL23+AL24+AL25 | AN26: =SUM(C26:N26) | AO26: =SUM(O26:Z26) | AP26: =SUM(AA26:AL26)
A27: TVA collectée | B27: € | C27: =C26*Hypothèses!$E$15/(1+Hypothèses!$E$15) | D27: =D26*Hypothèses!$E$15/(1+Hypothèses!$E$15) | E27: =E26*Hypothèses!$E$15/(1+Hypothèses!$E$15) | F27: =F26*Hypothèses!$E$15/(1+Hypothèses!$E$15) | G27: =G26*Hypothèses!$E$15/(1+Hypothèses!$E$15) | H27: =H26*Hypothèses!$E$15/(1+Hypothèses!$E$15) | I27: =I26*Hypothèses!$E$15/(1+Hypothèses!$E$15) | J27: =J26*Hypothèses!$E$15/(1+Hypothèses!$E$15) | ... AL27: =AL26*Hypothèses!$E$15/(1+Hypothèses!$E$15) | AN27: =SUM(C27:N27) | AO27: =SUM(O27:Z27) | AP27: =SUM(AA27:AL27)
A28: Chiffre d'affaires HT | B28: € HT | C28: =C26-C27 | D28: =D26-D27 | E28: =E26-E27 | F28: =F26-F27 | G28: =G26-G27 | H28: =H26-H27 | I28: =I26-I27 | J28: =J26-J27 | ... AL28: =AL26-AL27 | AN28: =SUM(C28:N28) | AO28: =SUM(O28:Z28) | AP28: =SUM(AA28:AL28)
A29: Impayés (TTC) | B29: € TTC | C29: =C26*Hypothèses!$E$27 | D29: =D26*Hypothèses!$E$27 | E29: =E26*Hypothèses!$E$27 | F29: =F26*Hypothèses!$E$27 | G29: =G26*Hypothèses!$E$27 | H29: =H26*Hypothèses!$E$27 | I29: =I26*Hypothèses!$E$27 | J29: =J26*Hypothèses!$E$27 | ... AL29: =AL26*Hypothèses!$E$27 | AN29: =SUM(C29:N29) | AO29: =SUM(O29:Z29) | AP29: =SUM(AA29:AL29)
A30: Frais de paiement | B30: € | C30: =(C26-C29)*Hypothèses!$E$28+C18*Hypothèses!$E$29 | D30: =(D26-D29)*Hypothèses!$E$28+D18*Hypothèses!$E$29 | E30: =(E26-E29)*Hypothèses!$E$28+E18*Hypothèses!$E$29 | F30: =(F26-F29)*Hypothèses!$E$28+F18*Hypothèses!$E$29 | G30: =(G26-G29)*Hypothèses!$E$28+G18*Hypothèses!$E$29 | H30: =(H26-H29)*Hypothèses!$E$28+H18*Hypothèses!$E$29 | I30: =(I26-I29)*Hypothèses!$E$28+I18*Hypothèses!$E$29 | J30: =(J26-J29)*Hypothèses!$E$28+J18*Hypothèses!$E$29 | ... AL30: =(AL26-AL29)*Hypothèses!$E$28+AL18*Hypothèses!$E$29 | AN30: =SUM(C30:N30) | AO30: =SUM(O30:Z30) | AP30: =SUM(AA30:AL30)
A31: Encaissements nets TTC | B31: € TTC | C31: =C26-C29-C30 | D31: =D26-D29-D30 | E31: =E26-E29-E30 | F31: =F26-F29-F30 | G31: =G26-G29-G30 | H31: =H26-H29-H30 | I31: =I26-I29-I30 | J31: =J26-J29-J30 | ... AL31: =AL26-AL29-AL30 | AN31: =SUM(C31:N31) | AO31: =SUM(O31:Z31) | AP31: =SUM(AA31:AL31)
A32: Coûts variables
A33: Coût IA et outils (missions × coût par mission) | B33: € HT | C33: =(C19*Hypothèses!$E$31+C20*Hypothèses!$E$32+C21*Hypothèses!$E$33)*Hypothèses!$E$34*$F$4 | D33: =(D19*Hypothèses!$E$31+D20*Hypothèses!$E$32+D21*Hypothèses!$E$33)*Hypothèses!$E$34*$F$4 | E33: =(E19*Hypothèses!$E$31+E20*Hypothèses!$E$32+E21*Hypothèses!$E$33)*Hypothèses!$E$34*$F$4 | F33: =(F19*Hypothèses!$E$31+F20*Hypothèses!$E$32+F21*Hypothèses!$E$33)*Hypothèses!$E$34*$F$4 | G33: =(G19*Hypothèses!$E$31+G20*Hypothèses!$E$32+G21*Hypothèses!$E$33)*Hypothèses!$E$34*$F$4 | H33: =(H19*Hypothèses!$E$31+H20*Hypothèses!$E$32+H21*Hypothèses!$E$33)*Hypothèses!$E$34*$F$4 | I33: =(I19*Hypothèses!$E$31+I20*Hypothèses!$E$32+I21*Hypothèses!$E$33)*Hypothèses!$E$34*$F$4 | J33: =(J19*Hypothèses!$E$31+J20*Hypothèses!$E$32+J21*Hypothèses!$E$33)*Hypothèses!$E$34*$F$4 | ... AL33: =(AL19*Hypothèses!$E$31+AL20*Hypothèses!$E$32+AL21*Hypothèses!$E$33)*Hypothèses!$E$34*$F$4 | AN33: =SUM(C33:N33) | AO33: =SUM(O33:Z33) | AP33: =SUM(AA33:AL33)
A34: Hébergement, stockage, connecteurs | B34: € HT | C34: =C18*Hypothèses!$E$35 | D34: =D18*Hypothèses!$E$35 | E34: =E18*Hypothèses!$E$35 | F34: =F18*Hypothèses!$E$35 | G34: =G18*Hypothèses!$E$35 | H34: =H18*Hypothèses!$E$35 | I34: =I18*Hypothèses!$E$35 | J34: =J18*Hypothèses!$E$35 | ... AL34: =AL18*Hypothèses!$E$35 | AN34: =SUM(C34:N34) | AO34: =SUM(O34:Z34) | AP34: =SUM(AA34:AL34)
A35: Support humain | B35: € HT | C35: =C18*Hypothèses!$E$36 | D35: =D18*Hypothèses!$E$36 | E35: =E18*Hypothèses!$E$36 | F35: =F18*Hypothèses!$E$36 | G35: =G18*Hypothèses!$E$36 | H35: =H18*Hypothèses!$E$36 | I35: =I18*Hypothèses!$E$36 | J35: =J18*Hypothèses!$E$36 | ... AL35: =AL18*Hypothèses!$E$36 | AN35: =SUM(C35:N35) | AO35: =SUM(O35:Z35) | AP35: =SUM(AA35:AL35)
A36: Total coûts variables | B36: € HT | C36: =C33+C34+C35 | D36: =D33+D34+D35 | E36: =E33+E34+E35 | F36: =F33+F34+F35 | G36: =G33+G34+G35 | H36: =H33+H34+H35 | I36: =I33+I34+I35 | J36: =J33+J34+J35 | ... AL36: =AL33+AL34+AL35 | AN36: =SUM(C36:N36) | AO36: =SUM(O36:Z36) | AP36: =SUM(AA36:AL36)
A37: Marge sur coûts variables (CA HT − variables − frais − impayés HT) | B37: € HT | C37: =C28-C36-C30-C29/(1+Hypothèses!$E$15) | D37: =D28-D36-D30-D29/(1+Hypothèses!$E$15) | E37: =E28-E36-E30-E29/(1+Hypothèses!$E$15) | F37: =F28-F36-F30-F29/(1+Hypothèses!$E$15) | G37: =G28-G36-G30-G29/(1+Hypothèses!$E$15) | H37: =H28-H36-H30-H29/(1+Hypothèses!$E$15) | I37: =I28-I36-I30-I29/(1+Hypothèses!$E$15) | J37: =J28-J36-J30-J29/(1+Hypothèses!$E$15) | ... AL37: =AL28-AL36-AL30-AL29/(1+Hypothèses!$E$15) | AN37: =SUM(C37:N37) | AO37: =SUM(O37:Z37) | AP37: =SUM(AA37:AL37)
A38: Acquisition et coûts fixes
A39: Dépenses d'acquisition | B39: € HT | C39: =C11 | D39: =D11 | E39: =E11 | F39: =F11 | G39: =G11 | H39: =H11 | I39: =I11 | J39: =J11 | ... AL39: =AL11 | AN39: =SUM(C39:N39) | AO39: =SUM(O39:Z39) | AP39: =SUM(AA39:AL39)
A40: Rémunération des fondateurs | B40: € HT | C40: =IF(C7>=Hypothèses!$E$39,Hypothèses!$E$38*Hypothèses!$E$40,0)*$G$4 | D40: =IF(D7>=Hypothèses!$E$39,Hypothèses!$E$38*Hypothèses!$E$40,0)*$G$4 | E40: =IF(E7>=Hypothèses!$E$39,Hypothèses!$E$38*Hypothèses!$E$40,0)*$G$4 | F40: =IF(F7>=Hypothèses!$E$39,Hypothèses!$E$38*Hypothèses!$E$40,0)*$G$4 | G40: =IF(G7>=Hypothèses!$E$39,Hypothèses!$E$38*Hypothèses!$E$40,0)*$G$4 | H40: =IF(H7>=Hypothèses!$E$39,Hypothèses!$E$38*Hypothèses!$E$40,0)*$G$4 | I40: =IF(I7>=Hypothèses!$E$39,Hypothèses!$E$38*Hypothèses!$E$40,0)*$G$4 | J40: =IF(J7>=Hypothèses!$E$39,Hypothèses!$E$38*Hypothèses!$E$40,0)*$G$4 | ... AL40: =IF(AL7>=Hypothèses!$E$39,Hypothèses!$E$38*Hypothèses!$E$40,0)*$G$4 | AN40: =SUM(C40:N40) | AO40: =SUM(O40:Z40) | AP40: =SUM(AA40:AL40)
A41: Salarié 1 (growth / customer success) | B41: € HT | C41: =IF(C7>=Hypothèses!$E$41,Hypothèses!$E$42,0)*$G$4 | D41: =IF(D7>=Hypothèses!$E$41,Hypothèses!$E$42,0)*$G$4 | E41: =IF(E7>=Hypothèses!$E$41,Hypothèses!$E$42,0)*$G$4 | F41: =IF(F7>=Hypothèses!$E$41,Hypothèses!$E$42,0)*$G$4 | G41: =IF(G7>=Hypothèses!$E$41,Hypothèses!$E$42,0)*$G$4 | H41: =IF(H7>=Hypothèses!$E$41,Hypothèses!$E$42,0)*$G$4 | I41: =IF(I7>=Hypothèses!$E$41,Hypothèses!$E$42,0)*$G$4 | J41: =IF(J7>=Hypothèses!$E$41,Hypothèses!$E$42,0)*$G$4 | ... AL41: =IF(AL7>=Hypothèses!$E$41,Hypothèses!$E$42,0)*$G$4 | AN41: =SUM(C41:N41) | AO41: =SUM(O41:Z41) | AP41: =SUM(AA41:AL41)
A42: Salarié 2 (ingénieur) | B42: € HT | C42: =IF(C7>=Hypothèses!$E$43,Hypothèses!$E$44,0)*$G$4 | D42: =IF(D7>=Hypothèses!$E$43,Hypothèses!$E$44,0)*$G$4 | E42: =IF(E7>=Hypothèses!$E$43,Hypothèses!$E$44,0)*$G$4 | F42: =IF(F7>=Hypothèses!$E$43,Hypothèses!$E$44,0)*$G$4 | G42: =IF(G7>=Hypothèses!$E$43,Hypothèses!$E$44,0)*$G$4 | H42: =IF(H7>=Hypothèses!$E$43,Hypothèses!$E$44,0)*$G$4 | I42: =IF(I7>=Hypothèses!$E$43,Hypothèses!$E$44,0)*$G$4 | J42: =IF(J7>=Hypothèses!$E$43,Hypothèses!$E$44,0)*$G$4 | ... AL42: =IF(AL7>=Hypothèses!$E$43,Hypothèses!$E$44,0)*$G$4 | AN42: =SUM(C42:N42) | AO42: =SUM(O42:Z42) | AP42: =SUM(AA42:AL42)
A43: Développement MVP externe (étalé jusqu'au lancement) | B43: € HT | C43: =IF(C7<$B$5,Hypothèses!$E$45/MAX(1,$B$5-1),0) | D43: =IF(D7<$B$5,Hypothèses!$E$45/MAX(1,$B$5-1),0) | E43: =IF(E7<$B$5,Hypothèses!$E$45/MAX(1,$B$5-1),0) | F43: =IF(F7<$B$5,Hypothèses!$E$45/MAX(1,$B$5-1),0) | G43: =IF(G7<$B$5,Hypothèses!$E$45/MAX(1,$B$5-1),0) | H43: =IF(H7<$B$5,Hypothèses!$E$45/MAX(1,$B$5-1),0) | I43: =IF(I7<$B$5,Hypothèses!$E$45/MAX(1,$B$5-1),0) | J43: =IF(J7<$B$5,Hypothèses!$E$45/MAX(1,$B$5-1),0) | ... AL43: =IF(AL7<$B$5,Hypothèses!$E$45/MAX(1,$B$5-1),0) | AN43: =SUM(C43:N43) | AO43: =SUM(O43:Z43) | AP43: =SUM(AA43:AL43)
A44: Outils et SaaS | B44: € HT | C44: =Hypothèses!$E$46*$G$4 | D44: =Hypothèses!$E$46*$G$4 | E44: =Hypothèses!$E$46*$G$4 | F44: =Hypothèses!$E$46*$G$4 | G44: =Hypothèses!$E$46*$G$4 | H44: =Hypothèses!$E$46*$G$4 | I44: =Hypothèses!$E$46*$G$4 | J44: =Hypothèses!$E$46*$G$4 | ... AL44: =Hypothèses!$E$46*$G$4 | AN44: =SUM(C44:N44) | AO44: =SUM(O44:Z44) | AP44: =SUM(AA44:AL44)
A45: Juridique et comptabilité | B45: € HT | C45: =Hypothèses!$E$47*$G$4 | D45: =Hypothèses!$E$47*$G$4 | E45: =Hypothèses!$E$47*$G$4 | F45: =Hypothèses!$E$47*$G$4 | G45: =Hypothèses!$E$47*$G$4 | H45: =Hypothèses!$E$47*$G$4 | I45: =Hypothèses!$E$47*$G$4 | J45: =Hypothèses!$E$47*$G$4 | ... AL45: =Hypothèses!$E$47*$G$4 | AN45: =SUM(C45:N45) | AO45: =SUM(O45:Z45) | AP45: =SUM(AA45:AL45)
A46: Assurance RC pro | B46: € | C46: =C9*Hypothèses!$E$48*$G$4 | D46: =D9*Hypothèses!$E$48*$G$4 | E46: =E9*Hypothèses!$E$48*$G$4 | F46: =F9*Hypothèses!$E$48*$G$4 | G46: =G9*Hypothèses!$E$48*$G$4 | H46: =H9*Hypothèses!$E$48*$G$4 | I46: =I9*Hypothèses!$E$48*$G$4 | J46: =J9*Hypothèses!$E$48*$G$4 | ... AL46: =AL9*Hypothèses!$E$48*$G$4 | AN46: =SUM(C46:N46) | AO46: =SUM(O46:Z46) | AP46: =SUM(AA46:AL46)
A47: Marketing fixe | B47: € HT | C47: =C9*Hypothèses!$E$49*$G$4 | D47: =D9*Hypothèses!$E$49*$G$4 | E47: =E9*Hypothèses!$E$49*$G$4 | F47: =F9*Hypothèses!$E$49*$G$4 | G47: =G9*Hypothèses!$E$49*$G$4 | H47: =H9*Hypothèses!$E$49*$G$4 | I47: =I9*Hypothèses!$E$49*$G$4 | J47: =J9*Hypothèses!$E$49*$G$4 | ... AL47: =AL9*Hypothèses!$E$49*$G$4 | AN47: =SUM(C47:N47) | AO47: =SUM(O47:Z47) | AP47: =SUM(AA47:AL47)
A48: Frais généraux | B48: € HT | C48: =Hypothèses!$E$50*$G$4 | D48: =Hypothèses!$E$50*$G$4 | E48: =Hypothèses!$E$50*$G$4 | F48: =Hypothèses!$E$50*$G$4 | G48: =Hypothèses!$E$50*$G$4 | H48: =Hypothèses!$E$50*$G$4 | I48: =Hypothèses!$E$50*$G$4 | J48: =Hypothèses!$E$50*$G$4 | ... AL48: =Hypothèses!$E$50*$G$4 | AN48: =SUM(C48:N48) | AO48: =SUM(O48:Z48) | AP48: =SUM(AA48:AL48)
A49: Audit de sécurité (annuel, à partir du lancement) | B49: € HT | C49: =IF(AND(C9=1,MOD(C7-$B$5,12)=0),Hypothèses!$E$51,0)*$G$4 | D49: =IF(AND(D9=1,MOD(D7-$B$5,12)=0),Hypothèses!$E$51,0)*$G$4 | E49: =IF(AND(E9=1,MOD(E7-$B$5,12)=0),Hypothèses!$E$51,0)*$G$4 | F49: =IF(AND(F9=1,MOD(F7-$B$5,12)=0),Hypothèses!$E$51,0)*$G$4 | G49: =IF(AND(G9=1,MOD(G7-$B$5,12)=0),Hypothèses!$E$51,0)*$G$4 | H49: =IF(AND(H9=1,MOD(H7-$B$5,12)=0),Hypothèses!$E$51,0)*$G$4 | I49: =IF(AND(I9=1,MOD(I7-$B$5,12)=0),Hypothèses!$E$51,0)*$G$4 | J49: =IF(AND(J9=1,MOD(J7-$B$5,12)=0),Hypothèses!$E$51,0)*$G$4 | ... AL49: =IF(AND(AL9=1,MOD(AL7-$B$5,12)=0),Hypothèses!$E$51,0)*$G$4 | AN49: =SUM(C49:N49) | AO49: =SUM(O49:Z49) | AP49: =SUM(AA49:AL49)
A50: Frais de constitution | B50: € HT | C50: =IF(C7=2,Hypothèses!$E$52,0) | D50: =IF(D7=2,Hypothèses!$E$52,0) | E50: =IF(E7=2,Hypothèses!$E$52,0) | F50: =IF(F7=2,Hypothèses!$E$52,0) | G50: =IF(G7=2,Hypothèses!$E$52,0) | H50: =IF(H7=2,Hypothèses!$E$52,0) | I50: =IF(I7=2,Hypothèses!$E$52,0) | J50: =IF(J7=2,Hypothèses!$E$52,0) | ... AL50: =IF(AL7=2,Hypothèses!$E$52,0) | AN50: =SUM(C50:N50) | AO50: =SUM(O50:Z50) | AP50: =SUM(AA50:AL50)
A51: Total coûts fixes | B51: € HT | C51: =SUM(C40:C50) | D51: =SUM(D40:D50) | E51: =SUM(E40:E50) | F51: =SUM(F40:F50) | G51: =SUM(G40:G50) | H51: =SUM(H40:H50) | I51: =SUM(I40:I50) | J51: =SUM(J40:J50) | ... AL51: =SUM(AL40:AL50) | AN51: =SUM(C51:N51) | AO51: =SUM(O51:Z51) | AP51: =SUM(AA51:AL51)
A52: EBITDA (marge variable − acquisition − fixes) | B52: € HT | C52: =C37-C39-C51 | D52: =D37-D39-D51 | E52: =E37-E39-E51 | F52: =F37-F39-F51 | G52: =G37-G39-G51 | H52: =H37-H39-H51 | I52: =I37-I39-I51 | J52: =J37-J39-J51 | ... AL52: =AL37-AL39-AL51 | AN52: =SUM(C52:N52) | AO52: =SUM(O52:Z52) | AP52: =SUM(AA52:AL52)
A53: EBITDA positif ? (1 = oui) | B53: 0/1 | C53: =IF(C52>0,1,0) | D53: =IF(D52>0,1,0) | E53: =IF(E52>0,1,0) | F53: =IF(F52>0,1,0) | G53: =IF(G52>0,1,0) | H53: =IF(H52>0,1,0) | I53: =IF(I52>0,1,0) | J53: =IF(J52>0,1,0) | ... AL53: =IF(AL52>0,1,0)
A54: Trésorerie
A55: TVA collectée reversée (mois suivant) | B55: € | C55: =0 | D55: =C27 | E55: =D27 | F55: =E27 | G55: =F27 | H55: =G27 | I55: =H27 | J55: =I27 | K55: =J27 | ... AL55: =AK27 | AN55: =SUM(C55:N55) | AO55: =SUM(O55:Z55) | AP55: =SUM(AA55:AL55)
A56: TVA déductible récupérée (mois suivant, coûts externes) | B56: € | C56: =0 | D56: =(C36+C39+C43+C44+C45+C47+C48+C49+C50)*Hypothèses!$E$15 | E56: =(D36+D39+D43+D44+D45+D47+D48+D49+D50)*Hypothèses!$E$15 | F56: =(E36+E39+E43+E44+E45+E47+E48+E49+E50)*Hypothèses!$E$15 | G56: =(F36+F39+F43+F44+F45+F47+F48+F49+F50)*Hypothèses!$E$15 | H56: =(G36+G39+G43+G44+G45+G47+G48+G49+G50)*Hypothèses!$E$15 | I56: =(H36+H39+H43+H44+H45+H47+H48+H49+H50)*Hypothèses!$E$15 | J56: =(I36+I39+I43+I44+I45+I47+I48+I49+I50)*Hypothèses!$E$15 | K56: =(J36+J39+J43+J44+J45+J47+J48+J49+J50)*Hypothèses!$E$15 | ... AL56: =(AK36+AK39+AK43+AK44+AK45+AK47+AK48+AK49+AK50)*Hypothèses!$E$15 | AN56: =SUM(C56:N56) | AO56: =SUM(O56:Z56) | AP56: =SUM(AA56:AL56)
A57: Financement reçu | B57: € | C57: =Hypothèses!$E$56*(IF(C7=Hypothèses!$E$57,Hypothèses!$E$58,0)+IF(C7=Hypothèses!$E$59,Hypothèses!$E$60,0)+IF(C7=Hypothèses!$E$61,Hypothèses!$E$62,0)) | D57: =Hypothèses!$E$56*(IF(D7=Hypothèses!$E$57,Hypothèses!$E$58,0)+IF(D7=Hypothèses!$E$59,Hypothèses!$E$60,0)+IF(D7=Hypothèses!$E$61,Hypothèses!$E$62,0)) | E57: =Hypothèses!$E$56*(IF(E7=Hypothèses!$E$57,Hypothèses!$E$58,0)+IF(E7=Hypothèses!$E$59,Hypothèses!$E$60,0)+IF(E7=Hypothèses!$E$61,Hypothèses!$E$62,0)) | F57: =Hypothèses!$E$56*(IF(F7=Hypothèses!$E$57,Hypothèses!$E$58,0)+IF(F7=Hypothèses!$E$59,Hypothèses!$E$60,0)+IF(F7=Hypothèses!$E$61,Hypothèses!$E$62,0)) | G57: =Hypothèses!$E$56*(IF(G7=Hypothèses!$E$57,Hypothèses!$E$58,0)+IF(G7=Hypothèses!$E$59,Hypothèses!$E$60,0)+IF(G7=Hypothèses!$E$61,Hypothèses!$E$62,0)) | H57: =Hypothèses!$E$56*(IF(H7=Hypothèses!$E$57,Hypothèses!$E$58,0)+IF(H7=Hypothèses!$E$59,Hypothèses!$E$60,0)+IF(H7=Hypothèses!$E$61,Hypothèses!$E$62,0)) | I57: =Hypothèses!$E$56*(IF(I7=Hypothèses!$E$57,Hypothèses!$E$58,0)+IF(I7=Hypothèses!$E$59,Hypothèses!$E$60,0)+IF(I7=Hypothèses!$E$61,Hypothèses!$E$62,0)) | J57: =Hypothèses!$E$56*(IF(J7=Hypothèses!$E$57,Hypothèses!$E$58,0)+IF(J7=Hypothèses!$E$59,Hypothèses!$E$60,0)+IF(J7=Hypothèses!$E$61,Hypothèses!$E$62,0)) | ... AL57: =Hypothèses!$E$56*(IF(AL7=Hypothèses!$E$57,Hypothèses!$E$58,0)+IF(AL7=Hypothèses!$E$59,Hypothèses!$E$60,0)+IF(AL7=Hypothèses!$E$61,Hypothèses!$E$62,0)) | AN57: =SUM(C57:N57) | AO57: =SUM(O57:Z57) | AP57: =SUM(AA57:AL57)
A58: Trésorerie d'ouverture | B58: € | C58: =Hypothèses!$E$54 | D58: =C60 | E58: =D60 | F58: =E60 | G58: =F60 | H58: =G60 | I58: =H60 | J58: =I60 | K58: =J60 | ... AL58: =AK60
A59: Flux de trésorerie du mois | B59: € | C59: =C31-C36-C39-C51-C55+C56+C57 | D59: =D31-D36-D39-D51-D55+D56+D57 | E59: =E31-E36-E39-E51-E55+E56+E57 | F59: =F31-F36-F39-F51-F55+F56+F57 | G59: =G31-G36-G39-G51-G55+G56+G57 | H59: =H31-H36-H39-H51-H55+H56+H57 | I59: =I31-I36-I39-I51-I55+I56+I57 | J59: =J31-J36-J39-J51-J55+J56+J57 | ... AL59: =AL31-AL36-AL39-AL51-AL55+AL56+AL57 | AN59: =SUM(C59:N59) | AO59: =SUM(O59:Z59) | AP59: =SUM(AA59:AL59)
A60: Trésorerie de clôture | B60: € | C60: =C58+C59 | D60: =D58+D59 | E60: =E58+E59 | F60: =F58+F59 | G60: =G58+G59 | H60: =H58+H59 | I60: =I58+I59 | J60: =J58+J59 | ... AL60: =AL58+AL59 | AN60: =N60 | AO60: =Z60 | AP60: =AL60
A61: Financement cumulé | B61: € | C61: =0+C57 | D61: =C61+D57 | E61: =D61+E57 | F61: =E61+F57 | G61: =F61+G57 | H61: =G61+H57 | I61: =H61+I57 | J61: =I61+J57 | K61: =J61+K57 | ... AL61: =AK61+AL57 | AN61: =N61 | AO61: =Z61 | AP61: =AL61
A62: Trésorerie cumulée hors financement | B62: € | C62: =C60-C61 | D62: =D60-D61 | E62: =E60-E61 | F62: =F60-F61 | G62: =G60-G61 | H62: =H60-H61 | I62: =I60-I61 | J62: =J60-J61 | ... AL62: =AL60-AL61 | AN62: =N62 | AO62: =Z62 | AP62: =AL62
A63: Point bas glissant hors financement | B63: € | C63: =C62 | D63: =MIN(C63,D62) | E63: =MIN(D63,E62) | F63: =MIN(E63,F62) | G63: =MIN(F63,G62) | H63: =MIN(G63,H62) | I63: =MIN(H63,I62) | J63: =MIN(I63,J62) | K63: =MIN(J63,K62) | ... AL63: =MIN(AK63,AL62) | AN63: =N63 | AO63: =Z63 | AP63: =AL63
A64: Trésorerie cumulée hors financement positive après lancement ? (1 = oui) | B64: 0/1 | C64: =IF(AND(C9=1,C62>0),1,0) | D64: =IF(AND(D9=1,D62>0),1,0) | E64: =IF(AND(E9=1,E62>0),1,0) | F64: =IF(AND(F9=1,F62>0),1,0) | G64: =IF(AND(G9=1,G62>0),1,0) | H64: =IF(AND(H9=1,H62>0),1,0) | I64: =IF(AND(I9=1,I62>0),1,0) | J64: =IF(AND(J9=1,J62>0),1,0) | ... AL64: =IF(AND(AL9=1,AL62>0),1,0)
A65: Indicateurs
A66: ARR HT instantané (CA HT × 12) | B66: € HT | C66: =C28*12 | D66: =D28*12 | E66: =E28*12 | F66: =F28*12 | G66: =G28*12 | H66: =H28*12 | I66: =I28*12 | J66: =J28*12 | ... AL66: =AL28*12 | AN66: =N66 | AO66: =Z66 | AP66: =AL66
A67: ARPA HT (CA HT / abonnés) | B67: € HT | C67: =IF(C18>0,C28/C18,0) | D67: =IF(D18>0,D28/D18,0) | E67: =IF(E18>0,E28/E18,0) | F67: =IF(F18>0,F28/F18,0) | G67: =IF(G18>0,G28/G18,0) | H67: =IF(H18>0,H28/H18,0) | I67: =IF(I18>0,I28/I18,0) | J67: =IF(J18>0,J28/J18,0) | ... AL67: =IF(AL18>0,AL28/AL18,0) | AN67: =N67 | AO67: =Z67 | AP67: =AL67
A68: Coût variable par abonné | B68: € HT | C68: =IF(C18>0,C36/C18,0) | D68: =IF(D18>0,D36/D18,0) | E68: =IF(E18>0,E36/E18,0) | F68: =IF(F18>0,F36/F18,0) | G68: =IF(G18>0,G36/G18,0) | H68: =IF(H18>0,H36/H18,0) | I68: =IF(I18>0,I36/I18,0) | J68: =IF(J18>0,J36/J18,0) | ... AL68: =IF(AL18>0,AL36/AL18,0) | AN68: =N68 | AO68: =Z68 | AP68: =AL68
A69: Contribution par abonné | B69: € HT | C69: =IF(C18>0,C37/C18,0) | D69: =IF(D18>0,D37/D18,0) | E69: =IF(E18>0,E37/E18,0) | F69: =IF(F18>0,F37/F18,0) | G69: =IF(G18>0,G37/G18,0) | H69: =IF(H18>0,H37/H18,0) | I69: =IF(I18>0,I37/I18,0) | J69: =IF(J18>0,J37/J18,0) | ... AL69: =IF(AL18>0,AL37/AL18,0) | AN69: =N69 | AO69: =Z69 | AP69: =AL69
A70: Marge variable (% du CA HT) | B70: % | C70: =IF(C28>0,C37/C28,0) | D70: =IF(D28>0,D37/D28,0) | E70: =IF(E28>0,E37/E28,0) | F70: =IF(F28>0,F37/F28,0) | G70: =IF(G28>0,G37/G28,0) | H70: =IF(H28>0,H37/H28,0) | I70: =IF(I28>0,I37/I28,0) | J70: =IF(J28>0,J37/J28,0) | ... AL70: =IF(AL28>0,AL37/AL28,0) | AN70: =N70 | AO70: =Z70 | AP70: =AL70
A71: CAC effectif | B71: € | C71: =IF(C14>0,C39/C14,0) | D71: =IF(D14>0,D39/D14,0) | E71: =IF(E14>0,E39/E14,0) | F71: =IF(F14>0,F39/F14,0) | G71: =IF(G14>0,G39/G14,0) | H71: =IF(H14>0,H39/H14,0) | I71: =IF(I14>0,I39/I14,0) | J71: =IF(J14>0,J39/J14,0) | ... AL71: =IF(AL14>0,AL39/AL14,0) | AN71: =N71 | AO71: =Z71 | AP71: =AL71
A72: Payback du CAC (mois) | B72: mois | C72: =IF(C69>0,Hypothèses!$E$23*$E$4/C69,0) | D72: =IF(D69>0,Hypothèses!$E$23*$E$4/D69,0) | E72: =IF(E69>0,Hypothèses!$E$23*$E$4/E69,0) | F72: =IF(F69>0,Hypothèses!$E$23*$E$4/F69,0) | G72: =IF(G69>0,Hypothèses!$E$23*$E$4/G69,0) | H72: =IF(H69>0,Hypothèses!$E$23*$E$4/H69,0) | I72: =IF(I69>0,Hypothèses!$E$23*$E$4/I69,0) | J72: =IF(J69>0,Hypothèses!$E$23*$E$4/J69,0) | ... AL72: =IF(AL69>0,Hypothèses!$E$23*$E$4/AL69,0) | AN72: =N72 | AO72: =Z72 | AP72: =AL72
A73: LTV contributive simplifiée (contribution / churn) | B73: € HT | C73: =IF(Hypothèses!$E$26*$D$4>0,C69/(Hypothèses!$E$26*$D$4),0) | D73: =IF(Hypothèses!$E$26*$D$4>0,D69/(Hypothèses!$E$26*$D$4),0) | E73: =IF(Hypothèses!$E$26*$D$4>0,E69/(Hypothèses!$E$26*$D$4),0) | F73: =IF(Hypothèses!$E$26*$D$4>0,F69/(Hypothèses!$E$26*$D$4),0) | G73: =IF(Hypothèses!$E$26*$D$4>0,G69/(Hypothèses!$E$26*$D$4),0) | H73: =IF(Hypothèses!$E$26*$D$4>0,H69/(Hypothèses!$E$26*$D$4),0) | I73: =IF(Hypothèses!$E$26*$D$4>0,I69/(Hypothèses!$E$26*$D$4),0) | J73: =IF(Hypothèses!$E$26*$D$4>0,J69/(Hypothèses!$E$26*$D$4),0) | ... AL73: =IF(Hypothèses!$E$26*$D$4>0,AL69/(Hypothèses!$E$26*$D$4),0) | AN73: =N73 | AO73: =Z73 | AP73: =AL73
A74: LTV / CAC | B74: x | C74: =IF(Hypothèses!$E$23*$E$4>0,C73/(Hypothèses!$E$23*$E$4),0) | D74: =IF(Hypothèses!$E$23*$E$4>0,D73/(Hypothèses!$E$23*$E$4),0) | E74: =IF(Hypothèses!$E$23*$E$4>0,E73/(Hypothèses!$E$23*$E$4),0) | F74: =IF(Hypothèses!$E$23*$E$4>0,F73/(Hypothèses!$E$23*$E$4),0) | G74: =IF(Hypothèses!$E$23*$E$4>0,G73/(Hypothèses!$E$23*$E$4),0) | H74: =IF(Hypothèses!$E$23*$E$4>0,H73/(Hypothèses!$E$23*$E$4),0) | I74: =IF(Hypothèses!$E$23*$E$4>0,I73/(Hypothèses!$E$23*$E$4),0) | J74: =IF(Hypothèses!$E$23*$E$4>0,J73/(Hypothèses!$E$23*$E$4),0) | ... AL74: =IF(Hypothèses!$E$23*$E$4>0,AL73/(Hypothèses!$E$23*$E$4),0) | AN74: =N74 | AO74: =Z74 | AP74: =AL74

Sheet Synthèse
A1: Synthèse des scénarios
A2: Toutes les valeurs sont calculées à partir des onglets Modèle. Trésorerie hors financement sauf mention contraire.
A4: Indicateur | B4: Unité | C4: Modèle Prudent | D4: Modèle Central | E4: Modèle Ambitieux
A5: Mois de lancement commercial | B5: mois | C5: ='Modèle Prudent'!$B$5 | D5: ='Modèle Central'!$B$5 | E5: ='Modèle Ambitieux'!$B$5
A6: Point bas de trésorerie hors financement | B6: € | C6: =MIN('Modèle Prudent'!C62:AL62) | D6: =MIN('Modèle Central'!C62:AL62) | E6: =MIN('Modèle Ambitieux'!C62:AL62)
A7: Mois du point bas | B7: mois | C7: =MATCH(MIN('Modèle Prudent'!C62:AL62),'Modèle Prudent'!C62:AL62,0) | D7: =MATCH(MIN('Modèle Central'!C62:AL62),'Modèle Central'!C62:AL62,0) | E7: =MATCH(MIN('Modèle Ambitieux'!C62:AL62),'Modèle Ambitieux'!C62:AL62,0)
A8: Besoin de financement (−point bas + réserve) | B8: € | C8: =MAX(0,-MIN('Modèle Prudent'!C62:AL62))+Hypothèses!$C$53 | D8: =MAX(0,-MIN('Modèle Central'!C62:AL62))+Hypothèses!$D$53 | E8: =MAX(0,-MIN('Modèle Ambitieux'!C62:AL62))+Hypothèses!$E$53
A9: Trésorerie cumulée hors financement fin A1 | B9: € | C9: ='Modèle Prudent'!N62 | D9: ='Modèle Central'!N62 | E9: ='Modèle Ambitieux'!N62
A10: Trésorerie cumulée hors financement fin A2 | B10: € | C10: ='Modèle Prudent'!Z62 | D10: ='Modèle Central'!Z62 | E10: ='Modèle Ambitieux'!Z62
A11: Trésorerie cumulée hors financement fin A3 | B11: € | C11: ='Modèle Prudent'!AL62 | D11: ='Modèle Central'!AL62 | E11: ='Modèle Ambitieux'!AL62
A12: Premier mois d'EBITDA positif | B12: mois | C12: =IFERROR(MATCH(1,'Modèle Prudent'!C53:AL53,0),"non atteint") | D12: =IFERROR(MATCH(1,'Modèle Central'!C53:AL53,0),"non atteint") | E12: =IFERROR(MATCH(1,'Modèle Ambitieux'!C53:AL53,0),"non atteint")
A13: Premier mois de trésorerie cumulée positive (hors financement) | B13: mois | C13: =IFERROR(MATCH(1,'Modèle Prudent'!C64:AL64,0),"non atteint") | D13: =IFERROR(MATCH(1,'Modèle Central'!C64:AL64,0),"non atteint") | E13: =IFERROR(MATCH(1,'Modèle Ambitieux'!C64:AL64,0),"non atteint")
A14: Abonnés actifs fin A1 | B14: abonnés | C14: ='Modèle Prudent'!N18 | D14: ='Modèle Central'!N18 | E14: ='Modèle Ambitieux'!N18
A15: Abonnés actifs fin A2 | B15: abonnés | C15: ='Modèle Prudent'!Z18 | D15: ='Modèle Central'!Z18 | E15: ='Modèle Ambitieux'!Z18
A16: Abonnés actifs fin A3 | B16: abonnés | C16: ='Modèle Prudent'!AL18 | D16: ='Modèle Central'!AL18 | E16: ='Modèle Ambitieux'!AL18
A17: Chiffre d'affaires HT A1 | B17: € | C17: ='Modèle Prudent'!AN28 | D17: ='Modèle Central'!AN28 | E17: ='Modèle Ambitieux'!AN28
A18: Chiffre d'affaires HT A2 | B18: € | C18: ='Modèle Prudent'!AO28 | D18: ='Modèle Central'!AO28 | E18: ='Modèle Ambitieux'!AO28
A19: Chiffre d'affaires HT A3 | B19: € | C19: ='Modèle Prudent'!AP28 | D19: ='Modèle Central'!AP28 | E19: ='Modèle Ambitieux'!AP28
A20: EBITDA A1 | B20: € | C20: ='Modèle Prudent'!AN52 | D20: ='Modèle Central'!AN52 | E20: ='Modèle Ambitieux'!AN52
A21: EBITDA A2 | B21: € | C21: ='Modèle Prudent'!AO52 | D21: ='Modèle Central'!AO52 | E21: ='Modèle Ambitieux'!AO52
A22: EBITDA A3 | B22: € | C22: ='Modèle Prudent'!AP52 | D22: ='Modèle Central'!AP52 | E22: ='Modèle Ambitieux'!AP52
A23: ARR HT instantané à M36 | B23: € | C23: ='Modèle Prudent'!AL66 | D23: ='Modèle Central'!AL66 | E23: ='Modèle Ambitieux'!AL66
A24: Coût variable par abonné à M36 | B24: € | C24: ='Modèle Prudent'!AL68 | D24: ='Modèle Central'!AL68 | E24: ='Modèle Ambitieux'!AL68
A25: Marge variable à M36 | B25: % | C25: ='Modèle Prudent'!AL70 | D25: ='Modèle Central'!AL70 | E25: ='Modèle Ambitieux'!AL70
A26: Payback du CAC à M36 | B26: mois | C26: ='Modèle Prudent'!AL72 | D26: ='Modèle Central'!AL72 | E26: ='Modèle Ambitieux'!AL72
A27: LTV / CAC à M36 | B27: x | C27: ='Modèle Prudent'!AL74 | D27: ='Modèle Central'!AL74 | E27: ='Modèle Ambitieux'!AL74
A28: Dépenses d'acquisition cumulées (36 mois) | B28: € | C28: =SUM('Modèle Prudent'!C39:AL39) | D28: =SUM('Modèle Central'!C39:AL39) | E28: =SUM('Modèle Ambitieux'!C39:AL39)
A29: Coûts fixes cumulés (36 mois) | B29: € | C29: =SUM('Modèle Prudent'!C51:AL51) | D29: =SUM('Modèle Central'!C51:AL51) | E29: =SUM('Modèle Ambitieux'!C51:AL51)
A31: Lecture : le besoin de financement est le montant à réunir avant le lancement pour ne jamais passer sous la réserve cible, si les hypothèses du scénario se réalisent. Aucun financement n'est acquis.

Sheet Tornade
A1: Sensibilité du scénario Central (tornade)
A2: Chaque cas est un onglet S01 à S10 : copie vivante du modèle Central avec un seul choc. Les écarts se recalculent.
A4: Cas | B4: Choc | C4: Point bas hors financement | D4: Écart vs Central | E4: Besoin de financement | F4: Trésorerie fin A3 hors financement | G4: 1er mois EBITDA > 0 | H4: Abonnés fin A3 | J4: Écart de trésorerie fin A3 vs Central
A5: Central (base) | B5: aucun | C5: =MIN('Modèle Central'!C62:AL62) | D5: 0 | E5: =MAX(0,-MIN('Modèle Central'!C62:AL62))+Hypothèses!$D$53 | F5: ='Modèle Central'!AL62 | G5: =IFERROR(MATCH(1,'Modèle Central'!C53:AL53,0),"non atteint") | H5: ='Modèle Central'!AL18
A6: Churn 5 % | B6: churn × 1,67 (3 % → 5 %) | C6: =MIN('S01'!C62:AL62) | D6: =C6-$C$5 | E6: =MAX(0,-MIN('S01'!C62:AL62))+Hypothèses!$D$53 | F6: ='S01'!AL62 | G6: =IFERROR(MATCH(1,'S01'!C53:AL53,0),"non atteint") | H6: ='S01'!AL18 | J6: =F6-$F$5
A7: Churn 2 % | B7: churn × 0,67 (3 % → 2 %) | C7: =MIN('S02'!C62:AL62) | D7: =C7-$C$5 | E7: =MAX(0,-MIN('S02'!C62:AL62))+Hypothèses!$D$53 | F7: ='S02'!AL62 | G7: =IFERROR(MATCH(1,'S02'!C53:AL53,0),"non atteint") | H7: ='S02'!AL18 | J7: =F7-$F$5
A8: CAC 240 € | B8: CAC × 1,6 | C8: =MIN('S03'!C62:AL62) | D8: =C8-$C$5 | E8: =MAX(0,-MIN('S03'!C62:AL62))+Hypothèses!$D$53 | F8: ='S03'!AL62 | G8: =IFERROR(MATCH(1,'S03'!C53:AL53,0),"non atteint") | H8: ='S03'!AL18 | J8: =F8-$F$5
A9: CAC 105 € | B9: CAC × 0,7 | C9: =MIN('S04'!C62:AL62) | D9: =C9-$C$5 | E9: =MAX(0,-MIN('S04'!C62:AL62))+Hypothèses!$D$53 | F9: ='S04'!AL62 | G9: =IFERROR(MATCH(1,'S04'!C53:AL53,0),"non atteint") | H9: ='S04'!AL18 | J9: =F9-$F$5
A10: Coût IA +67 % | B10: coût par mission × 1,67 (0,18 → 0,30 €) | C10: =MIN('S05'!C62:AL62) | D10: =C10-$C$5 | E10: =MAX(0,-MIN('S05'!C62:AL62))+Hypothèses!$D$53 | F10: ='S05'!AL62 | G10: =IFERROR(MATCH(1,'S05'!C53:AL53,0),"non atteint") | H10: ='S05'!AL18 | J10: =F10-$F$5
A11: Coût IA −33 % | B11: coût par mission × 0,67 (0,18 → 0,12 €) | C11: =MIN('S06'!C62:AL62) | D11: =C11-$C$5 | E11: =MAX(0,-MIN('S06'!C62:AL62))+Hypothèses!$D$53 | F11: ='S06'!AL62 | G11: =IFERROR(MATCH(1,'S06'!C53:AL53,0),"non atteint") | H11: ='S06'!AL18 | J11: =F11-$F$5
A12: Prix −20 % | B12: prix × 0,8 (Premium 79 → 63 €) | C12: =MIN('S07'!C62:AL62) | D12: =C12-$C$5 | E12: =MAX(0,-MIN('S07'!C62:AL62))+Hypothèses!$D$53 | F12: ='S07'!AL62 | G12: =IFERROR(MATCH(1,'S07'!C53:AL53,0),"non atteint") | H12: ='S07'!AL18 | J12: =F12-$F$5
A13: Prix +20 % | B13: prix × 1,2 (Premium 79 → 95 €) | C13: =MIN('S08'!C62:AL62) | D13: =C13-$C$5 | E13: =MAX(0,-MIN('S08'!C62:AL62))+Hypothèses!$D$53 | F13: ='S08'!AL62 | G13: =IFERROR(MATCH(1,'S08'!C53:AL53,0),"non atteint") | H13: ='S08'!AL18 | J13: =F13-$F$5
A14: Lancement +3 mois | B14: retard de lancement de 3 mois | C14: =MIN('S09'!C62:AL62) | D14: =C14-$C$5 | E14: =MAX(0,-MIN('S09'!C62:AL62))+Hypothèses!$D$53 | F14: ='S09'!AL62 | G14: =IFERROR(MATCH(1,'S09'!C53:AL53,0),"non atteint") | H14: ='S09'!AL18 | J14: =F14-$F$5
A15: Coûts fixes +30 % | B15: coûts fixes × 1,3 | C15: =MIN('S10'!C62:AL62) | D15: =C15-$C$5 | E15: =MAX(0,-MIN('S10'!C62:AL62))+Hypothèses!$D$53 | F15: ='S10'!AL62 | G15: =IFERROR(MATCH(1,'S10'!C53:AL53,0),"non atteint") | H15: ='S10'!AL18 | J15: =F15-$F$5
A16: Churn 8 % (type app store) | B16: churn × 2,67 (3 % → 8 %) | C16: =MIN('S11'!C62:AL62) | D16: =C16-$C$5 | E16: =MAX(0,-MIN('S11'!C62:AL62))+Hypothèses!$D$53 | F16: ='S11'!AL62 | G16: =IFERROR(MATCH(1,'S11'!C53:AL53,0),"non atteint") | H16: ='S11'!AL18 | J16: =F16-$F$5

Sheet KPI
A1: Architecture de KPI
A2: Sept indicateurs au niveau Board, huit au niveau équipe. Seuils fixés avant de voir les données ; chaque métrique est appariée à une contre-métrique.
A4: Niveau | B4: Indicateur | C4: Formule | D4: Décision qu'il change | E4: Propriétaire | F4: Avance / retard | G4: Vert | H4: Ambre (action) | I4: Rouge (action) | J4: Contre-métrique | K4: Cadence
A5: Board | B5: Abonnés actifs payants vs trajectoire | C5: Actifs fin de mois / cible du scénario | D5: Poursuivre, ralentir ou arrêter l'acquisition | E5: Malik | F5: Retard | G5: ≥ 100 % de la cible | H5: 80 à 100 % : revue des canaux | I5: < 80 % deux mois de suite : gel des dépenses d'acquisition | J5: Churn logo mensuel | K5: Mensuelle
A6: Board | B6: Rétention J30 des cohortes payantes | C6: Actifs à J30 / cohorte initiale | D6: Lancer ou non la montée en charge | E6: Steve | F6: Retard | G6: ≥ 70 % | H6: 60 à 70 % : entretiens de résiliation | I6: < 60 % : pas de montée en charge, retour produit | J6: Activation J7 | K6: Mensuelle
A7: Board | B7: Fiabilité des missions | C7: Missions réussies sans correction / missions lancées | D7: Élargir ou restreindre le périmètre des missions | E7: Isaac | F7: Avance | G7: ≥ 80 % | H7: 70 à 80 % : gel des nouvelles missions | I7: < 70 % : retrait de la mission la moins fiable | J7: Taux de missions corrigées par l'utilisateur | K7: Hebdomadaire
A8: Board | B8: Incidents critiques (action sans autorisation, fuite de données, confusion de profils) | C8: Nombre confirmé | D8: Arrêt du pilote | E8: Tiffany | F8: Avance | G8: 0 | H8: 1 mineur : analyse sous 48 h | I8: 1 critique : arrêt du parcours, revue avant reprise | J8: Volume d'actions exécutées (éviter la fiabilité par inactivité) | K8: Continue
A9: Board | B9: Coût variable par abonné | C9: Coûts variables HT / abonnés actifs | D9: Prix, routage des modèles, limites d'usage | E9: Sébastien | F9: Retard | G9: ≤ 18 € HT | H9: 18 à 24 € : revue du routage IA | I9: > 24 € : limites d'usage ou hausse de prix | J9: Missions par abonné (ne pas réduire l'usage pour réduire le coût) | K9: Mensuelle
A10: Board | B10: Payback du CAC | C10: CAC effectif / contribution mensuelle par abonné | D10: Budget d'acquisition du mois suivant | E10: Sébastien | F10: Retard | G10: ≤ 6 mois | H10: 6 à 9 mois : réallocation entre canaux | I10: > 9 mois : arrêt du canal concerné | J10: Qualité des leads (rétention J30 par canal) | K10: Mensuelle
A11: Board | B11: Marge variable | C11: (CA HT − coûts variables − frais − impayés) / CA HT | D11: Soutenabilité du prix | E11: Sébastien | F11: Retard | G11: ≥ 65 % | H11: 55 à 65 % | I11: < 55 % : revue prix et périmètre | J11: ARPA (ne pas gonfler la marge par un mix artificiel) | K11: Mensuelle
A12: Équipe | B12: Activation J7 | C12: Nouveaux clients avec ≥ 1 mission utile / nouveaux clients | D12: Onboarding | E12: Steve | F12: Avance | G12: ≥ 70 % | H12: 50 à 70 % | I12: < 50 % | J12: Temps jusqu'à la première mission | K12: Hebdomadaire
A13: Équipe | B13: Conversion essai → payant | C13: Payants / essais de la cohorte | D13: Parcours de souscription | E13: Steve | F13: Retard | G13: ≥ 20 % | H13: 10 à 20 % | I13: < 10 % | J13: Qualité des essais (activation) | K13: Hebdomadaire
A14: Équipe | B14: Churn logo mensuel | C14: Résiliations / actifs début de mois | D14: Rétention | E14: Steve | F14: Retard | G14: ≤ 3 % | H14: 3 à 5 % | I14: > 5 % | J14: Motifs de résiliation (produit vs prix) | K14: Mensuelle
A15: Équipe | B15: Coût par mission et taux d'échec | C15: Coût API / missions ; échecs / missions | D15: Choix des modèles | E15: Isaac | F15: Avance | G15: ≤ 0,18 € ; ≤ 10 % | H15: 0,18 à 0,30 € ; 10 à 20 % | I15: > 0,30 € ; > 20 % | J15: Fiabilité (ne pas dégrader la qualité pour le coût) | K15: Hebdomadaire
... A19: Équipe | B19: Délai de réponse support | C19: Médiane, heures ouvrées | D19: Dimensionnement du support | E19: Steve | F19: Avance | G19: ≤ 4 h | H19: 4 à 24 h | I19: > 24 h | J19: Taux de résolution au premier contact | K19: Hebdomadaire

Sheet Financement
A1: Plan de financement par jalons (hypothèses, aucune aide ni levée acquise)
A2: Reprend la stratégie Finance V1 (2 FINANCE/FINANCEMENT). Les montants alimentent les tranches de l'onglet Hypothèses quand « Inclure le financement » = 1.
A4: Phase | B4: Fenêtre | C4: Objectif | D4: Source envisagée | E4: Montant (hypothèse) | F4: Conditions et vérifications | G4: Statut
A5: Phase 0, validation | B5: M1 à M3 | C5: Entretiens, prototype des missions 1 et 5, test de prix | D5: Apports des fondateurs | E5: 15000 | F5: Pas de société nécessaire. Dépenses non éligibles aux aides si engagées avant création : vérifier avant tout paiement. | G5: Hypothèse
A6: Phase 1, création et MVP | B6: Au lancement (M7 central) | C6: Société, MVP, pilote, 30 premiers abonnés | D6: Prêts d'honneur (Initiative, Réseau Entreprendre), Bourse French Tech (Bpifrance), business angels, incubateur HEC | E6: 150000 | F6: Éligibilité, calendrier d'instruction et montants à vérifier auprès de chaque dispositif ; les prêts d'honneur sont personnels aux fondateurs. | G6: Hypothèse
A7: Phase 2, croissance | B7: M13 (central) | C7: Acquisition, embauches 1 et 2, Family | D7: Amorçage (business angels, fonds d'amorçage), prêt bancaire adossé | E7: 300000 | F7: Conditionné à : rétention J30 ≥ 70 %, payback ≤ 6 mois, coût variable ≤ 18 €, zéro incident critique. | G7: Hypothèse
D9: Total des tranches | E9: =SUM(E5:E7)
A11: Comparaison avec le besoin calculé (onglet Synthèse, scénario Central) :
A12: Besoin de financement Central | E12: =Synthèse!D8
A13: Couverture du besoin par les tranches (x) | E13: =IF(E12>0,E9/E12,0)

Sheet S01
A1: Sensibilité S01 : Churn 5 % (copie du Central)
A2: Flux en € HT sauf mention TTC. Formules vivantes ; ne saisir que dans l'onglet Hypothèses et la ligne de chocs ci-dessous.
A3: Chocs de sensibilité (1 = aucun ; retard en mois) | C3: Prix × | D3: Churn × | E3: CAC × | F3: Coût IA × | G3: Coûts fixes × | H3: Retard lancement (mois)
C4: 1 | D4: 1.6667 | E4: 1 | F4: 1 | G4: 1 | H4: 0
A5: Mois de lancement effectif | B5: =Hypothèses!$D$10+$H$4
A6: Ligne | B6: Unité | C6: M1 | D6: M2 | E6: M3 | F6: M4 | G6: M5 | H6: M6 | I6: M7 | J6: M8 | K6: M9 | L6: M10 | M6: M11 | N6: M12 | O6: M13 | P6: M14 | Q6: M15 | R6: M16 | S6: M17 | T6: M18 | U6: M19 | V6: M20 | W6: M21 | X6: M22 | Y6: M23 | Z6: M24 | AA6: M25 | AB6: M26 | AC6: M27 | AD6: M28 | AE6: M29 | AF6: M30 | AG6: M31 | AH6: M32 | AI6: M33 | AJ6: M34 | AK6: M35 | AL6: M36 | AN6: Année 1 | AO6: Année 2 | AP6: Année 3
A7: Mois | B7: n° | C7: 1 | D7: 2 | E7: 3 | F7: 4 | G7: 5 | H7: 6 | I7: 7 | J7: 8 | K7: 9 | L7: 10 | M7: 11 | N7: 12 | O7: 13 | P7: 14 | Q7: 15 | R7: 16 | S7: 17 | T7: 18 | U7: 19 | V7: 20 | W7: 21 | X7: 22 | Y7: 23 | Z7: 24 | AA7: 25 | AB7: 26 | AC7: 27 | AD7: 28 | AE7: 29 | AF7: 30 | AG7: 31 | AH7: 32 | AI7: 33 | AJ7: 34 | AK7: 35 | AL7: 36
A8: Date | C8: =EDATE(Hypothèses!$D$7,C7-1) | D8: =EDATE(Hypothèses!$D$7,D7-1) | E8: =EDATE(Hypothèses!$D$7,E7-1) | F8: =EDATE(Hypothèses!$D$7,F7-1) | G8: =EDATE(Hypothèses!$D$7,G7-1) | H8: =EDATE(Hypothèses!$D$7,H7-1) | I8: =EDATE(Hypothèses!$D$7,I7-1) | J8: =EDATE(Hypothèses!$D$7,J7-1) | ... AL8: =EDATE(Hypothèses!$D$7,AL7-1)
A9: Lancé ? (1 = oui) | B9: 0/1 | C9: =IF(C7>=$B$5,1,0) | D9: =IF(D7>=$B$5,1,0) | E9: =IF(E7>=$B$5,1,0) | F9: =IF(F7>=$B$5,1,0) | G9: =IF(G7>=$B$5,1,0) | H9: =IF(H7>=$B$5,1,0) | I9: =IF(I7>=$B$5,1,0) | J9: =IF(J7>=$B$5,1,0) | ... AL9: =IF(AL7>=$B$5,1,0)
A10: Pilote en cours ? (1 = oui) | B10: 0/1 | C10: =IF(AND(C7>=Hypothèses!$D$8,C7<$B$5),1,0) | D10: =IF(AND(D7>=Hypothèses!$D$8,D7<$B$5),1,0) | E10: =IF(AND(E7>=Hypothèses!$D$8,E7<$B$5),1,0) | F10: =IF(AND(F7>=Hypothèses!$D$8,F7<$B$5),1,0) | G10: =IF(AND(G7>=Hypothèses!$D$8,G7<$B$5),1,0) | H10: =IF(AND(H7>=Hypothèses!$D$8,H7<$B$5),1,0) | I10: =IF(AND(I7>=Hypothèses!$D$8,I7<$B$5),1,0) | J10: =IF(AND(J7>=Hypothèses!$D$8,J7<$B$5),1,0) | ... AL10: =IF(AND(AL7>=Hypothèses!$D$8,AL7<$B$5),1,0)
A11: Budget d'acquisition du mois | B11: € HT | C11: =IF(C9=1,IF(C7<=12,Hypothèses!$D$20,IF(C7<=24,Hypothèses!$D$21,Hypothèses!$D$22)),0) | D11: =IF(D9=1,IF(D7<=12,Hypothèses!$D$20,IF(D7<=24,Hypothèses!$D$21,Hypothèses!$D$22)),0) | E11: =IF(E9=1,IF(E7<=12,Hypothèses!$D$20,IF(E7<=24,Hypothèses!$D$21,Hypothèses!$D$22)),0) | F11: =IF(F9=1,IF(F7<=12,Hypothèses!$D$20,IF(F7<=24,Hypothèses!$D$21,Hypothèses!$D$22)),0) | G11: =IF(G9=1,IF(G7<=12,Hypothèses!$D$20,IF(G7<=24,Hypothèses!$D$21,Hypothèses!$D$22)),0) | H11: =IF(H9=1,IF(H7<=12,Hypothèses!$D$20,IF(H7<=24,Hypothèses!$D$21,Hypothèses!$D$22)),0) | I11: =IF(I9=1,IF(I7<=12,Hypothèses!$D$20,IF(I7<=24,Hypothèses!$D$21,Hypothèses!$D$22)),0) | J11: =IF(J9=1,IF(J7<=12,Hypothèses!$D$20,IF(J7<=24,Hypothèses!$D$21,Hypothèses!$D$22)),0) | ... AL11: =IF(AL9=1,IF(AL7<=12,Hypothèses!$D$20,IF(AL7<=24,Hypothèses!$D$21,Hypothèses!$D$22)),0) | AN11: =SUM(C11:N11) | AO11: =SUM(O11:Z11) | AP11: =SUM(AA11:AL11)
A12: Abonnés
A13: Abonnés en début de mois | B13: abonnés | C13: =0 | D13: =C18 | E13: =D18 | F13: =E18 | G13: =F18 | H13: =G18 | I13: =H18 | J13: =I18 | K13: =J18 | ... AL13: =AK18
A14: Nouveaux abonnés par acquisition payante | B14: abonnés | C14: =C11/(Hypothèses!$D$23*$E$4) | D14: =D11/(Hypothèses!$D$23*$E$4) | E14: =E11/(Hypothèses!$D$23*$E$4) | F14: =F11/(Hypothèses!$D$23*$E$4) | G14: =G11/(Hypothèses!$D$23*$E$4) | H14: =H11/(Hypothèses!$D$23*$E$4) | I14: =I11/(Hypothèses!$D$23*$E$4) | J14: =J11/(Hypothèses!$D$23*$E$4) | ... AL14: =AL11/(Hypothèses!$D$23*$E$4) | AN14: =SUM(C14:N14) | AO14: =SUM(O14:Z14) | AP14: =SUM(AA14:AL14)
A15: Nouveaux abonnés pilote | B15: abonnés | C15: =IF(C7=Hypothèses!$D$8,Hypothèses!$D$9,0) | D15: =IF(D7=Hypothèses!$D$8,Hypothèses!$D$9,0) | E15: =IF(E7=Hypothèses!$D$8,Hypothèses!$D$9,0) | F15: =IF(F7=Hypothèses!$D$8,Hypothèses!$D$9,0) | G15: =IF(G7=Hypothèses!$D$8,Hypothèses!$D$9,0) | H15: =IF(H7=Hypothèses!$D$8,Hypothèses!$D$9,0) | I15: =IF(I7=Hypothèses!$D$8,Hypothèses!$D$9,0) | J15: =IF(J7=Hypothèses!$D$8,Hypothèses!$D$9,0) | ... AL15: =IF(AL7=Hypothèses!$D$8,Hypothèses!$D$9,0) | AN15: =SUM(C15:N15) | AO15: =SUM(O15:Z15) | AP15: =SUM(AA15:AL15)
A16: Nouveaux abonnés organiques (parrainage) | B16: abonnés | C16: =C9*C13*Hypothèses!$D$24 | D16: =D9*D13*Hypothèses!$D$24 | E16: =E9*E13*Hypothèses!$D$24 | F16: =F9*F13*Hypothèses!$D$24 | G16: =G9*G13*Hypothèses!$D$24 | H16: =H9*H13*Hypothèses!$D$24 | I16: =I9*I13*Hypothèses!$D$24 | J16: =J9*J13*Hypothèses!$D$24 | ... AL16: =AL9*AL13*Hypothèses!$D$24 | AN16: =SUM(C16:N16) | AO16: =SUM(O16:Z16) | AP16: =SUM(AA16:AL16)
A17: Résiliations | B17: abonnés | C17: =C13*Hypothèses!$D$26*$D$4 | D17: =D13*Hypothèses!$D$26*$D$4 | E17: =E13*Hypothèses!$D$26*$D$4 | F17: =F13*Hypothèses!$D$26*$D$4 | G17: =G13*Hypothèses!$D$26*$D$4 | H17: =H13*Hypothèses!$D$26*$D$4 | I17: =I13*Hypothèses!$D$26*$D$4 | J17: =J13*Hypothèses!$D$26*$D$4 | ... AL17: =AL13*Hypothèses!$D$26*$D$4 | AN17: =SUM(C17:N17) | AO17: =SUM(O17:Z17) | AP17: =SUM(AA17:AL17)
A18: Abonnés en fin de mois | B18: abonnés | C18: =C13+C14+C15+C16-C17 | D18: =D13+D14+D15+D16-D17 | E18: =E13+E14+E15+E16-E17 | F18: =F13+F14+F15+F16-F17 | G18: =G13+G14+G15+G16-G17 | H18: =H13+H14+H15+H16-H17 | I18: =I13+I14+I15+I16-I17 | J18: =J13+J14+J15+J16-J17 | ... AL18: =AL13+AL14+AL15+AL16-AL17 | AN18: =N18 | AO18: =Z18 | AP18: =AL18
A19: dont Personal | B19: abonnés | C19: =C18*Hypothèses!$D$16 | D19: =D18*Hypothèses!$D$16 | E19: =E18*Hypothèses!$D$16 | F19: =F18*Hypothèses!$D$16 | G19: =G18*Hypothèses!$D$16 | H19: =H18*Hypothèses!$D$16 | I19: =I18*Hypothèses!$D$16 | J19: =J18*Hypothèses!$D$16 | ... AL19: =AL18*Hypothèses!$D$16 | AN19: =N19 | AO19: =Z19 | AP19: =AL19
A20: dont Premium | B20: abonnés | C20: =C18*Hypothèses!$D$17 | D20: =D18*Hypothèses!$D$17 | E20: =E18*Hypothèses!$D$17 | F20: =F18*Hypothèses!$D$17 | G20: =G18*Hypothèses!$D$17 | H20: =H18*Hypothèses!$D$17 | I20: =I18*Hypothèses!$D$17 | J20: =J18*Hypothèses!$D$17 | ... AL20: =AL18*Hypothèses!$D$17 | AN20: =N20 | AO20: =Z20 | AP20: =AL20
A21: dont Family | B21: abonnés | C21: =C18*Hypothèses!$D$18 | D21: =D18*Hypothèses!$D$18 | E21: =E18*Hypothèses!$D$18 | F21: =F18*Hypothèses!$D$18 | G21: =G18*Hypothèses!$D$18 | H21: =H18*Hypothèses!$D$18 | I21: =I18*Hypothèses!$D$18 | J21: =J18*Hypothèses!$D$18 | ... AL21: =AL18*Hypothèses!$D$18 | AN21: =N21 | AO21: =Z21 | AP21: =AL21
A22: Revenus
A23: Facturation Personal TTC | B23: € TTC | C23: =C19*Hypothèses!$D$12*$C$4 | D23: =D19*Hypothèses!$D$12*$C$4 | E23: =E19*Hypothèses!$D$12*$C$4 | F23: =F19*Hypothèses!$D$12*$C$4 | G23: =G19*Hypothèses!$D$12*$C$4 | H23: =H19*Hypothèses!$D$12*$C$4 | I23: =I19*Hypothèses!$D$12*$C$4 | J23: =J19*Hypothèses!$D$12*$C$4 | ... AL23: =AL19*Hypothèses!$D$12*$C$4 | AN23: =SUM(C23:N23) | AO23: =SUM(O23:Z23) | AP23: =SUM(AA23:AL23)
A24: Facturation Premium TTC | B24: € TTC | C24: =C20*Hypothèses!$D$13*$C$4 | D24: =D20*Hypothèses!$D$13*$C$4 | E24: =E20*Hypothèses!$D$13*$C$4 | F24: =F20*Hypothèses!$D$13*$C$4 | G24: =G20*Hypothèses!$D$13*$C$4 | H24: =H20*Hypothèses!$D$13*$C$4 | I24: =I20*Hypothèses!$D$13*$C$4 | J24: =J20*Hypothèses!$D$13*$C$4 | ... AL24: =AL20*Hypothèses!$D$13*$C$4 | AN24: =SUM(C24:N24) | AO24: =SUM(O24:Z24) | AP24: =SUM(AA24:AL24)
A25: Facturation Family TTC | B25: € TTC | C25: =C21*Hypothèses!$D$14*$C$4 | D25: =D21*Hypothèses!$D$14*$C$4 | E25: =E21*Hypothèses!$D$14*$C$4 | F25: =F21*Hypothèses!$D$14*$C$4 | G25: =G21*Hypothèses!$D$14*$C$4 | H25: =H21*Hypothèses!$D$14*$C$4 | I25: =I21*Hypothèses!$D$14*$C$4 | J25: =J21*Hypothèses!$D$14*$C$4 | ... AL25: =AL21*Hypothèses!$D$14*$C$4 | AN25: =SUM(C25:N25) | AO25: =SUM(O25:Z25) | AP25: =SUM(AA25:AL25)
A26: Facturation totale TTC (MRR TTC) | B26: € TTC | C26: =C23+C24+C25 | D26: =D23+D24+D25 | E26: =E23+E24+E25 | F26: =F23+F24+F25 | G26: =G23+G24+G25 | H26: =H23+H24+H25 | I26: =I23+I24+I25 | J26: =J23+J24+J25 | ... AL26: =AL23+AL24+AL25 | AN26: =SUM(C26:N26) | AO26: =SUM(O26:Z26) | AP26: =SUM(AA26:AL26)
A27: TVA collectée | B27: € | C27: =C26*Hypothèses!$D$15/(1+Hypothèses!$D$15) | D27: =D26*Hypothèses!$D$15/(1+Hypothèses!$D$15) | E27: =E26*Hypothèses!$D$15/(1+Hypothèses!$D$15) | F27: =F26*Hypothèses!$D$15/(1+Hypothèses!$D$15) | G27: =G26*Hypothèses!$D$15/(1+Hypothèses!$D$15) | H27: =H26*Hypothèses!$D$15/(1+Hypothèses!$D$15) | I27: =I26*Hypothèses!$D$15/(1+Hypothèses!$D$15) | J27: =J26*Hypothèses!$D$15/(1+Hypothèses!$D$15) | ... AL27: =AL26*Hypothèses!$D$15/(1+Hypothèses!$D$15) | AN27: =SUM(C27:N27) | AO27: =SUM(O27:Z27) | AP27: =SUM(AA27:AL27)
A28: Chiffre d'affaires HT | B28: € HT | C28: =C26-C27 | D28: =D26-D27 | E28: =E26-E27 | F28: =F26-F27 | G28: =G26-G27 | H28: =H26-H27 | I28: =I26-I27 | J28: =J26-J27 | ... AL28: =AL26-AL27 | AN28: =SUM(C28:N28) | AO28: =SUM(O28:Z28) | AP28: =SUM(AA28:AL28)
A29: Impayés (TTC) | B29: € TTC | C29: =C26*Hypothèses!$D$27 | D29: =D26*Hypothèses!$D$27 | E29: =E26*Hypothèses!$D$27 | F29: =F26*Hypothèses!$D$27 | G29: =G26*Hypothèses!$D$27 | H29: =H26*Hypothèses!$D$27 | I29: =I26*Hypothèses!$D$27 | J29: =J26*Hypothèses!$D$27 | ... AL29: =AL26*Hypothèses!$D$27 | AN29: =SUM(C29:N29) | AO29: =SUM(O29:Z29) | AP29: =SUM(AA29:AL29)
A30: Frais de paiement | B30: € | C30: =(C26-C29)*Hypothèses!$D$28+C18*Hypothèses!$D$29 | D30: =(D26-D29)*Hypothèses!$D$28+D18*Hypothèses!$D$29 | E30: =(E26-E29)*Hypothèses!$D$28+E18*Hypothèses!$D$29 | F30: =(F26-F29)*Hypothèses!$D$28+F18*Hypothèses!$D$29 | G30: =(G26-G29)*Hypothèses!$D$28+G18*Hypothèses!$D$29 | H30: =(H26-H29)*Hypothèses!$D$28+H18*Hypothèses!$D$29 | I30: =(I26-I29)*Hypothèses!$D$28+I18*Hypothèses!$D$29 | J30: =(J26-J29)*Hypothèses!$D$28+J18*Hypothèses!$D$29 | ... AL30: =(AL26-AL29)*Hypothèses!$D$28+AL18*Hypothèses!$D$29 | AN30: =SUM(C30:N30) | AO30: =SUM(O30:Z30) | AP30: =SUM(AA30:AL30)
A31: Encaissements nets TTC | B31: € TTC | C31: =C26-C29-C30 | D31: =D26-D29-D30 | E31: =E26-E29-E30 | F31: =F26-F29-F30 | G31: =G26-G29-G30 | H31: =H26-H29-H30 | I31: =I26-I29-I30 | J31: =J26-J29-J30 | ... AL31: =AL26-AL29-AL30 | AN31: =SUM(C31:N31) | AO31: =SUM(O31:Z31) | AP31: =SUM(AA31:AL31)
A32: Coûts variables
A33: Coût IA et outils (missions × coût par mission) | B33: € HT | C33: =(C19*Hypothèses!$D$31+C20*Hypothèses!$D$32+C21*Hypothèses!$D$33)*Hypothèses!$D$34*$F$4 | D33: =(D19*Hypothèses!$D$31+D20*Hypothèses!$D$32+D21*Hypothèses!$D$33)*Hypothèses!$D$34*$F$4 | E33: =(E19*Hypothèses!$D$31+E20*Hypothèses!$D$32+E21*Hypothèses!$D$33)*Hypothèses!$D$34*$F$4 | F33: =(F19*Hypothèses!$D$31+F20*Hypothèses!$D$32+F21*Hypothèses!$D$33)*Hypothèses!$D$34*$F$4 | G33: =(G19*Hypothèses!$D$31+G20*Hypothèses!$D$32+G21*Hypothèses!$D$33)*Hypothèses!$D$34*$F$4 | H33: =(H19*Hypothèses!$D$31+H20*Hypothèses!$D$32+H21*Hypothèses!$D$33)*Hypothèses!$D$34*$F$4 | I33: =(I19*Hypothèses!$D$31+I20*Hypothèses!$D$32+I21*Hypothèses!$D$33)*Hypothèses!$D$34*$F$4 | J33: =(J19*Hypothèses!$D$31+J20*Hypothèses!$D$32+J21*Hypothèses!$D$33)*Hypothèses!$D$34*$F$4 | ... AL33: =(AL19*Hypothèses!$D$31+AL20*Hypothèses!$D$32+AL21*Hypothèses!$D$33)*Hypothèses!$D$34*$F$4 | AN33: =SUM(C33:N33) | AO33: =SUM(O33:Z33) | AP33: =SUM(AA33:AL33)
A34: Hébergement, stockage, connecteurs | B34: € HT | C34: =C18*Hypothèses!$D$35 | D34: =D18*Hypothèses!$D$35 | E34: =E18*Hypothèses!$D$35 | F34: =F18*Hypothèses!$D$35 | G34: =G18*Hypothèses!$D$35 | H34: =H18*Hypothèses!$D$35 | I34: =I18*Hypothèses!$D$35 | J34: =J18*Hypothèses!$D$35 | ... AL34: =AL18*Hypothèses!$D$35 | AN34: =SUM(C34:N34) | AO34: =SUM(O34:Z34) | AP34: =SUM(AA34:AL34)
A35: Support humain | B35: € HT | C35: =C18*Hypothèses!$D$36 | D35: =D18*Hypothèses!$D$36 | E35: =E18*Hypothèses!$D$36 | F35: =F18*Hypothèses!$D$36 | G35: =G18*Hypothèses!$D$36 | H35: =H18*Hypothèses!$D$36 | I35: =I18*Hypothèses!$D$36 | J35: =J18*Hypothèses!$D$36 | ... AL35: =AL18*Hypothèses!$D$36 | AN35: =SUM(C35:N35) | AO35: =SUM(O35:Z35) | AP35: =SUM(AA35:AL35)
A36: Total coûts variables | B36: € HT | C36: =C33+C34+C35 | D36: =D33+D34+D35 | E36: =E33+E34+E35 | F36: =F33+F34+F35 | G36: =G33+G34+G35 | H36: =H33+H34+H35 | I36: =I33+I34+I35 | J36: =J33+J34+J35 | ... AL36: =AL33+AL34+AL35 | AN36: =SUM(C36:N36) | AO36: =SUM(O36:Z36) | AP36: =SUM(AA36:AL36)
A37: Marge sur coûts variables (CA HT − variables − frais − impayés HT) | B37: € HT | C37: =C28-C36-C30-C29/(1+Hypothèses!$D$15) | D37: =D28-D36-D30-D29/(1+Hypothèses!$D$15) | E37: =E28-E36-E30-E29/(1+Hypothèses!$D$15) | F37: =F28-F36-F30-F29/(1+Hypothèses!$D$15) | G37: =G28-G36-G30-G29/(1+Hypothèses!$D$15) | H37: =H28-H36-H30-H29/(1+Hypothèses!$D$15) | I37: =I28-I36-I30-I29/(1+Hypothèses!$D$15) | J37: =J28-J36-J30-J29/(1+Hypothèses!$D$15) | ... AL37: =AL28-AL36-AL30-AL29/(1+Hypothèses!$D$15) | AN37: =SUM(C37:N37) | AO37: =SUM(O37:Z37) | AP37: =SUM(AA37:AL37)
A38: Acquisition et coûts fixes
A39: Dépenses d'acquisition | B39: € HT | C39: =C11 | D39: =D11 | E39: =E11 | F39: =F11 | G39: =G11 | H39: =H11 | I39: =I11 | J39: =J11 | ... AL39: =AL11 | AN39: =SUM(C39:N39) | AO39: =SUM(O39:Z39) | AP39: =SUM(AA39:AL39)
A40: Rémunération des fondateurs | B40: € HT | C40: =IF(C7>=Hypothèses!$D$39,Hypothèses!$D$38*Hypothèses!$D$40,0)*$G$4 | D40: =IF(D7>=Hypothèses!$D$39,Hypothèses!$D$38*Hypothèses!$D$40,0)*$G$4 | E40: =IF(E7>=Hypothèses!$D$39,Hypothèses!$D$38*Hypothèses!$D$40,0)*$G$4 | F40: =IF(F7>=Hypothèses!$D$39,Hypothèses!$D$38*Hypothèses!$D$40,0)*$G$4 | G40: =IF(G7>=Hypothèses!$D$39,Hypothèses!$D$38*Hypothèses!$D$40,0)*$G$4 | H40: =IF(H7>=Hypothèses!$D$39,Hypothèses!$D$38*Hypothèses!$D$40,0)*$G$4 | I40: =IF(I7>=Hypothèses!$D$39,Hypothèses!$D$38*Hypothèses!$D$40,0)*$G$4 | J40: =IF(J7>=Hypothèses!$D$39,Hypothèses!$D$38*Hypothèses!$D$40,0)*$G$4 | ... AL40: =IF(AL7>=Hypothèses!$D$39,Hypothèses!$D$38*Hypothèses!$D$40,0)*$G$4 | AN40: =SUM(C40:N40) | AO40: =SUM(O40:Z40) | AP40: =SUM(AA40:AL40)
A41: Salarié 1 (growth / customer success) | B41: € HT | C41: =IF(C7>=Hypothèses!$D$41,Hypothèses!$D$42,0)*$G$4 | D41: =IF(D7>=Hypothèses!$D$41,Hypothèses!$D$42,0)*$G$4 | E41: =IF(E7>=Hypothèses!$D$41,Hypothèses!$D$42,0)*$G$4 | F41: =IF(F7>=Hypothèses!$D$41,Hypothèses!$D$42,0)*$G$4 | G41: =IF(G7>=Hypothèses!$D$41,Hypothèses!$D$42,0)*$G$4 | H41: =IF(H7>=Hypothèses!$D$41,Hypothèses!$D$42,0)*$G$4 | I41: =IF(I7>=Hypothèses!$D$41,Hypothèses!$D$42,0)*$G$4 | J41: =IF(J7>=Hypothèses!$D$41,Hypothèses!$D$42,0)*$G$4 | ... AL41: =IF(AL7>=Hypothèses!$D$41,Hypothèses!$D$42,0)*$G$4 | AN41: =SUM(C41:N41) | AO41: =SUM(O41:Z41) | AP41: =SUM(AA41:AL41)
A42: Salarié 2 (ingénieur) | B42: € HT | C42: =IF(C7>=Hypothèses!$D$43,Hypothèses!$D$44,0)*$G$4 | D42: =IF(D7>=Hypothèses!$D$43,Hypothèses!$D$44,0)*$G$4 | E42: =IF(E7>=Hypothèses!$D$43,Hypothèses!$D$44,0)*$G$4 | F42: =IF(F7>=Hypothèses!$D$43,Hypothèses!$D$44,0)*$G$4 | G42: =IF(G7>=Hypothèses!$D$43,Hypothèses!$D$44,0)*$G$4 | H42: =IF(H7>=Hypothèses!$D$43,Hypothèses!$D$44,0)*$G$4 | I42: =IF(I7>=Hypothèses!$D$43,Hypothèses!$D$44,0)*$G$4 | J42: =IF(J7>=Hypothèses!$D$43,Hypothèses!$D$44,0)*$G$4 | ... AL42: =IF(AL7>=Hypothèses!$D$43,Hypothèses!$D$44,0)*$G$4 | AN42: =SUM(C42:N42) | AO42: =SUM(O42:Z42) | AP42: =SUM(AA42:AL42)
A43: Développement MVP externe (étalé jusqu'au lancement) | B43: € HT | C43: =IF(C7<$B$5,Hypothèses!$D$45/MAX(1,$B$5-1),0) | D43: =IF(D7<$B$5,Hypothèses!$D$45/MAX(1,$B$5-1),0) | E43: =IF(E7<$B$5,Hypothèses!$D$45/MAX(1,$B$5-1),0) | F43: =IF(F7<$B$5,Hypothèses!$D$45/MAX(1,$B$5-1),0) | G43: =IF(G7<$B$5,Hypothèses!$D$45/MAX(1,$B$5-1),0) | H43: =IF(H7<$B$5,Hypothèses!$D$45/MAX(1,$B$5-1),0) | I43: =IF(I7<$B$5,Hypothèses!$D$45/MAX(1,$B$5-1),0) | J43: =IF(J7<$B$5,Hypothèses!$D$45/MAX(1,$B$5-1),0) | ... AL43: =IF(AL7<$B$5,Hypothèses!$D$45/MAX(1,$B$5-1),0) | AN43: =SUM(C43:N43) | AO43: =SUM(O43:Z43) | AP43: =SUM(AA43:AL43)
A44: Outils et SaaS | B44: € HT | C44: =Hypothèses!$D$46*$G$4 | D44: =Hypothèses!$D$46*$G$4 | E44: =Hypothèses!$D$46*$G$4 | F44: =Hypothèses!$D$46*$G$4 | G44: =Hypothèses!$D$46*$G$4 | H44: =Hypothèses!$D$46*$G$4 | I44: =Hypothèses!$D$46*$G$4 | J44: =Hypothèses!$D$46*$G$4 | ... AL44: =Hypothèses!$D$46*$G$4 | AN44: =SUM(C44:N44) | AO44: =SUM(O44:Z44) | AP44: =SUM(AA44:AL44)
A45: Juridique et comptabilité | B45: € HT | C45: =Hypothèses!$D$47*$G$4 | D45: =Hypothèses!$D$47*$G$4 | E45: =Hypothèses!$D$47*$G$4 | F45: =Hypothèses!$D$47*$G$4 | G45: =Hypothèses!$D$47*$G$4 | H45: =Hypothèses!$D$47*$G$4 | I45: =Hypothèses!$D$47*$G$4 | J45: =Hypothèses!$D$47*$G$4 | ... AL45: =Hypothèses!$D$47*$G$4 | AN45: =SUM(C45:N45) | AO45: =SUM(O45:Z45) | AP45: =SUM(AA45:AL45)
A46: Assurance RC pro | B46: € | C46: =C9*Hypothèses!$D$48*$G$4 | D46: =D9*Hypothèses!$D$48*$G$4 | E46: =E9*Hypothèses!$D$48*$G$4 | F46: =F9*Hypothèses!$D$48*$G$4 | G46: =G9*Hypothèses!$D$48*$G$4 | H46: =H9*Hypothèses!$D$48*$G$4 | I46: =I9*Hypothèses!$D$48*$G$4 | J46: =J9*Hypothèses!$D$48*$G$4 | ... AL46: =AL9*Hypothèses!$D$48*$G$4 | AN46: =SUM(C46:N46) | AO46: =SUM(O46:Z46) | AP46: =SUM(AA46:AL46)
A47: Marketing fixe | B47: € HT | C47: =C9*Hypothèses!$D$49*$G$4 | D47: =D9*Hypothèses!$D$49*$G$4 | E47: =E9*Hypothèses!$D$49*$G$4 | F47: =F9*Hypothèses!$D$49*$G$4 | G47: =G9*Hypothèses!$D$49*$G$4 | H47: =H9*Hypothèses!$D$49*$G$4 | I47: =I9*Hypothèses!$D$49*$G$4 | J47: =J9*Hypothèses!$D$49*$G$4 | ... AL47: =AL9*Hypothèses!$D$49*$G$4 | AN47: =SUM(C47:N47) | AO47: =SUM(O47:Z47) | AP47: =SUM(AA47:AL47)
A48: Frais généraux | B48: € HT | C48: =Hypothèses!$D$50*$G$4 | D48: =Hypothèses!$D$50*$G$4 | E48: =Hypothèses!$D$50*$G$4 | F48: =Hypothèses!$D$50*$G$4 | G48: =Hypothèses!$D$50*$G$4 | H48: =Hypothèses!$D$50*$G$4 | I48: =Hypothèses!$D$50*$G$4 | J48: =Hypothèses!$D$50*$G$4 | ... AL48: =Hypothèses!$D$50*$G$4 | AN48: =SUM(C48:N48) | AO48: =SUM(O48:Z48) | AP48: =SUM(AA48:AL48)
A49: Audit de sécurité (annuel, à partir du lancement) | B49: € HT | C49: =IF(AND(C9=1,MOD(C7-$B$5,12)=0),Hypothèses!$D$51,0)*$G$4 | D49: =IF(AND(D9=1,MOD(D7-$B$5,12)=0),Hypothèses!$D$51,0)*$G$4 | E49: =IF(AND(E9=1,MOD(E7-$B$5,12)=0),Hypothèses!$D$51,0)*$G$4 | F49: =IF(AND(F9=1,MOD(F7-$B$5,12)=0),Hypothèses!$D$51,0)*$G$4 | G49: =IF(AND(G9=1,MOD(G7-$B$5,12)=0),Hypothèses!$D$51,0)*$G$4 | H49: =IF(AND(H9=1,MOD(H7-$B$5,12)=0),Hypothèses!$D$51,0)*$G$4 | I49: =IF(AND(I9=1,MOD(I7-$B$5,12)=0),Hypothèses!$D$51,0)*$G$4 | J49: =IF(AND(J9=1,MOD(J7-$B$5,12)=0),Hypothèses!$D$51,0)*$G$4 | ... AL49: =IF(AND(AL9=1,MOD(AL7-$B$5,12)=0),Hypothèses!$D$51,0)*$G$4 | AN49: =SUM(C49:N49) | AO49: =SUM(O49:Z49) | AP49: =SUM(AA49:AL49)
A50: Frais de constitution | B50: € HT | C50: =IF(C7=2,Hypothèses!$D$52,0) | D50: =IF(D7=2,Hypothèses!$D$52,0) | E50: =IF(E7=2,Hypothèses!$D$52,0) | F50: =IF(F7=2,Hypothèses!$D$52,0) | G50: =IF(G7=2,Hypothèses!$D$52,0) | H50: =IF(H7=2,Hypothèses!$D$52,0) | I50: =IF(I7=2,Hypothèses!$D$52,0) | J50: =IF(J7=2,Hypothèses!$D$52,0) | ... AL50: =IF(AL7=2,Hypothèses!$D$52,0) | AN50: =SUM(C50:N50) | AO50: =SUM(O50:Z50) | AP50: =SUM(AA50:AL50)
A51: Total coûts fixes | B51: € HT | C51: =SUM(C40:C50) | D51: =SUM(D40:D50) | E51: =SUM(E40:E50) | F51: =SUM(F40:F50) | G51: =SUM(G40:G50) | H51: =SUM(H40:H50) | I51: =SUM(I40:I50) | J51: =SUM(J40:J50) | ... AL51: =SUM(AL40:AL50) | AN51: =SUM(C51:N51) | AO51: =SUM(O51:Z51) | AP51: =SUM(AA51:AL51)
A52: EBITDA (marge variable − acquisition − fixes) | B52: € HT | C52: =C37-C39-C51 | D52: =D37-D39-D51 | E52: =E37-E39-E51 | F52: =F37-F39-F51 | G52: =G37-G39-G51 | H52: =H37-H39-H51 | I52: =I37-I39-I51 | J52: =J37-J39-J51 | ... AL52: =AL37-AL39-AL51 | AN52: =SUM(C52:N52) | AO52: =SUM(O52:Z52) | AP52: =SUM(AA52:AL52)
A53: EBITDA positif ? (1 = oui) | B53: 0/1 | C53: =IF(C52>0,1,0) | D53: =IF(D52>0,1,0) | E53: =IF(E52>0,1,0) | F53: =IF(F52>0,1,0) | G53: =IF(G52>0,1,0) | H53: =IF(H52>0,1,0) | I53: =IF(I52>0,1,0) | J53: =IF(J52>0,1,0) | ... AL53: =IF(AL52>0,1,0)
A54: Trésorerie
A55: TVA collectée reversée (mois suivant) | B55: € | C55: =0 | D55: =C27 | E55: =D27 | F55: =E27 | G55: =F27 | H55: =G27 | I55: =H27 | J55: =I27 | K55: =J27 | ... AL55: =AK27 | AN55: =SUM(C55:N55) | AO55: =SUM(O55:Z55) | AP55: =SUM(AA55:AL55)
A56: TVA déductible récupérée (mois suivant, coûts externes) | B56: € | C56: =0 | D56: =(C36+C39+C43+C44+C45+C47+C48+C49+C50)*Hypothèses!$D$15 | E56: =(D36+D39+D43+D44+D45+D47+D48+D49+D50)*Hypothèses!$D$15 | F56: =(E36+E39+E43+E44+E45+E47+E48+E49+E50)*Hypothèses!$D$15 | G56: =(F36+F39+F43+F44+F45+F47+F48+F49+F50)*Hypothèses!$D$15 | H56: =(G36+G39+G43+G44+G45+G47+G48+G49+G50)*Hypothèses!$D$15 | I56: =(H36+H39+H43+H44+H45+H47+H48+H49+H50)*Hypothèses!$D$15 | J56: =(I36+I39+I43+I44+I45+I47+I48+I49+I50)*Hypothèses!$D$15 | K56: =(J36+J39+J43+J44+J45+J47+J48+J49+J50)*Hypothèses!$D$15 | ... AL56: =(AK36+AK39+AK43+AK44+AK45+AK47+AK48+AK49+AK50)*Hypothèses!$D$15 | AN56: =SUM(C56:N56) | AO56: =SUM(O56:Z56) | AP56: =SUM(AA56:AL56)
A57: Financement reçu | B57: € | C57: =Hypothèses!$D$56*(IF(C7=Hypothèses!$D$57,Hypothèses!$D$58,0)+IF(C7=Hypothèses!$D$59,Hypothèses!$D$60,0)+IF(C7=Hypothèses!$D$61,Hypothèses!$D$62,0)) | D57: =Hypothèses!$D$56*(IF(D7=Hypothèses!$D$57,Hypothèses!$D$58,0)+IF(D7=Hypothèses!$D$59,Hypothèses!$D$60,0)+IF(D7=Hypothèses!$D$61,Hypothèses!$D$62,0)) | E57: =Hypothèses!$D$56*(IF(E7=Hypothèses!$D$57,Hypothèses!$D$58,0)+IF(E7=Hypothèses!$D$59,Hypothèses!$D$60,0)+IF(E7=Hypothèses!$D$61,Hypothèses!$D$62,0)) | F57: =Hypothèses!$D$56*(IF(F7=Hypothèses!$D$57,Hypothèses!$D$58,0)+IF(F7=Hypothèses!$D$59,Hypothèses!$D$60,0)+IF(F7=Hypothèses!$D$61,Hypothèses!$D$62,0)) | G57: =Hypothèses!$D$56*(IF(G7=Hypothèses!$D$57,Hypothèses!$D$58,0)+IF(G7=Hypothèses!$D$59,Hypothèses!$D$60,0)+IF(G7=Hypothèses!$D$61,Hypothèses!$D$62,0)) | H57: =Hypothèses!$D$56*(IF(H7=Hypothèses!$D$57,Hypothèses!$D$58,0)+IF(H7=Hypothèses!$D$59,Hypothèses!$D$60,0)+IF(H7=Hypothèses!$D$61,Hypothèses!$D$62,0)) | I57: =Hypothèses!$D$56*(IF(I7=Hypothèses!$D$57,Hypothèses!$D$58,0)+IF(I7=Hypothèses!$D$59,Hypothèses!$D$60,0)+IF(I7=Hypothèses!$D$61,Hypothèses!$D$62,0)) | J57: =Hypothèses!$D$56*(IF(J7=Hypothèses!$D$57,Hypothèses!$D$58,0)+IF(J7=Hypothèses!$D$59,Hypothèses!$D$60,0)+IF(J7=Hypothèses!$D$61,Hypothèses!$D$62,0)) | ... AL57: =Hypothèses!$D$56*(IF(AL7=Hypothèses!$D$57,Hypothèses!$D$58,0)+IF(AL7=Hypothèses!$D$59,Hypothèses!$D$60,0)+IF(AL7=Hypothèses!$D$61,Hypothèses!$D$62,0)) | AN57: =SUM(C57:N57) | AO57: =SUM(O57:Z57) | AP57: =SUM(AA57:AL57)
A58: Trésorerie d'ouverture | B58: € | C58: =Hypothèses!$D$54 | D58: =C60 | E58: =D60 | F58: =E60 | G58: =F60 | H58: =G60 | I58: =H60 | J58: =I60 | K58: =J60 | ... AL58: =AK60
A59: Flux de trésorerie du mois | B59: € | C59: =C31-C36-C39-C51-C55+C56+C57 | D59: =D31-D36-D39-D51-D55+D56+D57 | E59: =E31-E36-E39-E51-E55+E56+E57 | F59: =F31-F36-F39-F51-F55+F56+F57 | G59: =G31-G36-G39-G51-G55+G56+G57 | H59: =H31-H36-H39-H51-H55+H56+H57 | I59: =I31-I36-I39-I51-I55+I56+I57 | J59: =J31-J36-J39-J51-J55+J56+J57 | ... AL59: =AL31-AL36-AL39-AL51-AL55+AL56+AL57 | AN59: =SUM(C59:N59) | AO59: =SUM(O59:Z59) | AP59: =SUM(AA59:AL59)
A60: Trésorerie de clôture | B60: € | C60: =C58+C59 | D60: =D58+D59 | E60: =E58+E59 | F60: =F58+F59 | G60: =G58+G59 | H60: =H58+H59 | I60: =I58+I59 | J60: =J58+J59 | ... AL60: =AL58+AL59 | AN60: =N60 | AO60: =Z60 | AP60: =AL60
A61: Financement cumulé | B61: € | C61: =0+C57 | D61: =C61+D57 | E61: =D61+E57 | F61: =E61+F57 | G61: =F61+G57 | H61: =G61+H57 | I61: =H61+I57 | J61: =I61+J57 | K61: =J61+K57 | ... AL61: =AK61+AL57 | AN61: =N61 | AO61: =Z61 | AP61: =AL61
A62: Trésorerie cumulée hors financement | B62: € | C62: =C60-C61 | D62: =D60-D61 | E62: =E60-E61 | F62: =F60-F61 | G62: =G60-G61 | H62: =H60-H61 | I62: =I60-I61 | J62: =J60-J61 | ... AL62: =AL60-AL61 | AN62: =N62 | AO62: =Z62 | AP62: =AL62
A63: Point bas glissant hors financement | B63: € | C63: =C62 | D63: =MIN(C63,D62) | E63: =MIN(D63,E62) | F63: =MIN(E63,F62) | G63: =MIN(F63,G62) | H63: =MIN(G63,H62) | I63: =MIN(H63,I62) | J63: =MIN(I63,J62) | K63: =MIN(J63,K62) | ... AL63: =MIN(AK63,AL62) | AN63: =N63 | AO63: =Z63 | AP63: =AL63
A64: Trésorerie cumulée hors financement positive après lancement ? (1 = oui) | B64: 0/1 | C64: =IF(AND(C9=1,C62>0),1,0) | D64: =IF(AND(D9=1,D62>0),1,0) | E64: =IF(AND(E9=1,E62>0),1,0) | F64: =IF(AND(F9=1,F62>0),1,0) | G64: =IF(AND(G9=1,G62>0),1,0) | H64: =IF(AND(H9=1,H62>0),1,0) | I64: =IF(AND(I9=1,I62>0),1,0) | J64: =IF(AND(J9=1,J62>0),1,0) | ... AL64: =IF(AND(AL9=1,AL62>0),1,0)
A65: Indicateurs
A66: ARR HT instantané (CA HT × 12) | B66: € HT | C66: =C28*12 | D66: =D28*12 | E66: =E28*12 | F66: =F28*12 | G66: =G28*12 | H66: =H28*12 | I66: =I28*12 | J66: =J28*12 | ... AL66: =AL28*12 | AN66: =N66 | AO66: =Z66 | AP66: =AL66
A67: ARPA HT (CA HT / abonnés) | B67: € HT | C67: =IF(C18>0,C28/C18,0) | D67: =IF(D18>0,D28/D18,0) | E67: =IF(E18>0,E28/E18,0) | F67: =IF(F18>0,F28/F18,0) | G67: =IF(G18>0,G28/G18,0) | H67: =IF(H18>0,H28/H18,0) | I67: =IF(I18>0,I28/I18,0) | J67: =IF(J18>0,J28/J18,0) | ... AL67: =IF(AL18>0,AL28/AL18,0) | AN67: =N67 | AO67: =Z67 | AP67: =AL67
A68: Coût variable par abonné | B68: € HT | C68: =IF(C18>0,C36/C18,0) | D68: =IF(D18>0,D36/D18,0) | E68: =IF(E18>0,E36/E18,0) | F68: =IF(F18>0,F36/F18,0) | G68: =IF(G18>0,G36/G18,0) | H68: =IF(H18>0,H36/H18,0) | I68: =IF(I18>0,I36/I18,0) | J68: =IF(J18>0,J36/J18,0) | ... AL68: =IF(AL18>0,AL36/AL18,0) | AN68: =N68 | AO68: =Z68 | AP68: =AL68
A69: Contribution par abonné | B69: € HT | C69: =IF(C18>0,C37/C18,0) | D69: =IF(D18>0,D37/D18,0) | E69: =IF(E18>0,E37/E18,0) | F69: =IF(F18>0,F37/F18,0) | G69: =IF(G18>0,G37/G18,0) | H69: =IF(H18>0,H37/H18,0) | I69: =IF(I18>0,I37/I18,0) | J69: =IF(J18>0,J37/J18,0) | ... AL69: =IF(AL18>0,AL37/AL18,0) | AN69: =N69 | AO69: =Z69 | AP69: =AL69
A70: Marge variable (% du CA HT) | B70: % | C70: =IF(C28>0,C37/C28,0) | D70: =IF(D28>0,D37/D28,0) | E70: =IF(E28>0,E37/E28,0) | F70: =IF(F28>0,F37/F28,0) | G70: =IF(G28>0,G37/G28,0) | H70: =IF(H28>0,H37/H28,0) | I70: =IF(I28>0,I37/I28,0) | J70: =IF(J28>0,J37/J28,0) | ... AL70: =IF(AL28>0,AL37/AL28,0) | AN70: =N70 | AO70: =Z70 | AP70: =AL70
A71: CAC effectif | B71: € | C71: =IF(C14>0,C39/C14,0) | D71: =IF(D14>0,D39/D14,0) | E71: =IF(E14>0,E39/E14,0) | F71: =IF(F14>0,F39/F14,0) | G71: =IF(G14>0,G39/G14,0) | H71: =IF(H14>0,H39/H14,0) | I71: =IF(I14>0,I39/I14,0) | J71: =IF(J14>0,J39/J14,0) | ... AL71: =IF(AL14>0,AL39/AL14,0) | AN71: =N71 | AO71: =Z71 | AP71: =AL71
A72: Payback du CAC (mois) | B72: mois | C72: =IF(C69>0,Hypothèses!$D$23*$E$4/C69,0) | D72: =IF(D69>0,Hypothèses!$D$23*$E$4/D69,0) | E72: =IF(E69>0,Hypothèses!$D$23*$E$4/E69,0) | F72: =IF(F69>0,Hypothèses!$D$23*$E$4/F69,0) | G72: =IF(G69>0,Hypothèses!$D$23*$E$4/G69,0) | H72: =IF(H69>0,Hypothèses!$D$23*$E$4/H69,0) | I72: =IF(I69>0,Hypothèses!$D$23*$E$4/I69,0) | J72: =IF(J69>0,Hypothèses!$D$23*$E$4/J69,0) | ... AL72: =IF(AL69>0,Hypothèses!$D$23*$E$4/AL69,0) | AN72: =N72 | AO72: =Z72 | AP72: =AL72
A73: LTV contributive simplifiée (contribution / churn) | B73: € HT | C73: =IF(Hypothèses!$D$26*$D$4>0,C69/(Hypothèses!$D$26*$D$4),0) | D73: =IF(Hypothèses!$D$26*$D$4>0,D69/(Hypothèses!$D$26*$D$4),0) | E73: =IF(Hypothèses!$D$26*$D$4>0,E69/(Hypothèses!$D$26*$D$4),0) | F73: =IF(Hypothèses!$D$26*$D$4>0,F69/(Hypothèses!$D$26*$D$4),0) | G73: =IF(Hypothèses!$D$26*$D$4>0,G69/(Hypothèses!$D$26*$D$4),0) | H73: =IF(Hypothèses!$D$26*$D$4>0,H69/(Hypothèses!$D$26*$D$4),0) | I73: =IF(Hypothèses!$D$26*$D$4>0,I69/(Hypothèses!$D$26*$D$4),0) | J73: =IF(Hypothèses!$D$26*$D$4>0,J69/(Hypothèses!$D$26*$D$4),0) | ... AL73: =IF(Hypothèses!$D$26*$D$4>0,AL69/(Hypothèses!$D$26*$D$4),0) | AN73: =N73 | AO73: =Z73 | AP73: =AL73
A74: LTV / CAC | B74: x | C74: =IF(Hypothèses!$D$23*$E$4>0,C73/(Hypothèses!$D$23*$E$4),0) | D74: =IF(Hypothèses!$D$23*$E$4>0,D73/(Hypothèses!$D$23*$E$4),0) | E74: =IF(Hypothèses!$D$23*$E$4>0,E73/(Hypothèses!$D$23*$E$4),0) | F74: =IF(Hypothèses!$D$23*$E$4>0,F73/(Hypothèses!$D$23*$E$4),0) | G74: =IF(Hypothèses!$D$23*$E$4>0,G73/(Hypothèses!$D$23*$E$4),0) | H74: =IF(Hypothèses!$D$23*$E$4>0,H73/(Hypothèses!$D$23*$E$4),0) | I74: =IF(Hypothèses!$D$23*$E$4>0,I73/(Hypothèses!$D$23*$E$4),0) | J74: =IF(Hypothèses!$D$23*$E$4>0,J73/(Hypothèses!$D$23*$E$4),0) | ... AL74: =IF(Hypothèses!$D$23*$E$4>0,AL73/(Hypothèses!$D$23*$E$4),0) | AN74: =N74 | AO74: =Z74 | AP74: =AL74

Sheet S02
A1: Sensibilité S02 : Churn 2 % (copie du Central)
A2: Flux en € HT sauf mention TTC. Formules vivantes ; ne saisir que dans l'onglet Hypothèses et la ligne de chocs ci-dessous.
A3: Chocs de sensibilité (1 = aucun ; retard en mois) | C3: Prix × | D3: Churn × | E3: CAC × | F3: Coût IA × | G3: Coûts fixes × | H3: Retard lancement (mois)
C4: 1 | D4: 0.6667 | E4: 1 | F4: 1 | G4: 1 | H4: 0
A5: Mois de lancement effectif | B5: =Hypothèses!$D$10+$H$4
A6: Ligne | B6: Unité | C6: M1 | D6: M2 | E6: M3 | F6: M4 | G6: M5 | H6: M6 | I6: M7 | J6: M8 | K6: M9 | L6: M10 | M6: M11 | N6: M12 | O6: M13 | P6: M14 | Q6: M15 | R6: M16 | S6: M17 | T6: M18 | U6: M19 | V6: M20 | W6: M21 | X6: M22 | Y6: M23 | Z6: M24 | AA6: M25 | AB6: M26 | AC6: M27 | AD6: M28 | AE6: M29 | AF6: M30 | AG6: M31 | AH6: M32 | AI6: M33 | AJ6: M34 | AK6: M35 | AL6: M36 | AN6: Année 1 | AO6: Année 2 | AP6: Année 3
A7: Mois | B7: n° | C7: 1 | D7: 2 | E7: 3 | F7: 4 | G7: 5 | H7: 6 | I7: 7 | J7: 8 | K7: 9 | L7: 10 | M7: 11 | N7: 12 | O7: 13 | P7: 14 | Q7: 15 | R7: 16 | S7: 17 | T7: 18 | U7: 19 | V7: 20 | W7: 21 | X7: 22 | Y7: 23 | Z7: 24 | AA7: 25 | AB7: 26 | AC7: 27 | AD7: 28 | AE7: 29 | AF7: 30 | AG7: 31 | AH7: 32 | AI7: 33 | AJ7: 34 | AK7: 35 | AL7: 36
A8: Date | C8: =EDATE(Hypothèses!$D$7,C7-1) | D8: =EDATE(Hypothèses!$D$7,D7-1) | E8: =EDATE(Hypothèses!$D$7,E7-1) | F8: =EDATE(Hypothèses!$D$7,F7-1) | G8: =EDATE(Hypothèses!$D$7,G7-1) | H8: =EDATE(Hypothèses!$D$7,H7-1) | I8: =EDATE(Hypothèses!$D$7,I7-1) | J8: =EDATE(Hypothèses!$D$7,J7-1) | ... AL8: =EDATE(Hypothèses!$D$7,AL7-1)
A9: Lancé ? (1 = oui) | B9: 0/1 | C9: =IF(C7>=$B$5,1,0) | D9: =IF(D7>=$B$5,1,0) | E9: =IF(E7>=$B$5,1,0) | F9: =IF(F7>=$B$5,1,0) | G9: =IF(G7>=$B$5,1,0) | H9: =IF(H7>=$B$5,1,0) | I9: =IF(I7>=$B$5,1,0) | J9: =IF(J7>=$B$5,1,0) | ... AL9: =IF(AL7>=$B$5,1,0)
A10: Pilote en cours ? (1 = oui) | B10: 0/1 | C10: =IF(AND(C7>=Hypothèses!$D$8,C7<$B$5),1,0) | D10: =IF(AND(D7>=Hypothèses!$D$8,D7<$B$5),1,0) | E10: =IF(AND(E7>=Hypothèses!$D$8,E7<$B$5),1,0) | F10: =IF(AND(F7>=Hypothèses!$D$8,F7<$B$5),1,0) | G10: =IF(AND(G7>=Hypothèses!$D$8,G7<$B$5),1,0) | H10: =IF(AND(H7>=Hypothèses!$D$8,H7<$B$5),1,0) | I10: =IF(AND(I7>=Hypothèses!$D$8,I7<$B$5),1,0) | J10: =IF(AND(J7>=Hypothèses!$D$8,J7<$B$5),1,0) | ... AL10: =IF(AND(AL7>=Hypothèses!$D$8,AL7<$B$5),1,0)
A11: Budget d'acquisition du mois | B11: € HT | C11: =IF(C9=1,IF(C7<=12,Hypothèses!$D$20,IF(C7<=24,Hypothèses!$D$21,Hypothèses!$D$22)),0) | D11: =IF(D9=1,IF(D7<=12,Hypothèses!$D$20,IF(D7<=24,Hypothèses!$D$21,Hypothèses!$D$22)),0) | E11: =IF(E9=1,IF(E7<=12,Hypothèses!$D$20,IF(E7<=24,Hypothèses!$D$21,Hypothèses!$D$22)),0) | F11: =IF(F9=1,IF(F7<=12,Hypothèses!$D$20,IF(F7<=24,Hypothèses!$D$21,Hypothèses!$D$22)),0) | G11: =IF(G9=1,IF(G7<=12,Hypothèses!$D$20,IF(G7<=24,Hypothèses!$D$21,Hypothèses!$D$22)),0) | H11: =IF(H9=1,IF(H7<=12,Hypothèses!$D$20,IF(H7<=24,Hypothèses!$D$21,Hypothèses!$D$22)),0) | I11: =IF(I9=1,IF(I7<=12,Hypothèses!$D$20,IF(I7<=24,Hypothèses!$D$21,Hypothèses!$D$22)),0) | J11: =IF(J9=1,IF(J7<=12,Hypothèses!$D$20,IF(J7<=24,Hypothèses!$D$21,Hypothèses!$D$22)),0) | ... AL11: =IF(AL9=1,IF(AL7<=12,Hypothèses!$D$20,IF(AL7<=24,Hypothèses!$D$21,Hypothèses!$D$22)),0) | AN11: =SUM(C11:N11) | AO11: =SUM(O11:Z11) | AP11: =SUM(AA11:AL11)
A12: Abonnés
A13: Abonnés en début de mois | B13: abonnés | C13: =0 | D13: =C18 | E13: =D18 | F13: =E18 | G13: =F18 | H13: =G18 | I13: =H18 | J13: =I18 | K13: =J18 | ... AL13: =AK18
A14: Nouveaux abonnés par acquisition payante | B14: abonnés | C14: =C11/(Hypothèses!$D$23*$E$4) | D14: =D11/(Hypothèses!$D$23*$E$4) | E14: =E11/(Hypothèses!$D$23*$E$4) | F14: =F11/(Hypothèses!$D$23*$E$4) | G14: =G11/(Hypothèses!$D$23*$E$4) | H14: =H11/(Hypothèses!$D$23*$E$4) | I14: =I11/(Hypothèses!$D$23*$E$4) | J14: =J11/(Hypothèses!$D$23*$E$4) | ... AL14: =AL11/(Hypothèses!$D$23*$E$4) | AN14: =SUM(C14:N14) | AO14: =SUM(O14:Z14) | AP14: =SUM(AA14:AL14)
A15: Nouveaux abonnés pilote | B15: abonnés | C15: =IF(C7=Hypothèses!$D$8,Hypothèses!$D$9,0) | D15: =IF(D7=Hypothèses!$D$8,Hypothèses!$D$9,0) | E15: =IF(E7=Hypothèses!$D$8,Hypothèses!$D$9,0) | F15: =IF(F7=Hypothèses!$D$8,Hypothèses!$D$9,0) | G15: =IF(G7=Hypothèses!$D$8,Hypothèses!$D$9,0) | H15: =IF(H7=Hypothèses!$D$8,Hypothèses!$D$9,0) | I15: =IF(I7=Hypothèses!$D$8,Hypothèses!$D$9,0) | J15: =IF(J7=Hypothèses!$D$8,Hypothèses!$D$9,0) | ... AL15: =IF(AL7=Hypothèses!$D$8,Hypothèses!$D$9,0) | AN15: =SUM(C15:N15) | AO15: =SUM(O15:Z15) | AP15: =SUM(AA15:AL15)
A16: Nouveaux abonnés organiques (parrainage) | B16: abonnés | C16: =C9*C13*Hypothèses!$D$24 | D16: =D9*D13*Hypothèses!$D$24 | E16: =E9*E13*Hypothèses!$D$24 | F16: =F9*F13*Hypothèses!$D$24 | G16: =G9*G13*Hypothèses!$D$24 | H16: =H9*H13*Hypothèses!$D$24 | I16: =I9*I13*Hypothèses!$D$24 | J16: =J9*J13*Hypothèses!$D$24 | ... AL16: =AL9*AL13*Hypothèses!$D$24 | AN16: =SUM(C16:N16) | AO16: =SUM(O16:Z16) | AP16: =SUM(AA16:AL16)
A17: Résiliations | B17: abonnés | C17: =C13*Hypothèses!$D$26*$D$4 | D17: =D13*Hypothèses!$D$26*$D$4 | E17: =E13*Hypothèses!$D$26*$D$4 | F17: =F13*Hypothèses!$D$26*$D$4 | G17: =G13*Hypothèses!$D$26*$D$4 | H17: =H13*Hypothèses!$D$26*$D$4 | I17: =I13*Hypothèses!$D$26*$D$4 | J17: =J13*Hypothèses!$D$26*$D$4 | ... AL17: =AL13*Hypothèses!$D$26*$D$4 | AN17: =SUM(C17:N17) | AO17: =SUM(O17:Z17) | AP17: =SUM(AA17:AL17)
A18: Abonnés en fin de mois | B18: abonnés | C18: =C13+C14+C15+C16-C17 | D18: =D13+D14+D15+D16-D17 | E18: =E13+E14+E15+E16-E17 | F18: =F13+F14+F15+F16-F17 | G18: =G13+G14+G15+G16-G17 | H18: =H13+H14+H15+H16-H17 | I18: =I13+I14+I15+I16-I17 | J18: =J13+J14+J15+J16-J17 | ... AL18: =AL13+AL14+AL15+AL16-AL17 | AN18: =N18 | AO18: =Z18 | AP18: =AL18
A19: dont Personal | B19: abonnés | C19: =C18*Hypothèses!$D$16 | D19: =D18*Hypothèses!$D$16 | E19: =E18*Hypothèses!$D$16 | F19: =F18*Hypothèses!$D$16 | G19: =G18*Hypothèses!$D$16 | H19: =H18*Hypothèses!$D$16 | I19: =I18*Hypothèses!$D$16 | J19: =J18*Hypothèses!$D$16 | ... AL19: =AL18*Hypothèses!$D$16 | AN19: =N19 | AO19: =Z19 | AP19: =AL19
A20: dont Premium | B20: abonnés | C20: =C18*Hypothèses!$D$17 | D20: =D18*Hypothèses!$D$17 | E20: =E18*Hypothèses!$D$17 | F20: =F18*Hypothèses!$D$17 | G20: =G18*Hypothèses!$D$17 | H20: =H18*Hypothèses!$D$17 | I20: =I18*Hypothèses!$D$17 | J20: =J18*Hypothèses!$D$17 | ... AL20: =AL18*Hypothèses!$D$17 | AN20: =N20 | AO20: =Z20 | AP20: =AL20
A21: dont Family | B21: abonnés | C21: =C18*Hypothèses!$D$18 | D21: =D18*Hypothèses!$D$18 | E21: =E18*Hypothèses!$D$18 | F21: =F18*Hypothèses!$D$18 | G21: =G18*Hypothèses!$D$18 | H21: =H18*Hypothèses!$D$18 | I21: =I18*Hypothèses!$D$18 | J21: =J18*Hypothèses!$D$18 | ... AL21: =AL18*Hypothèses!$D$18 | AN21: =N21 | AO21: =Z21 | AP21: =AL21
A22: Revenus
A23: Facturation Personal TTC | B23: € TTC | C23: =C19*Hypothèses!$D$12*$C$4 | D23: =D19*Hypothèses!$D$12*$C$4 | E23: =E19*Hypothèses!$D$12*$C$4 | F23: =F19*Hypothèses!$D$12*$C$4 | G23: =G19*Hypothèses!$D$12*$C$4 | H23: =H19*Hypothèses!$D$12*$C$4 | I23: =I19*Hypothèses!$D$12*$C$4 | J23: =J19*Hypothèses!$D$12*$C$4 | ... AL23: =AL19*Hypothèses!$D$12*$C$4 | AN23: =SUM(C23:N23) | AO23: =SUM(O23:Z23) | AP23: =SUM(AA23:AL23)
A24: Facturation Premium TTC | B24: € TTC | C24: =C20*Hypothèses!$D$13*$C$4 | D24: =D20*Hypothèses!$D$13*$C$4 | E24: =E20*Hypothèses!$D$13*$C$4 | F24: =F20*Hypothèses!$D$13*$C$4 | G24: =G20*Hypothèses!$D$13*$C$4 | H24: =H20*Hypothèses!$D$13*$C$4 | I24: =I20*Hypothèses!$D$13*$C$4 | J24: =J20*Hypothèses!$D$13*$C$4 | ... AL24: =AL20*Hypothèses!$D$13*$C$4 | AN24: =SUM(C24:N24) | AO24: =SUM(O24:Z24) | AP24: =SUM(AA24:AL24)
A25: Facturation Family TTC | B25: € TTC | C25: =C21*Hypothèses!$D$14*$C$4 | D25: =D21*Hypothèses!$D$14*$C$4 | E25: =E21*Hypothèses!$D$14*$C$4 | F25: =F21*Hypothèses!$D$14*$C$4 | G25: =G21*Hypothèses!$D$14*$C$4 | H25: =H21*Hypothèses!$D$14*$C$4 | I25: =I21*Hypothèses!$D$14*$C$4 | J25: =J21*Hypothèses!$D$14*$C$4 | ... AL25: =AL21*Hypothèses!$D$14*$C$4 | AN25: =SUM(C25:N25) | AO25: =SUM(O25:Z25) | AP25: =SUM(AA25:AL25)
A26: Facturation totale TTC (MRR TTC) | B26: € TTC | C26: =C23+C24+C25 | D26: =D23+D24+D25 | E26: =E23+E24+E25 | F26: =F23+F24+F25 | G26: =G23+G24+G25 | H26: =H23+H24+H25 | I26: =I23+I24+I25 | J26: =J23+J24+J25 | ... AL26: =AL23+AL24+AL25 | AN26: =SUM(C26:N26) | AO26: =SUM(O26:Z26) | AP26: =SUM(AA26:AL26)
A27: TVA collectée | B27: € | C27: =C26*Hypothèses!$D$15/(1+Hypothèses!$D$15) | D27: =D26*Hypothèses!$D$15/(1+Hypothèses!$D$15) | E27: =E26*Hypothèses!$D$15/(1+Hypothèses!$D$15) | F27: =F26*Hypothèses!$D$15/(1+Hypothèses!$D$15) | G27: =G26*Hypothèses!$D$15/(1+Hypothèses!$D$15) | H27: =H26*Hypothèses!$D$15/(1+Hypothèses!$D$15) | I27: =I26*Hypothèses!$D$15/(1+Hypothèses!$D$15) | J27: =J26*Hypothèses!$D$15/(1+Hypothèses!$D$15) | ... AL27: =AL26*Hypothèses!$D$15/(1+Hypothèses!$D$15) | AN27: =SUM(C27:N27) | AO27: =SUM(O27:Z27) | AP27: =SUM(AA27:AL27)
A28: Chiffre d'affaires HT | B28: € HT | C28: =C26-C27 | D28: =D26-D27 | E28: =E26-E27 | F28: =F26-F27 | G28: =G26-G27 | H28: =H26-H27 | I28: =I26-I27 | J28: =J26-J27 | ... AL28: =AL26-AL27 | AN28: =SUM(C28:N28) | AO28: =SUM(O28:Z28) | AP28: =SUM(AA28:AL28)
A29: Impayés (TTC) | B29: € TTC | C29: =C26*Hypothèses!$D$27 | D29: =D26*Hypothèses!$D$27 | E29: =E26*Hypothèses!$D$27 | F29: =F26*Hypothèses!$D$27 | G29: =G26*Hypothèses!$D$27 | H29: =H26*Hypothèses!$D$27 | I29: =I26*Hypothèses!$D$27 | J29: =J26*Hypothèses!$D$27 | ... AL29: =AL26*Hypothèses!$D$27 | AN29: =SUM(C29:N29) | AO29: =SUM(O29:Z29) | AP29: =SUM(AA29:AL29)
A30: Frais de paiement | B30: € | C30: =(C26-C29)*Hypothèses!$D$28+C18*Hypothèses!$D$29 | D30: =(D26-D29)*Hypothèses!$D$28+D18*Hypothèses!$D$29 | E30: =(E26-E29)*Hypothèses!$D$28+E18*Hypothèses!$D$29 | F30: =(F26-F29)*Hypothèses!$D$28+F18*Hypothèses!$D$29 | G30: =(G26-G29)*Hypothèses!$D$28+G18*Hypothèses!$D$29 | H30: =(H26-H29)*Hypothèses!$D$28+H18*Hypothèses!$D$29 | I30: =(I26-I29)*Hypothèses!$D$28+I18*Hypothèses!$D$29 | J30: =(J26-J29)*Hypothèses!$D$28+J18*Hypothèses!$D$29 | ... AL30: =(AL26-AL29)*Hypothèses!$D$28+AL18*Hypothèses!$D$29 | AN30: =SUM(C30:N30) | AO30: =SUM(O30:Z30) | AP30: =SUM(AA30:AL30)
A31: Encaissements nets TTC | B31: € TTC | C31: =C26-C29-C30 | D31: =D26-D29-D30 | E31: =E26-E29-E30 | F31: =F26-F29-F30 | G31: =G26-G29-G30 | H31: =H26-H29-H30 | I31: =I26-I29-I30 | J31: =J26-J29-J30 | ... AL31: =AL26-AL29-AL30 | AN31: =SUM(C31:N31) | AO31: =SUM(O31:Z31) | AP31: =SUM(AA31:AL31)
A32: Coûts variables
A33: Coût IA et outils (missions × coût par mission) | B33: € HT | C33: =(C19*Hypothèses!$D$31+C20*Hypothèses!$D$32+C21*Hypothèses!$D$33)*Hypothèses!$D$34*$F$4 | D33: =(D19*Hypothèses!$D$31+D20*Hypothèses!$D$32+D21*Hypothèses!$D$33)*Hypothèses!$D$34*$F$4 | E33: =(E19*Hypothèses!$D$31+E20*Hypothèses!$D$32+E21*Hypothèses!$D$33)*Hypothèses!$D$34*$F$4 | F33: =(F19*Hypothèses!$D$31+F20*Hypothèses!$D$32+F21*Hypothèses!$D$33)*Hypothèses!$D$34*$F$4 | G33: =(G19*Hypothèses!$D$31+G20*Hypothèses!$D$32+G21*Hypothèses!$D$33)*Hypothèses!$D$34*$F$4 | H33: =(H19*Hypothèses!$D$31+H20*Hypothèses!$D$32+H21*Hypothèses!$D$33)*Hypothèses!$D$34*$F$4 | I33: =(I19*Hypothèses!$D$31+I20*Hypothèses!$D$32+I21*Hypothèses!$D$33)*Hypothèses!$D$34*$F$4 | J33: =(J19*Hypothèses!$D$31+J20*Hypothèses!$D$32+J21*Hypothèses!$D$33)*Hypothèses!$D$34*$F$4 | ... AL33: =(AL19*Hypothèses!$D$31+AL20*Hypothèses!$D$32+AL21*Hypothèses!$D$33)*Hypothèses!$D$34*$F$4 | AN33: =SUM(C33:N33) | AO33: =SUM(O33:Z33) | AP33: =SUM(AA33:AL33)
A34: Hébergement, stockage, connecteurs | B34: € HT | C34: =C18*Hypothèses!$D$35 | D34: =D18*Hypothèses!$D$35 | E34: =E18*Hypothèses!$D$35 | F34: =F18*Hypothèses!$D$35 | G34: =G18*Hypothèses!$D$35 | H34: =H18*Hypothèses!$D$35 | I34: =I18*Hypothèses!$D$35 | J34: =J18*Hypothèses!$D$35 | ... AL34: =AL18*Hypothèses!$D$35 | AN34: =SUM(C34:N34) | AO34: =SUM(O34:Z34) | AP34: =SUM(AA34:AL34)
A35: Support humain | B35: € HT | C35: =C18*Hypothèses!$D$36 | D35: =D18*Hypothèses!$D$36 | E35: =E18*Hypothèses!$D$36 | F35: =F18*Hypothèses!$D$36 | G35: =G18*Hypothèses!$D$36 | H35: =H18*Hypothèses!$D$36 | I35: =I18*Hypothèses!$D$36 | J35: =J18*Hypothèses!$D$36 | ... AL35: =AL18*Hypothèses!$D$36 | AN35: =SUM(C35:N35) | AO35: =SUM(O35:Z35) | AP35: =SUM(AA35:AL35)
A36: Total coûts variables | B36: € HT | C36: =C33+C34+C35 | D36: =D33+D34+D35 | E36: =E33+E34+E35 | F36: =F33+F34+F35 | G36: =G33+G34+G35 | H36: =H33+H34+H35 | I36: =I33+I34+I35 | J36: =J33+J34+J35 | ... AL36: =AL33+AL34+AL35 | AN36: =SUM(C36:N36) | AO36: =SUM(O36:Z36) | AP36: =SUM(AA36:AL36)
A37: Marge sur coûts variables (CA HT − variables − frais − impayés HT) | B37: € HT | C37: =C28-C36-C30-C29/(1+Hypothèses!$D$15) | D37: =D28-D36-D30-D29/(1+Hypothèses!$D$15) | E37: =E28-E36-E30-E29/(1+Hypothèses!$D$15) | F37: =F28-F36-F30-F29/(1+Hypothèses!$D$15) | G37: =G28-G36-G30-G29/(1+Hypothèses!$D$15) | H37: =H28-H36-H30-H29/(1+Hypothèses!$D$15) | I37: =I28-I36-I30-I29/(1+Hypothèses!$D$15) | J37: =J28-J36-J30-J29/(1+Hypothèses!$D$15) | ... AL37: =AL28-AL36-AL30-AL29/(1+Hypothèses!$D$15) | AN37: =SUM(C37:N37) | AO37: =SUM(O37:Z37) | AP37: =SUM(AA37:AL37)
A38: Acquisition et coûts fixes
A39: Dépenses d'acquisition | B39: € HT | C39: =C11 | D39: =D11 | E39: =E11 | F39: =F11 | G39: =G11 | H39: =H11 | I39: =I11 | J39: =J11 | ... AL39: =AL11 | AN39: =SUM(C39:N39) | AO39: =SUM(O39:Z39) | AP39: =SUM(AA39:AL39)
A40: Rémunération des fondateurs | B40: € HT | C40: =IF(C7>=Hypothèses!$D$39,Hypothèses!$D$38*Hypothèses!$D$40,0)*$G$4 | D40: =IF(D7>=Hypothèses!$D$39,Hypothèses!$D$38*Hypothèses!$D$40,0)*$G$4 | E40: =IF(E7>=Hypothèses!$D$39,Hypothèses!$D$38*Hypothèses!$D$40,0)*$G$4 | F40: =IF(F7>=Hypothèses!$D$39,Hypothèses!$D$38*Hypothèses!$D$40,0)*$G$4 | G40: =IF(G7>=Hypothèses!$D$39,Hypothèses!$D$38*Hypothèses!$D$40,0)*$G$4 | H40: =IF(H7>=Hypothèses!$D$39,Hypothèses!$D$38*Hypothèses!$D$40,0)*$G$4 | I40: =IF(I7>=Hypothèses!$D$39,Hypothèses!$D$38*Hypothèses!$D$40,0)*$G$4 | J40: =IF(J7>=Hypothèses!$D$39,Hypothèses!$D$38*Hypothèses!$D$40,0)*$G$4 | ... AL40: =IF(AL7>=Hypothèses!$D$39,Hypothèses!$D$38*Hypothèses!$D$40,0)*$G$4 | AN40: =SUM(C40:N40) | AO40: =SUM(O40:Z40) | AP40: =SUM(AA40:AL40)
A41: Salarié 1 (growth / customer success) | B41: € HT | C41: =IF(C7>=Hypothèses!$D$41,Hypothèses!$D$42,0)*$G$4 | D41: =IF(D7>=Hypothèses!$D$41,Hypothèses!$D$42,0)*$G$4 | E41: =IF(E7>=Hypothèses!$D$41,Hypothèses!$D$42,0)*$G$4 | F41: =IF(F7>=Hypothèses!$D$41,Hypothèses!$D$42,0)*$G$4 | G41: =IF(G7>=Hypothèses!$D$41,Hypothèses!$D$42,0)*$G$4 | H41: =IF(H7>=Hypothèses!$D$41,Hypothèses!$D$42,0)*$G$4 | I41: =IF(I7>=Hypothèses!$D$41,Hypothèses!$D$42,0)*$G$4 | J41: =IF(J7>=Hypothèses!$D$41,Hypothèses!$D$42,0)*$G$4 | ... AL41: =IF(AL7>=Hypothèses!$D$41,Hypothèses!$D$42,0)*$G$4 | AN41: =SUM(C41:N41) | AO41: =SUM(O41:Z41) | AP41: =SUM(AA41:AL41)
A42: Salarié 2 (ingénieur) | B42: € HT | C42: =IF(C7>=Hypothèses!$D$43,Hypothèses!$D$44,0)*$G$4 | D42: =IF(D7>=Hypothèses!$D$43,Hypothèses!$D$44,0)*$G$4 | E42: =IF(E7>=Hypothèses!$D$43,Hypothèses!$D$44,0)*$G$4 | F42: =IF(F7>=Hypothèses!$D$43,Hypothèses!$D$44,0)*$G$4 | G42: =IF(G7>=Hypothèses!$D$43,Hypothèses!$D$44,0)*$G$4 | H42: =IF(H7>=Hypothèses!$D$43,Hypothèses!$D$44,0)*$G$4 | I42: =IF(I7>=Hypothèses!$D$43,Hypothèses!$D$44,0)*$G$4 | J42: =IF(J7>=Hypothèses!$D$43,Hypothèses!$D$44,0)*$G$4 | ... AL42: =IF(AL7>=Hypothèses!$D$43,Hypothèses!$D$44,0)*$G$4 | AN42: =SUM(C42:N42) | AO42: =SUM(O42:Z42) | AP42: =SUM(AA42:AL42)
A43: Développement MVP externe (étalé jusqu'au lancement) | B43: € HT | C43: =IF(C7<$B$5,Hypothèses!$D$45/MAX(1,$B$5-1),0) | D43: =IF(D7<$B$5,Hypothèses!$D$45/MAX(1,$B$5-1),0) | E43: =IF(E7<$B$5,Hypothèses!$D$45/MAX(1,$B$5-1),0) | F43: =IF(F7<$B$5,Hypothèses!$D$45/MAX(1,$B$5-1),0) | G43: =IF(G7<$B$5,Hypothèses!$D$45/MAX(1,$B$5-1),0) | H43: =IF(H7<$B$5,Hypothèses!$D$45/MAX(1,$B$5-1),0) | I43: =IF(I7<$B$5,Hypothèses!$D$45/MAX(1,$B$5-1),0) | J43: =IF(J7<$B$5,Hypothèses!$D$45/MAX(1,$B$5-1),0) | ... AL43: =IF(AL7<$B$5,Hypothèses!$D$45/MAX(1,$B$5-1),0) | AN43: =SUM(C43:N43) | AO43: =SUM(O43:Z43) | AP43: =SUM(AA43:AL43)
A44: Outils et SaaS | B44: € HT | C44: =Hypothèses!$D$46*$G$4 | D44: =Hypothèses!$D$46*$G$4 | E44: =Hypothèses!$D$46*$G$4 | F44: =Hypothèses!$D$46*$G$4 | G44: =Hypothèses!$D$46*$G$4 | H44: =Hypothèses!$D$46*$G$4 | I44: =Hypothèses!$D$46*$G$4 | J44: =Hypothèses!$D$46*$G$4 | ... AL44: =Hypothèses!$D$46*$G$4 | AN44: =SUM(C44:N44) | AO44: =SUM(O44:Z44) | AP44: =SUM(AA44:AL44)
A45: Juridique et comptabilité | B45: € HT | C45: =Hypothèses!$D$47*$G$4 | D45: =Hypothèses!$D$47*$G$4 | E45: =Hypothèses!$D$47*$G$4 | F45: =Hypothèses!$D$47*$G$4 | G45: =Hypothèses!$D$47*$G$4 | H45: =Hypothèses!$D$47*$G$4 | I45: =Hypothèses!$D$47*$G$4 | J45: =Hypothèses!$D$47*$G$4 | ... AL45: =Hypothèses!$D$47*$G$4 | AN45: =SUM(C45:N45) | AO45: =SUM(O45:Z45) | AP45: =SUM(AA45:AL45)
A46: Assurance RC pro | B46: € | C46: =C9*Hypothèses!$D$48*$G$4 | D46: =D9*Hypothèses!$D$48*$G$4 | E46: =E9*Hypothèses!$D$48*$G$4 | F46: =F9*Hypothèses!$D$48*$G$4 | G46: =G9*Hypothèses!$D$48*$G$4 | H46: =H9*Hypothèses!$D$48*$G$4 | I46: =I9*Hypothèses!$D$48*$G$4 | J46: =J9*Hypothèses!$D$48*$G$4 | ... AL46: =AL9*Hypothèses!$D$48*$G$4 | AN46: =SUM(C46:N46) | AO46: =SUM(O46:Z46) | AP46: =SUM(AA46:AL46)
A47: Marketing fixe | B47: € HT | C47: =C9*Hypothèses!$D$49*$G$4 | D47: =D9*Hypothèses!$D$49*$G$4 | E47: =E9*Hypothèses!$D$49*$G$4 | F47: =F9*Hypothèses!$D$49*$G$4 | G47: =G9*Hypothèses!$D$49*$G$4 | H47: =H9*Hypothèses!$D$49*$G$4 | I47: =I9*Hypothèses!$D$49*$G$4 | J47: =J9*Hypothèses!$D$49*$G$4 | ... AL47: =AL9*Hypothèses!$D$49*$G$4 | AN47: =SUM(C47:N47) | AO47: =SUM(O47:Z47) | AP47: =SUM(AA47:AL47)
A48: Frais généraux | B48: € HT | C48: =Hypothèses!$D$50*$G$4 | D48: =Hypothèses!$D$50*$G$4 | E48: =Hypothèses!$D$50*$G$4 | F48: =Hypothèses!$D$50*$G$4 | G48: =Hypothèses!$D$50*$G$4 | H48: =Hypothèses!$D$50*$G$4 | I48: =Hypothèses!$D$50*$G$4 | J48: =Hypothèses!$D$50*$G$4 | ... AL48: =Hypothèses!$D$50*$G$4 | AN48: =SUM(C48:N48) | AO48: =SUM(O48:Z48) | AP48: =SUM(AA48:AL48)
A49: Audit de sécurité (annuel, à partir du lancement) | B49: € HT | C49: =IF(AND(C9=1,MOD(C7-$B$5,12)=0),Hypothèses!$D$51,0)*$G$4 | D49: =IF(AND(D9=1,MOD(D7-$B$5,12)=0),Hypothèses!$D$51,0)*$G$4 | E49: =IF(AND(E9=1,MOD(E7-$B$5,12)=0),Hypothèses!$D$51,0)*$G$4 | F49: =IF(AND(F9=1,MOD(F7-$B$5,12)=0),Hypothèses!$D$51,0)*$G$4 | G49: =IF(AND(G9=1,MOD(G7-$B$5,12)=0),Hypothèses!$D$51,0)*$G$4 | H49: =IF(AND(H9=1,MOD(H7-$B$5,12)=0),Hypothèses!$D$51,0)*$G$4 | I49: =IF(AND(I9=1,MOD(I7-$B$5,12)=0),Hypothèses!$D$51,0)*$G$4 | J49: =IF(AND(J9=1,MOD(J7-$B$5,12)=0),Hypothèses!$D$51,0)*$G$4 | ... AL49: =IF(AND(AL9=1,MOD(AL7-$B$5,12)=0),Hypothèses!$D$51,0)*$G$4 | AN49: =SUM(C49:N49) | AO49: =SUM(O49:Z49) | AP49: =SUM(AA49:AL49)
A50: Frais de constitution | B50: € HT | C50: =IF(C7=2,Hypothèses!$D$52,0) | D50: =IF(D7=2,Hypothèses!$D$52,0) | E50: =IF(E7=2,Hypothèses!$D$52,0) | F50: =IF(F7=2,Hypothèses!$D$52,0) | G50: =IF(G7=2,Hypothèses!$D$52,0) | H50: =IF(H7=2,Hypothèses!$D$52,0) | I50: =IF(I7=2,Hypothèses!$D$52,0) | J50: =IF(J7=2,Hypothèses!$D$52,0) | ... AL50: =IF(AL7=2,Hypothèses!$D$52,0) | AN50: =SUM(C50:N50) | AO50: =SUM(O50:Z50) | AP50: =SUM(AA50:AL50)
A51: Total coûts fixes | B51: € HT | C51: =SUM(C40:C50) | D51: =SUM(D40:D50) | E51: =SUM(E40:E50) | F51: =SUM(F40:F50) | G51: =SUM(G40:G50) | H51: =SUM(H40:H50) | I51: =SUM(I40:I50) | J51: =SUM(J40:J50) | ... AL51: =SUM(AL40:AL50) | AN51: =SUM(C51:N51) | AO51: =SUM(O51:Z51) | AP51: =SUM(AA51:AL51)
A52: EBITDA (marge variable − acquisition − fixes) | B52: € HT | C52: =C37-C39-C51 | D52: =D37-D39-D51 | E52: =E37-E39-E51 | F52: =F37-F39-F51 | G52: =G37-G39-G51 | H52: =H37-H39-H51 | I52: =I37-I39-I51 | J52: =J37-J39-J51 | ... AL52: =AL37-AL39-AL51 | AN52: =SUM(C52:N52) | AO52: =SUM(O52:Z52) | AP52: =SUM(AA52:AL52)
A53: EBITDA positif ? (1 = oui) | B53: 0/1 | C53: =IF(C52>0,1,0) | D53: =IF(D52>0,1,0) | E53: =IF(E52>0,1,0) | F53: =IF(F52>0,1,0) | G53: =IF(G52>0,1,0) | H53: =IF(H52>0,1,0) | I53: =IF(I52>0,1,0) | J53: =IF(J52>0,1,0) | ... AL53: =IF(AL52>0,1,0)
A54: Trésorerie
A55: TVA collectée reversée (mois suivant) | B55: € | C55: =0 | D55: =C27 | E55: =D27 | F55: =E27 | G55: =F27 | H55: =G27 | I55: =H27 | J55: =I27 | K55: =J27 | ... AL55: =AK27 | AN55: =SUM(C55:N55) | AO55: =SUM(O55:Z55) | AP55: =SUM(AA55:AL55)
A56: TVA déductible récupérée (mois suivant, coûts externes) | B56: € | C56: =0 | D56: =(C36+C39+C43+C44+C45+C47+C48+C49+C50)*Hypothèses!$D$15 | E56: =(D36+D39+D43+D44+D45+D47+D48+D49+D50)*Hypothèses!$D$15 | F56: =(E36+E39+E43+E44+E45+E47+E48+E49+E50)*Hypothèses!$D$15 | G56: =(F36+F39+F43+F44+F45+F47+F48+F49+F50)*Hypothèses!$D$15 | H56: =(G36+G39+G43+G44+G45+G47+G48+G49+G50)*Hypothèses!$D$15 | I56: =(H36+H39+H43+H44+H45+H47+H48+H49+H50)*Hypothèses!$D$15 | J56: =(I36+I39+I43+I44+I45+I47+I48+I49+I50)*Hypothèses!$D$15 | K56: =(J36+J39+J43+J44+J45+J47+J48+J49+J50)*Hypothèses!$D$15 | ... AL56: =(AK36+AK39+AK43+AK44+AK45+AK47+AK48+AK49+AK50)*Hypothèses!$D$15 | AN56: =SUM(C56:N56) | AO56: =SUM(O56:Z56) | AP56: =SUM(AA56:AL56)
A57: Financement reçu | B57: € | C57: =Hypothèses!$D$56*(IF(C7=Hypothèses!$D$57,Hypothèses!$D$58,0)+IF(C7=Hypothèses!$D$59,Hypothèses!$D$60,0)+IF(C7=Hypothèses!$D$61,Hypothèses!$D$62,0)) | D57: =Hypothèses!$D$56*(IF(D7=Hypothèses!$D$57,Hypothèses!$D$58,0)+IF(D7=Hypothèses!$D$59,Hypothèses!$D$60,0)+IF(D7=Hypothèses!$D$61,Hypothèses!$D$62,0)) | E57: =Hypothèses!$D$56*(IF(E7=Hypothèses!$D$57,Hypothèses!$D$58,0)+IF(E7=Hypothèses!$D$59,Hypothèses!$D$60,0)+IF(E7=Hypothèses!$D$61,Hypothèses!$D$62,0)) | F57: =Hypothèses!$D$56*(IF(F7=Hypothèses!$D$57,Hypothèses!$D$58,0)+IF(F7=Hypothèses!$D$59,Hypothèses!$D$60,0)+IF(F7=Hypothèses!$D$61,Hypothèses!$D$62,0)) | G57: =Hypothèses!$D$56*(IF(G7=Hypothèses!$D$57,Hypothèses!$D$58,0)+IF(G7=Hypothèses!$D$59,Hypothèses!$D$60,0)+IF(G7=Hypothèses!$D$61,Hypothèses!$D$62,0)) | H57: =Hypothèses!$D$56*(IF(H7=Hypothèses!$D$57,Hypothèses!$D$58,0)+IF(H7=Hypothèses!$D$59,Hypothèses!$D$60,0)+IF(H7=Hypothèses!$D$61,Hypothèses!$D$62,0)) | I57: =Hypothèses!$D$56*(IF(I7=Hypothèses!$D$57,Hypothèses!$D$58,0)+IF(I7=Hypothèses!$D$59,Hypothèses!$D$60,0)+IF(I7=Hypothèses!$D$61,Hypothèses!$D$62,0)) | J57: =Hypothèses!$D$56*(IF(J7=Hypothèses!$D$57,Hypothèses!$D$58,0)+IF(J7=Hypothèses!$D$59,Hypothèses!$D$60,0)+IF(J7=Hypothèses!$D$61,Hypothèses!$D$62,0)) | ... AL57: =Hypothèses!$D$56*(IF(AL7=Hypothèses!$D$57,Hypothèses!$D$58,0)+IF(AL7=Hypothèses!$D$59,Hypothèses!$D$60,0)+IF(AL7=Hypothèses!$D$61,Hypothèses!$D$62,0)) | AN57: =SUM(C57:N57) | AO57: =SUM(O57:Z57) | AP57: =SUM(AA57:AL57)
A58: Trésorerie d'ouverture | B58: € | C58: =Hypothèses!$D$54 | D58: =C60 | E58: =D60 | F58: =E60 | G58: =F60 | H58: =G60 | I58: =H60 | J58: =I60 | K58: =J60 | ... AL58: =AK60
A59: Flux de trésorerie du mois | B59: € | C59: =C31-C36-C39-C51-C55+C56+C57 | D59: =D31-D36-D39-D51-D55+D56+D57 | E59: =E31-E36-E39-E51-E55+E56+E57 | F59: =F31-F36-F39-F51-F55+F56+F57 | G59: =G31-G36-G39-G51-G55+G56+G57 | H59: =H31-H36-H39-H51-H55+H56+H57 | I59: =I31-I36-I39-I51-I55+I56+I57 | J59: =J31-J36-J39-J51-J55+J56+J57 | ... AL59: =AL31-AL36-AL39-AL51-AL55+AL56+AL57 | AN59: =SUM(C59:N59) | AO59: =SUM(O59:Z59) | AP59: =SUM(AA59:AL59)
A60: Trésorerie de clôture | B60: € | C60: =C58+C59 | D60: =D58+D59 | E60: =E58+E59 | F60: =F58+F59 | G60: =G58+G59 | H60: =H58+H59 | I60: =I58+I59 | J60: =J58+J59 | ... AL60: =AL58+AL59 | AN60: =N60 | AO60: =Z60 | AP60: =AL60
A61: Financement cumulé | B61: € | C61: =0+C57 | D61: =C61+D57 | E61: =D61+E57 | F61: =E61+F57 | G61: =F61+G57 | H61: =G61+H57 | I61: =H61+I57 | J61: =I61+J57 | K61: =J61+K57 | ... AL61: =AK61+AL57 | AN61: =N61 | AO61: =Z61 | AP61: =AL61
A62: Trésorerie cumulée hors financement | B62: € | C62: =C60-C61 | D62: =D60-D61 | E62: =E60-E61 | F62: =F60-F61 | G62: =G60-G61 | H62: =H60-H61 | I62: =I60-I61 | J62: =J60-J61 | ... AL62: =AL60-AL61 | AN62: =N62 | AO62: =Z62 | AP62: =AL62
A63: Point bas glissant hors financement | B63: € | C63: =C62 | D63: =MIN(C63,D62) | E63: =MIN(D63,E62) | F63: =MIN(E63,F62) | G63: =MIN(F63,G62) | H63: =MIN(G63,H62) | I63: =MIN(H63,I62) | J63: =MIN(I63,J62) | K63: =MIN(J63,K62) | ... AL63: =MIN(AK63,AL62) | AN63: =N63 | AO63: =Z63 | AP63: =AL63
A64: Trésorerie cumulée hors financement positive après lancement ? (1 = oui) | B64: 0/1 | C64: =IF(AND(C9=1,C62>0),1,0) | D64: =IF(AND(D9=1,D62>0),1,0) | E64: =IF(AND(E9=1,E62>0),1,0) | F64: =IF(AND(F9=1,F62>0),1,0) | G64: =IF(AND(G9=1,G62>0),1,0) | H64: =IF(AND(H9=1,H62>0),1,0) | I64: =IF(AND(I9=1,I62>0),1,0) | J64: =IF(AND(J9=1,J62>0),1,0) | ... AL64: =IF(AND(AL9=1,AL62>0),1,0)
A65: Indicateurs
A66: ARR HT instantané (CA HT × 12) | B66: € HT | C66: =C28*12 | D66: =D28*12 | E66: =E28*12 | F66: =F28*12 | G66: =G28*12 | H66: =H28*12 | I66: =I28*12 | J66: =J28*12 | ... AL66: =AL28*12 | AN66: =N66 | AO66: =Z66 | AP66: =AL66
A67: ARPA HT (CA HT / abonnés) | B67: € HT | C67: =IF(C18>0,C28/C18,0) | D67: =IF(D18>0,D28/D18,0) | E67: =IF(E18>0,E28/E18,0) | F67: =IF(F18>0,F28/F18,0) | G67: =IF(G18>0,G28/G18,0) | H67: =IF(H18>0,H28/H18,0) | I67: =IF(I18>0,I28/I18,0) | J67: =IF(J18>0,J28/J18,0) | ... AL67: =IF(AL18>0,AL28/AL18,0) | AN67: =N67 | AO67: =Z67 | AP67: =AL67
A68: Coût variable par abonné | B68: € HT | C68: =IF(C18>0,C36/C18,0) | D68: =IF(D18>0,D36/D18,0) | E68: =IF(E18>0,E36/E18,0) | F68: =IF(F18>0,F36/F18,0) | G68: =IF(G18>0,G36/G18,0) | H68: =IF(H18>0,H36/H18,0) | I68: =IF(I18>0,I36/I18,0) | J68: =IF(J18>0,J36/J18,0) | ... AL68: =IF(AL18>0,AL36/AL18,0) | AN68: =N68 | AO68: =Z68 | AP68: =AL68
A69: Contribution par abonné | B69: € HT | C69: =IF(C18>0,C37/C18,0) | D69: =IF(D18>0,D37/D18,0) | E69: =IF(E18>0,E37/E18,0) | F69: =IF(F18>0,F37/F18,0) | G69: =IF(G18>0,G37/G18,0) | H69: =IF(H18>0,H37/H18,0) | I69: =IF(I18>0,I37/I18,0) | J69: =IF(J18>0,J37/J18,0) | ... AL69: =IF(AL18>0,AL37/AL18,0) | AN69: =N69 | AO69: =Z69 | AP69: =AL69
A70: Marge variable (% du CA HT) | B70: % | C70: =IF(C28>0,C37/C28,0) | D70: =IF(D28>0,D37/D28,0) | E70: =IF(E28>0,E37/E28,0) | F70: =IF(F28>0,F37/F28,0) | G70: =IF(G28>0,G37/G28,0) | H70: =IF(H28>0,H37/H28,0) | I70: =IF(I28>0,I37/I28,0) | J70: =IF(J28>0,J37/J28,0) | ... AL70: =IF(AL28>0,AL37/AL28,0) | AN70: =N70 | AO70: =Z70 | AP70: =AL70
A71: CAC effectif | B71: € | C71: =IF(C14>0,C39/C14,0) | D71: =IF(D14>0,D39/D14,0) | E71: =IF(E14>0,E39/E14,0) | F71: =IF(F14>0,F39/F14,0) | G71: =IF(G14>0,G39/G14,0) | H71: =IF(H14>0,H39/H14,0) | I71: =IF(I14>0,I39/I14,0) | J71: =IF(J14>0,J39/J14,0) | ... AL71: =IF(AL14>0,AL39/AL14,0) | AN71: =N71 | AO71: =Z71 | AP71: =AL71
A72: Payback du CAC (mois) | B72: mois | C72: =IF(C69>0,Hypothèses!$D$23*$E$4/C69,0) | D72: =IF(D69>0,Hypothèses!$D$23*$E$4/D69,0) | E72: =IF(E69>0,Hypothèses!$D$23*$E$4/E69,0) | F72: =IF(F69>0,Hypothèses!$D$23*$E$4/F69,0) | G72: =IF(G69>0,Hypothèses!$D$23*$E$4/G69,0) | H72: =IF(H69>0,Hypothèses!$D$23*$E$4/H69,0) | I72: =IF(I69>0,Hypothèses!$D$23*$E$4/I69,0) | J72: =IF(J69>0,Hypothèses!$D$23*$E$4/J69,0) | ... AL72: =IF(AL69>0,Hypothèses!$D$23*$E$4/AL69,0) | AN72: =N72 | AO72: =Z72 | AP72: =AL72
A73: LTV contributive simplifiée (contribution / churn) | B73: € HT | C73: =IF(Hypothèses!$D$26*$D$4>0,C69/(Hypothèses!$D$26*$D$4),0) | D73: =IF(Hypothèses!$D$26*$D$4>0,D69/(Hypothèses!$D$26*$D$4),0) | E73: =IF(Hypothèses!$D$26*$D$4>0,E69/(Hypothèses!$D$26*$D$4),0) | F73: =IF(Hypothèses!$D$26*$D$4>0,F69/(Hypothèses!$D$26*$D$4),0) | G73: =IF(Hypothèses!$D$26*$D$4>0,G69/(Hypothèses!$D$26*$D$4),0) | H73: =IF(Hypothèses!$D$26*$D$4>0,H69/(Hypothèses!$D$26*$D$4),0) | I73: =IF(Hypothèses!$D$26*$D$4>0,I69/(Hypothèses!$D$26*$D$4),0) | J73: =IF(Hypothèses!$D$26*$D$4>0,J69/(Hypothèses!$D$26*$D$4),0) | ... AL73: =IF(Hypothèses!$D$26*$D$4>0,AL69/(Hypothèses!$D$26*$D$4),0) | AN73: =N73 | AO73: =Z73 | AP73: =AL73
A74: LTV / CAC | B74: x | C74: =IF(Hypothèses!$D$23*$E$4>0,C73/(Hypothèses!$D$23*$E$4),0) | D74: =IF(Hypothèses!$D$23*$E$4>0,D73/(Hypothèses!$D$23*$E$4),0) | E74: =IF(Hypothèses!$D$23*$E$4>0,E73/(Hypothèses!$D$23*$E$4),0) | F74: =IF(Hypothèses!$D$23*$E$4>0,F73/(Hypothèses!$D$23*$E$4),0) | G74: =IF(Hypothèses!$D$23*$E$4>0,G73/(Hypothèses!$D$23*$E$4),0) | H74: =IF(Hypothèses!$D$23*$E$4>0,H73/(Hypothèses!$D$23*$E$4),0) | I74: =IF(Hypothèses!$D$23*$E$4>0,I73/(Hypothèses!$D$23*$E$4),0) | J74: =IF(Hypothèses!$D$23*$E$4>0,J73/(Hypothèses!$D$23*$E$4),0) | ... AL74: =IF(Hypothèses!$D$23*$E$4>0,AL73/(Hypothèses!$D$23*$E$4),0) | AN74: =N74 | AO74: =Z74 | AP74: =AL74

Sheet S03
A1: Sensibilité S03 : CAC 240 € (copie du Central)
A2: Flux en € HT sauf mention TTC. Formules vivantes ; ne saisir que dans l'onglet Hypothèses et la ligne de chocs ci-dessous.
A3: Chocs de sensibilité (1 = aucun ; retard en mois) | C3: Prix × | D3: Churn × | E3: CAC × | F3: Coût IA × | G3: Coûts fixes × | H3: Retard lancement (mois)
C4: 1 | D4: 1 | E4: 1.6 | F4: 1 | G4: 1 | H4: 0
A5: Mois de lancement effectif | B5: =Hypothèses!$D$10+$H$4
A6: Ligne | B6: Unité | C6: M1 | D6: M2 | E6: M3 | F6: M4 | G6: M5 | H6: M6 | I6: M7 | J6: M8 | K6: M9 | L6: M10 | M6: M11 | N6: M12 | O6: M13 | P6: M14 | Q6: M15 | R6: M16 | S6: M17 | T6: M18 | U6: M19 | V6: M20 | W6: M21 | X6: M22 | Y6: M23 | Z6: M24 | AA6: M25 | AB6: M26 | AC6: M27 | AD6: M28 | AE6: M29 | AF6: M30 | AG6: M31 | AH6: M32 | AI6: M33 | AJ6: M34 | AK6: M35 | AL6: M36 | AN6: Année 1 | AO6: Année 2 | AP6: Année 3
A7: Mois | B7: n° | C7: 1 | D7: 2 | E7: 3 | F7: 4 | G7: 5 | H7: 6 | I7: 7 | J7: 8 | K7: 9 | L7: 10 | M7: 11 | N7: 12 | O7: 13 | P7: 14 | Q7: 15 | R7: 16 | S7: 17 | T7: 18 | U7: 19 | V7: 20 | W7: 21 | X7: 22 | Y7: 23 | Z7: 24 | AA7: 25 | AB7: 26 | AC7: 27 | AD7: 28 | AE7: 29 | AF7: 30 | AG7: 31 | AH7: 32 | AI7: 33 | AJ7: 34 | AK7: 35 | AL7: 36
A8: Date | C8: =EDATE(Hypothèses!$D$7,C7-1) | D8: =EDATE(Hypothèses!$D$7,D7-1) | E8: =EDATE(Hypothèses!$D$7,E7-1) | F8: =EDATE(Hypothèses!$D$7,F7-1) | G8: =EDATE(Hypothèses!$D$7,G7-1) | H8: =EDATE(Hypothèses!$D$7,H7-1) | I8: =EDATE(Hypothèses!$D$7,I7-1) | J8: =EDATE(Hypothèses!$D$7,J7-1) | ... AL8: =EDATE(Hypothèses!$D$7,AL7-1)
A9: Lancé ? (1 = oui) | B9: 0/1 | C9: =IF(C7>=$B$5,1,0) | D9: =IF(D7>=$B$5,1,0) | E9: =IF(E7>=$B$5,1,0) | F9: =IF(F7>=$B$5,1,0) | G9: =IF(G7>=$B$5,1,0) | H9: =IF(H7>=$B$5,1,0) | I9: =IF(I7>=$B$5,1,0) | J9: =IF(J7>=$B$5,1,0) | ... AL9: =IF(AL7>=$B$5,1,0)
A10: Pilote en cours ? (1 = oui) | B10: 0/1 | C10: =IF(AND(C7>=Hypothèses!$D$8,C7<$B$5),1,0) | D10: =IF(AND(D7>=Hypothèses!$D$8,D7<$B$5),1,0) | E10: =IF(AND(E7>=Hypothèses!$D$8,E7<$B$5),1,0) | F10: =IF(AND(F7>=Hypothèses!$D$8,F7<$B$5),1,0) | G10: =IF(AND(G7>=Hypothèses!$D$8,G7<$B$5),1,0) | H10: =IF(AND(H7>=Hypothèses!$D$8,H7<$B$5),1,0) | I10: =IF(AND(I7>=Hypothèses!$D$8,I7<$B$5),1,0) | J10: =IF(AND(J7>=Hypothèses!$D$8,J7<$B$5),1,0) | ... AL10: =IF(AND(AL7>=Hypothèses!$D$8,AL7<$B$5),1,0)
A11: Budget d'acquisition du mois | B11: € HT | C11: =IF(C9=1,IF(C7<=12,Hypothèses!$D$20,IF(C7<=24,Hypothèses!$D$21,Hypothèses!$D$22)),0) | D11: =IF(D9=1,IF(D7<=12,Hypothèses!$D$20,IF(D7<=24,Hypothèses!$D$21,Hypothèses!$D$22)),0) | E11: =IF(E9=1,IF(E7<=12,Hypothèses!$D$20,IF(E7<=24,Hypothèses!$D$21,Hypothèses!$D$22)),0) | F11: =IF(F9=1,IF(F7<=12,Hypothèses!$D$20,IF(F7<=24,Hypothèses!$D$21,Hypothèses!$D$22)),0) | G11: =IF(G9=1,IF(G7<=12,Hypothèses!$D$20,IF(G7<=24,Hypothèses!$D$21,Hypothèses!$D$22)),0) | H11: =IF(H9=1,IF(H7<=12,Hypothèses!$D$20,IF(H7<=24,Hypothèses!$D$21,Hypothèses!$D$22)),0) | I11: =IF(I9=1,IF(I7<=12,Hypothèses!$D$20,IF(I7<=24,Hypothèses!$D$21,Hypothèses!$D$22)),0) | J11: =IF(J9=1,IF(J7<=12,Hypothèses!$D$20,IF(J7<=24,Hypothèses!$D$21,Hypothèses!$D$22)),0) | ... AL11: =IF(AL9=1,IF(AL7<=12,Hypothèses!$D$20,IF(AL7<=24,Hypothèses!$D$21,Hypothèses!$D$22)),0) | AN11: =SUM(C11:N11) | AO11: =SUM(O11:Z11) | AP11: =SUM(AA11:AL11)
A12: Abonnés
A13: Abonnés en début de mois | B13: abonnés | C13: =0 | D13: =C18 | E13: =D18 | F13: =E18 | G13: =F18 | H13: =G18 | I13: =H18 | J13: =I18 | K13: =J18 | ... AL13: =AK18
A14: Nouveaux abonnés par acquisition payante | B14: abonnés | C14: =C11/(Hypothèses!$D$23*$E$4) | D14: =D11/(Hypothèses!$D$23*$E$4) | E14: =E11/(Hypothèses!$D$23*$E$4) | F14: =F11/(Hypothèses!$D$23*$E$4) | G14: =G11/(Hypothèses!$D$23*$E$4) | H14: =H11/(Hypothèses!$D$23*$E$4) | I14: =I11/(Hypothèses!$D$23*$E$4) | J14: =J11/(Hypothèses!$D$23*$E$4) | ... AL14: =AL11/(Hypothèses!$D$23*$E$4) | AN14: =SUM(C14:N14) | AO14: =SUM(O14:Z14) | AP14: =SUM(AA14:AL14)
A15: Nouveaux abonnés pilote | B15: abonnés | C15: =IF(C7=Hypothèses!$D$8,Hypothèses!$D$9,0) | D15: =IF(D7=Hypothèses!$D$8,Hypothèses!$D$9,0) | E15: =IF(E7=Hypothèses!$D$8,Hypothèses!$D$9,0) | F15: =IF(F7=Hypothèses!$D$8,Hypothèses!$D$9,0) | G15: =IF(G7=Hypothèses!$D$8,Hypothèses!$D$9,0) | H15: =IF(H7=Hypothèses!$D$8,Hypothèses!$D$9,0) | I15: =IF(I7=Hypothèses!$D$8,Hypothèses!$D$9,0) | J15: =IF(J7=Hypothèses!$D$8,Hypothèses!$D$9,0) | ... AL15: =IF(AL7=Hypothèses!$D$8,Hypothèses!$D$9,0) | AN15: =SUM(C15:N15) | AO15: =SUM(O15:Z15) | AP15: =SUM(AA15:AL15)
A16: Nouveaux abonnés organiques (parrainage) | B16: abonnés | C16: =C9*C13*Hypothèses!$D$24 | D16: =D9*D13*Hypothèses!$D$24 | E16: =E9*E13*Hypothèses!$D$24 | F16: =F9*F13*Hypothèses!$D$24 | G16: =G9*G13*Hypothèses!$D$24 | H16: =H9*H13*Hypothèses!$D$24 | I16: =I9*I13*Hypothèses!$D$24 | J16: =J9*J13*Hypothèses!$D$24 | ... AL16: =AL9*AL13*Hypothèses!$D$24 | AN16: =SUM(C16:N16) | AO16: =SUM(O16:Z16) | AP16: =SUM(AA16:AL16)
A17: Résiliations | B17: abonnés | C17: =C13*Hypothèses!$D$26*$D$4 | D17: =D13*Hypothèses!$D$26*$D$4 | E17: =E13*Hypothèses!$D$26*$D$4 | F17: =F13*Hypothèses!$D$26*$D$4 | G17: =G13*Hypothèses!$D$26*$D$4 | H17: =H13*Hypothèses!$D$26*$D$4 | I17: =I13*Hypothèses!$D$26*$D$4 | J17: =J13*Hypothèses!$D$26*$D$4 | ... AL17: =AL13*Hypothèses!$D$26*$D$4 | AN17: =SUM(C17:N17) | AO17: =SUM(O17:Z17) | AP17: =SUM(AA17:AL17)
A18: Abonnés en fin de mois | B18: abonnés | C18: =C13+C14+C15+C16-C17 | D18: =D13+D14+D15+D16-D17 | E18: =E13+E14+E15+E16-E17 | F18: =F13+F14+F15+F16-F17 | G18: =G13+G14+G15+G16-G17 | H18: =H13+H14+H15+H16-H17 | I18: =I13+I14+I15+I16-I17 | J18: =J13+J14+J15+J16-J17 | ... AL18: =AL13+AL14+AL15+AL16-AL17 | AN18: =N18 | AO18: =Z18 | AP18: =AL18
A19: dont Personal | B19: abonnés | C19: =C18*Hypothèses!$D$16 | D19: =D18*Hypothèses!$D$16 | E19: =E18*Hypothèses!$D$16 | F19: =F18*Hypothèses!$D$16 | G19: =G18*Hypothèses!$D$16 | H19: =H18*Hypothèses!$D$16 | I19: =I18*Hypothèses!$D$16 | J19: =J18*Hypothèses!$D$16 | ... AL19: =AL18*Hypothèses!$D$16 | AN19: =N19 | AO19: =Z19 | AP19: =AL19
A20: dont Premium | B20: abonnés | C20: =C18*Hypothèses!$D$17 | D20: =D18*Hypothèses!$D$17 | E20: =E18*Hypothèses!$D$17 | F20: =F18*Hypothèses!$D$17 | G20: =G18*Hypothèses!$D$17 | H20: =H18*Hypothèses!$D$17 | I20: =I18*Hypothèses!$D$17 | J20: =J18*Hypothèses!$D$17 | ... AL20: =AL18*Hypothèses!$D$17 | AN20: =N20 | AO20: =Z20 | AP20: =AL20
A21: dont Family | B21: abonnés | C21: =C18*Hypothèses!$D$18 | D21: =D18*Hypothèses!$D$18 | E21: =E18*Hypothèses!$D$18 | F21: =F18*Hypothèses!$D$18 | G21: =G18*Hypothèses!$D$18 | H21: =H18*Hypothèses!$D$18 | I21: =I18*Hypothèses!$D$18 | J21: =J18*Hypothèses!$D$18 | ... AL21: =AL18*Hypothèses!$D$18 | AN21: =N21 | AO21: =Z21 | AP21: =AL21
A22: Revenus
A23: Facturation Personal TTC | B23: € TTC | C23: =C19*Hypothèses!$D$12*$C$4 | D23: =D19*Hypothèses!$D$12*$C$4 | E23: =E19*Hypothèses!$D$12*$C$4 | F23: =F19*Hypothèses!$D$12*$C$4 | G23: =G19*Hypothèses!$D$12*$C$4 | H23: =H19*Hypothèses!$D$12*$C$4 | I23: =I19*Hypothèses!$D$12*$C$4 | J23: =J19*Hypothèses!$D$12*$C$4 | ... AL23: =AL19*Hypothèses!$D$12*$C$4 | AN23: =SUM(C23:N23) | AO23: =SUM(O23:Z23) | AP23: =SUM(AA23:AL23)
A24: Facturation Premium TTC | B24: € TTC | C24: =C20*Hypothèses!$D$13*$C$4 | D24: =D20*Hypothèses!$D$13*$C$4 | E24: =E20*Hypothèses!$D$13*$C$4 | F24: =F20*Hypothèses!$D$13*$C$4 | G24: =G20*Hypothèses!$D$13*$C$4 | H24: =H20*Hypothèses!$D$13*$C$4 | I24: =I20*Hypothèses!$D$13*$C$4 | J24: =J20*Hypothèses!$D$13*$C$4 | ... AL24: =AL20*Hypothèses!$D$13*$C$4 | AN24: =SUM(C24:N24) | AO24: =SUM(O24:Z24) | AP24: =SUM(AA24:AL24)
A25: Facturation Family TTC | B25: € TTC | C25: =C21*Hypothèses!$D$14*$C$4 | D25: =D21*Hypothèses!$D$14*$C$4 | E25: =E21*Hypothèses!$D$14*$C$4 | F25: =F21*Hypothèses!$D$14*$C$4 | G25: =G21*Hypothèses!$D$14*$C$4 | H25: =H21*Hypothèses!$D$14*$C$4 | I25: =I21*Hypothèses!$D$14*$C$4 | J25: =J21*Hypothèses!$D$14*$C$4 | ... AL25: =AL21*Hypothèses!$D$14*$C$4 | AN25: =SUM(C25:N25) | AO25: =SUM(O25:Z25) | AP25: =SUM(AA25:AL25)
A26: Facturation totale TTC (MRR TTC) | B26: € TTC | C26: =C23+C24+C25 | D26: =D23+D24+D25 | E26: =E23+E24+E25 | F26: =F23+F24+F25 | G26: =G23+G24+G25 | H26: =H23+H24+H25 | I26: =I23+I24+I25 | J26: =J23+J24+J25 | ... AL26: =AL23+AL24+AL25 | AN26: =SUM(C26:N26) | AO26: =SUM(O26:Z26) | AP26: =SUM(AA26:AL26)
A27: TVA collectée | B27: € | C27: =C26*Hypothèses!$D$15/(1+Hypothèses!$D$15) | D27: =D26*Hypothèses!$D$15/(1+Hypothèses!$D$15) | E27: =E26*Hypothèses!$D$15/(1+Hypothèses!$D$15) | F27: =F26*Hypothèses!$D$15/(1+Hypothèses!$D$15) | G27: =G26*Hypothèses!$D$15/(1+Hypothèses!$D$15) | H27: =H26*Hypothèses!$D$15/(1+Hypothèses!$D$15) | I27: =I26*Hypothèses!$D$15/(1+Hypothèses!$D$15) | J27: =J26*Hypothèses!$D$15/(1+Hypothèses!$D$15) | ... AL27: =AL26*Hypothèses!$D$15/(1+Hypothèses!$D$15) | AN27: =SUM(C27:N27) | AO27: =SUM(O27:Z27) | AP27: =SUM(AA27:AL27)
A28: Chiffre d'affaires HT | B28: € HT | C28: =C26-C27 | D28: =D26-D27 | E28: =E26-E27 | F28: =F26-F27 | G28: =G26-G27 | H28: =H26-H27 | I28: =I26-I27 | J28: =J26-J27 | ... AL28: =AL26-AL27 | AN28: =SUM(C28:N28) | AO28: =SUM(O28:Z28) | AP28: =SUM(AA28:AL28)
A29: Impayés (TTC) | B29: € TTC | C29: =C26*Hypothèses!$D$27 | D29: =D26*Hypothèses!$D$27 | E29: =E26*Hypothèses!$D$27 | F29: =F26*Hypothèses!$D$27 | G29: =G26*Hypothèses!$D$27 | H29: =H26*Hypothèses!$D$27 | I29: =I26*Hypothèses!$D$27 | J29: =J26*Hypothèses!$D$27 | ... AL29: =AL26*Hypothèses!$D$27 | AN29: =SUM(C29:N29) | AO29: =SUM(O29:Z29) | AP29: =SUM(AA29:AL29)
A30: Frais de paiement | B30: € | C30: =(C26-C29)*Hypothèses!$D$28+C18*Hypothèses!$D$29 | D30: =(D26-D29)*Hypothèses!$D$28+D18*Hypothèses!$D$29 | E30: =(E26-E29)*Hypothèses!$D$28+E18*Hypothèses!$D$29 | F30: =(F26-F29)*Hypothèses!$D$28+F18*Hypothèses!$D$29 | G30: =(G26-G29)*Hypothèses!$D$28+G18*Hypothèses!$D$29 | H30: =(H26-H29)*Hypothèses!$D$28+H18*Hypothèses!$D$29 | I30: =(I26-I29)*Hypothèses!$D$28+I18*Hypothèses!$D$29 | J30: =(J26-J29)*Hypothèses!$D$28+J18*Hypothèses!$D$29 | ... AL30: =(AL26-AL29)*Hypothèses!$D$28+AL18*Hypothèses!$D$29 | AN30: =SUM(C30:N30) | AO30: =SUM(O30:Z30) | AP30: =SUM(AA30:AL30)
A31: Encaissements nets TTC | B31: € TTC | C31: =C26-C29-C30 | D31: =D26-D29-D30 | E31: =E26-E29-E30 | F31: =F26-F29-F30 | G31: =G26-G29-G30 | H31: =H26-H29-H30 | I31: =I26-I29-I30 | J31: =J26-J29-J30 | ... AL31: =AL26-AL29-AL30 | AN31: =SUM(C31:N31) | AO31: =SUM(O31:Z31) | AP31: =SUM(AA31:AL31)
A32: Coûts variables
A33: Coût IA et outils (missions × coût par mission) | B33: € HT | C33: =(C19*Hypothèses!$D$31+C20*Hypothèses!$D$32+C21*Hypothèses!$D$33)*Hypothèses!$D$34*$F$4 | D33: =(D19*Hypothèses!$D$31+D20*Hypothèses!$D$32+D21*Hypothèses!$D$33)*Hypothèses!$D$34*$F$4 | E33: =(E19*Hypothèses!$D$31+E20*Hypothèses!$D$32+E21*Hypothèses!$D$33)*Hypothèses!$D$34*$F$4 | F33: =(F19*Hypothèses!$D$31+F20*Hypothèses!$D$32+F21*Hypothèses!$D$33)*Hypothèses!$D$34*$F$4 | G33: =(G19*Hypothèses!$D$31+G20*Hypothèses!$D$32+G21*Hypothèses!$D$33)*Hypothèses!$D$34*$F$4 | H33: =(H19*Hypothèses!$D$31+H20*Hypothèses!$D$32+H21*Hypothèses!$D$33)*Hypothèses!$D$34*$F$4 | I33: =(I19*Hypothèses!$D$31+I20*Hypothèses!$D$32+I21*Hypothèses!$D$33)*Hypothèses!$D$34*$F$4 | J33: =(J19*Hypothèses!$D$31+J20*Hypothèses!$D$32+J21*Hypothèses!$D$33)*Hypothèses!$D$34*$F$4 | ... AL33: =(AL19*Hypothèses!$D$31+AL20*Hypothèses!$D$32+AL21*Hypothèses!$D$33)*Hypothèses!$D$34*$F$4 | AN33: =SUM(C33:N33) | AO33: =SUM(O33:Z33) | AP33: =SUM(AA33:AL33)
A34: Hébergement, stockage, connecteurs | B34: € HT | C34: =C18*Hypothèses!$D$35 | D34: =D18*Hypothèses!$D$35 | E34: =E18*Hypothèses!$D$35 | F34: =F18*Hypothèses!$D$35 | G34: =G18*Hypothèses!$D$35 | H34: =H18*Hypothèses!$D$35 | I34: =I18*Hypothèses!$D$35 | J34: =J18*Hypothèses!$D$35 | ... AL34: =AL18*Hypothèses!$D$35 | AN34: =SUM(C34:N34) | AO34: =SUM(O34:Z34) | AP34: =SUM(AA34:AL34)
A35: Support humain | B35: € HT | C35: =C18*Hypothèses!$D$36 | D35: =D18*Hypothèses!$D$36 | E35: =E18*Hypothèses!$D$36 | F35: =F18*Hypothèses!$D$36 | G35: =G18*Hypothèses!$D$36 | H35: =H18*Hypothèses!$D$36 | I35: =I18*Hypothèses!$D$36 | J35: =J18*Hypothèses!$D$36 | ... AL35: =AL18*Hypothèses!$D$36 | AN35: =SUM(C35:N35) | AO35: =SUM(O35:Z35) | AP35: =SUM(AA35:AL35)
A36: Total coûts variables | B36: € HT | C36: =C33+C34+C35 | D36: =D33+D34+D35 | E36: =E33+E34+E35 | F36: =F33+F34+F35 | G36: =G33+G34+G35 | H36: =H33+H34+H35 | I36: =I33+I34+I35 | J36: =J33+J34+J35 | ... AL36: =AL33+AL34+AL35 | AN36: =SUM(C36:N36) | AO36: =SUM(O36:Z36) | AP36: =SUM(AA36:AL36)
A37: Marge sur coûts variables (CA HT − variables − frais − impayés HT) | B37: € HT | C37: =C28-C36-C30-C29/(1+Hypothèses!$D$15) | D37: =D28-D36-D30-D29/(1+Hypothèses!$D$15) | E37: =E28-E36-E30-E29/(1+Hypothèses!$D$15) | F37: =F28-F36-F30-F29/(1+Hypothèses!$D$15) | G37: =G28-G36-G30-G29/(1+Hypothèses!$D$15) | H37: =H28-H36-H30-H29/(1+Hypothèses!$D$15) | I37: =I28-I36-I30-I29/(1+Hypothèses!$D$15) | J37: =J28-J36-J30-J29/(1+Hypothèses!$D$15) | ... AL37: =AL28-AL36-AL30-AL29/(1+Hypothèses!$D$15) | AN37: =SUM(C37:N37) | AO37: =SUM(O37:Z37) | AP37: =SUM(AA37:AL37)
A38: Acquisition et coûts fixes
A39: Dépenses d'acquisition | B39: € HT | C39: =C11 | D39: =D11 | E39: =E11 | F39: =F11 | G39: =G11 | H39: =H11 | I39: =I11 | J39: =J11 | ... AL39: =AL11 | AN39: =SUM(C39:N39) | AO39: =SUM(O39:Z39) | AP39: =SUM(AA39:AL39)
A40: Rémunération des fondateurs | B40: € HT | C40: =IF(C7>=Hypothèses!$D$39,Hypothèses!$D$38*Hypothèses!$D$40,0)*$G$4 | D40: =IF(D7>=Hypothèses!$D$39,Hypothèses!$D$38*Hypothèses!$D$40,0)*$G$4 | E40: =IF(E7>=Hypothèses!$D$39,Hypothèses!$D$38*Hypothèses!$D$40,0)*$G$4 | F40: =IF(F7>=Hypothèses!$D$39,Hypothèses!$D$38*Hypothèses!$D$40,0)*$G$4 | G40: =IF(G7>=Hypothèses!$D$39,Hypothèses!$D$38*Hypothèses!$D$40,0)*$G$4 | H40: =IF(H7>=Hypothèses!$D$39,Hypothèses!$D$38*Hypothèses!$D$40,0)*$G$4 | I40: =IF(I7>=Hypothèses!$D$39,Hypothèses!$D$38*Hypothèses!$D$40,0)*$G$4 | J40: =IF(J7>=Hypothèses!$D$39,Hypothèses!$D$38*Hypothèses!$D$40,0)*$G$4 | ... AL40: =IF(AL7>=Hypothèses!$D$39,Hypothèses!$D$38*Hypothèses!$D$40,0)*$G$4 | AN40: =SUM(C40:N40) | AO40: =SUM(O40:Z40) | AP40: =SUM(AA40:AL40)
A41: Salarié 1 (growth / customer success) | B41: € HT | C41: =IF(C7>=Hypothèses!$D$41,Hypothèses!$D$42,0)*$G$4 | D41: =IF(D7>=Hypothèses!$D$41,Hypothèses!$D$42,0)*$G$4 | E41: =IF(E7>=Hypothèses!$D$41,Hypothèses!$D$42,0)*$G$4 | F41: =IF(F7>=Hypothèses!$D$41,Hypothèses!$D$42,0)*$G$4 | G41: =IF(G7>=Hypothèses!$D$41,Hypothèses!$D$42,0)*$G$4 | H41: =IF(H7>=Hypothèses!$D$41,Hypothèses!$D$42,0)*$G$4 | I41: =IF(I7>=Hypothèses!$D$41,Hypothèses!$D$42,0)*$G$4 | J41: =IF(J7>=Hypothèses!$D$41,Hypothèses!$D$42,0)*$G$4 | ... AL41: =IF(AL7>=Hypothèses!$D$41,Hypothèses!$D$42,0)*$G$4 | AN41: =SUM(C41:N41) | AO41: =SUM(O41:Z41) | AP41: =SUM(AA41:AL41)
A42: Salarié 2 (ingénieur) | B42: € HT | C42: =IF(C7>=Hypothèses!$D$43,Hypothèses!$D$44,0)*$G$4 | D42: =IF(D7>=Hypothèses!$D$43,Hypothèses!$D$44,0)*$G$4 | E42: =IF(E7>=Hypothèses!$D$43,Hypothèses!$D$44,0)*$G$4 | F42: =IF(F7>=Hypothèses!$D$43,Hypothèses!$D$44,0)*$G$4 | G42: =IF(G7>=Hypothèses!$D$43,Hypothèses!$D$44,0)*$G$4 | H42: =IF(H7>=Hypothèses!$D$43,Hypothèses!$D$44,0)*$G$4 | I42: =IF(I7>=Hypothèses!$D$43,Hypothèses!$D$44,0)*$G$4 | J42: =IF(J7>=Hypothèses!$D$43,Hypothèses!$D$44,0)*$G$4 | ... AL42: =IF(AL7>=Hypothèses!$D$43,Hypothèses!$D$44,0)*$G$4 | AN42: =SUM(C42:N42) | AO42: =SUM(O42:Z42) | AP42: =SUM(AA42:AL42)
A43: Développement MVP externe (étalé jusqu'au lancement) | B43: € HT | C43: =IF(C7<$B$5,Hypothèses!$D$45/MAX(1,$B$5-1),0) | D43: =IF(D7<$B$5,Hypothèses!$D$45/MAX(1,$B$5-1),0) | E43: =IF(E7<$B$5,Hypothèses!$D$45/MAX(1,$B$5-1),0) | F43: =IF(F7<$B$5,Hypothèses!$D$45/MAX(1,$B$5-1),0) | G43: =IF(G7<$B$5,Hypothèses!$D$45/MAX(1,$B$5-1),0) | H43: =IF(H7<$B$5,Hypothèses!$D$45/MAX(1,$B$5-1),0) | I43: =IF(I7<$B$5,Hypothèses!$D$45/MAX(1,$B$5-1),0) | J43: =IF(J7<$B$5,Hypothèses!$D$45/MAX(1,$B$5-1),0) | ... AL43: =IF(AL7<$B$5,Hypothèses!$D$45/MAX(1,$B$5-1),0) | AN43: =SUM(C43:N43) | AO43: =SUM(O43:Z43) | AP43: =SUM(AA43:AL43)
A44: Outils et SaaS | B44: € HT | C44: =Hypothèses!$D$46*$G$4 | D44: =Hypothèses!$D$46*$G$4 | E44: =Hypothèses!$D$46*$G$4 | F44: =Hypothèses!$D$46*$G$4 | G44: =Hypothèses!$D$46*$G$4 | H44: =Hypothèses!$D$46*$G$4 | I44: =Hypothèses!$D$46*$G$4 | J44: =Hypothèses!$D$46*$G$4 | ... AL44: =Hypothèses!$D$46*$G$4 | AN44: =SUM(C44:N44) | AO44: =SUM(O44:Z44) | AP44: =SUM(AA44:AL44)
A45: Juridique et comptabilité | B45: € HT | C45: =Hypothèses!$D$47*$G$4 | D45: =Hypothèses!$D$47*$G$4 | E45: =Hypothèses!$D$47*$G$4 | F45: =Hypothèses!$D$47*$G$4 | G45: =Hypothèses!$D$47*$G$4 | H45: =Hypothèses!$D$47*$G$4 | I45: =Hypothèses!$D$47*$G$4 | J45: =Hypothèses!$D$47*$G$4 | ... AL45: =Hypothèses!$D$47*$G$4 | AN45: =SUM(C45:N45) | AO45: =SUM(O45:Z45) | AP45: =SUM(AA45:AL45)
A46: Assurance RC pro | B46: € | C46: =C9*Hypothèses!$D$48*$G$4 | D46: =D9*Hypothèses!$D$48*$G$4 | E46: =E9*Hypothèses!$D$48*$G$4 | F46: =F9*Hypothèses!$D$48*$G$4 | G46: =G9*Hypothèses!$D$48*$G$4 | H46: =H9*Hypothèses!$D$48*$G$4 | I46: =I9*Hypothèses!$D$48*$G$4 | J46: =J9*Hypothèses!$D$48*$G$4 | ... AL46: =AL9*Hypothèses!$D$48*$G$4 | AN46: =SUM(C46:N46) | AO46: =SUM(O46:Z46) | AP46: =SUM(AA46:AL46)
A47: Marketing fixe | B47: € HT | C47: =C9*Hypothèses!$D$49*$G$4 | D47: =D9*Hypothèses!$D$49*$G$4 | E47: =E9*Hypothèses!$D$49*$G$4 | F47: =F9*Hypothèses!$D$49*$G$4 | G47: =G9*Hypothèses!$D$49*$G$4 | H47: =H9*Hypothèses!$D$49*$G$4 | I47: =I9*Hypothèses!$D$49*$G$4 | J47: =J9*Hypothèses!$D$49*$G$4 | ... AL47: =AL9*Hypothèses!$D$49*$G$4 | AN47: =SUM(C47:N47) | AO47: =SUM(O47:Z47) | AP47: =SUM(AA47:AL47)
A48: Frais généraux | B48: € HT | C48: =Hypothèses!$D$50*$G$4 | D48: =Hypothèses!$D$50*$G$4 | E48: =Hypothèses!$D$50*$G$4 | F48: =Hypothèses!$D$50*$G$4 | G48: =Hypothèses!$D$50*$G$4 | H48: =Hypothèses!$D$50*$G$4 | I48: =Hypothèses!$D$50*$G$4 | J48: =Hypothèses!$D$50*$G$4 | ... AL48: =Hypothèses!$D$50*$G$4 | AN48: =SUM(C48:N48) | AO48: =SUM(O48:Z48) | AP48: =SUM(AA48:AL48)
A49: Audit de sécurité (annuel, à partir du lancement) | B49: € HT | C49: =IF(AND(C9=1,MOD(C7-$B$5,12)=0),Hypothèses!$D$51,0)*$G$4 | D49: =IF(AND(D9=1,MOD(D7-$B$5,12)=0),Hypothèses!$D$51,0)*$G$4 | E49: =IF(AND(E9=1,MOD(E7-$B$5,12)=0),Hypothèses!$D$51,0)*$G$4 | F49: =IF(AND(F9=1,MOD(F7-$B$5,12)=0),Hypothèses!$D$51,0)*$G$4 | G49: =IF(AND(G9=1,MOD(G7-$B$5,12)=0),Hypothèses!$D$51,0)*$G$4 | H49: =IF(AND(H9=1,MOD(H7-$B$5,12)=0),Hypothèses!$D$51,0)*$G$4 | I49: =IF(AND(I9=1,MOD(I7-$B$5,12)=0),Hypothèses!$D$51,0)*$G$4 | J49: =IF(AND(J9=1,MOD(J7-$B$5,12)=0),Hypothèses!$D$51,0)*$G$4 | ... AL49: =IF(AND(AL9=1,MOD(AL7-$B$5,12)=0),Hypothèses!$D$51,0)*$G$4 | AN49: =SUM(C49:N49) | AO49: =SUM(O49:Z49) | AP49: =SUM(AA49:AL49)
A50: Frais de constitution | B50: € HT | C50: =IF(C7=2,Hypothèses!$D$52,0) | D50: =IF(D7=2,Hypothèses!$D$52,0) | E50: =IF(E7=2,Hypothèses!$D$52,0) | F50: =IF(F7=2,Hypothèses!$D$52,0) | G50: =IF(G7=2,Hypothèses!$D$52,0) | H50: =IF(H7=2,Hypothèses!$D$52,0) | I50: =IF(I7=2,Hypothèses!$D$52,0) | J50: =IF(J7=2,Hypothèses!$D$52,0) | ... AL50: =IF(AL7=2,Hypothèses!$D$52,0) | AN50: =SUM(C50:N50) | AO50: =SUM(O50:Z50) | AP50: =SUM(AA50:AL50)
A51: Total coûts fixes | B51: € HT | C51: =SUM(C40:C50) | D51: =SUM(D40:D50) | E51: =SUM(E40:E50) | F51: =SUM(F40:F50) | G51: =SUM(G40:G50) | H51: =SUM(H40:H50) | I51: =SUM(I40:I50) | J51: =SUM(J40:J50) | ... AL51: =SUM(AL40:AL50) | AN51: =SUM(C51:N51) | AO51: =SUM(O51:Z51) | AP51: =SUM(AA51:AL51)
A52: EBITDA (marge variable − acquisition − fixes) | B52: € HT | C52: =C37-C39-C51 | D52: =D37-D39-D51 | E52: =E37-E39-E51 | F52: =F37-F39-F51 | G52: =G37-G39-G51 | H52: =H37-H39-H51 | I52: =I37-I39-I51 | J52: =J37-J39-J51 | ... AL52: =AL37-AL39-AL51 | AN52: =SUM(C52:N52) | AO52: =SUM(O52:Z52) | AP52: =SUM(AA52:AL52)
A53: EBITDA positif ? (1 = oui) | B53: 0/1 | C53: =IF(C52>0,1,0) | D53: =IF(D52>0,1,0) | E53: =IF(E52>0,1,0) | F53: =IF(F52>0,1,0) | G53: =IF(G52>0,1,0) | H53: =IF(H52>0,1,0) | I53: =IF(I52>0,1,0) | J53: =IF(J52>0,1,0) | ... AL53: =IF(AL52>0,1,0)
A54: Trésorerie
A55: TVA collectée reversée (mois suivant) | B55: € | C55: =0 | D55: =C27 | E55: =D27 | F55: =E27 | G55: =F27 | H55: =G27 | I55: =H27 | J55: =I27 | K55: =J27 | ... AL55: =AK27 | AN55: =SUM(C55:N55) | AO55: =SUM(O55:Z55) | AP55: =SUM(AA55:AL55)
A56: TVA déductible récupérée (mois suivant, coûts externes) | B56: € | C56: =0 | D56: =(C36+C39+C43+C44+C45+C47+C48+C49+C50)*Hypothèses!$D$15 | E56: =(D36+D39+D43+D44+D45+D47+D48+D49+D50)*Hypothèses!$D$15 | F56: =(E36+E39+E43+E44+E45+E47+E48+E49+E50)*Hypothèses!$D$15 | G56: =(F36+F39+F43+F44+F45+F47+F48+F49+F50)*Hypothèses!$D$15 | H56: =(G36+G39+G43+G44+G45+G47+G48+G49+G50)*Hypothèses!$D$15 | I56: =(H36+H39+H43+H44+H45+H47+H48+H49+H50)*Hypothèses!$D$15 | J56: =(I36+I39+I43+I44+I45+I47+I48+I49+I50)*Hypothèses!$D$15 | K56: =(J36+J39+J43+J44+J45+J47+J48+J49+J50)*Hypothèses!$D$15 | ... AL56: =(AK36+AK39+AK43+AK44+AK45+AK47+AK48+AK49+AK50)*Hypothèses!$D$15 | AN56: =SUM(C56:N56) | AO56: =SUM(O56:Z56) | AP56: =SUM(AA56:AL56)
A57: Financement reçu | B57: € | C57: =Hypothèses!$D$56*(IF(C7=Hypothèses!$D$57,Hypothèses!$D$58,0)+IF(C7=Hypothèses!$D$59,Hypothèses!$D$60,0)+IF(C7=Hypothèses!$D$61,Hypothèses!$D$62,0)) | D57: =Hypothèses!$D$56*(IF(D7=Hypothèses!$D$57,Hypothèses!$D$58,0)+IF(D7=Hypothèses!$D$59,Hypothèses!$D$60,0)+IF(D7=Hypothèses!$D$61,Hypothèses!$D$62,0)) | E57: =Hypothèses!$D$56*(IF(E7=Hypothèses!$D$57,Hypothèses!$D$58,0)+IF(E7=Hypothèses!$D$59,Hypothèses!$D$60,0)+IF(E7=Hypothèses!$D$61,Hypothèses!$D$62,0)) | F57: =Hypothèses!$D$56*(IF(F7=Hypothèses!$D$57,Hypothèses!$D$58,0)+IF(F7=Hypothèses!$D$59,Hypothèses!$D$60,0)+IF(F7=Hypothèses!$D$61,Hypothèses!$D$62,0)) | G57: =Hypothèses!$D$56*(IF(G7=Hypothèses!$D$57,Hypothèses!$D$58,0)+IF(G7=Hypothèses!$D$59,Hypothèses!$D$60,0)+IF(G7=Hypothèses!$D$61,Hypothèses!$D$62,0)) | H57: =Hypothèses!$D$56*(IF(H7=Hypothèses!$D$57,Hypothèses!$D$58,0)+IF(H7=Hypothèses!$D$59,Hypothèses!$D$60,0)+IF(H7=Hypothèses!$D$61,Hypothèses!$D$62,0)) | I57: =Hypothèses!$D$56*(IF(I7=Hypothèses!$D$57,Hypothèses!$D$58,0)+IF(I7=Hypothèses!$D$59,Hypothèses!$D$60,0)+IF(I7=Hypothèses!$D$61,Hypothèses!$D$62,0)) | J57: =Hypothèses!$D$56*(IF(J7=Hypothèses!$D$57,Hypothèses!$D$58,0)+IF(J7=Hypothèses!$D$59,Hypothèses!$D$60,0)+IF(J7=Hypothèses!$D$61,Hypothèses!$D$62,0)) | ... AL57: =Hypothèses!$D$56*(IF(AL7=Hypothèses!$D$57,Hypothèses!$D$58,0)+IF(AL7=Hypothèses!$D$59,Hypothèses!$D$60,0)+IF(AL7=Hypothèses!$D$61,Hypothèses!$D$62,0)) | AN57: =SUM(C57:N57) | AO57: =SUM(O57:Z57) | AP57: =SUM(AA57:AL57)
A58: Trésorerie d'ouverture | B58: € | C58: =Hypothèses!$D$54 | D58: =C60 | E58: =D60 | F58: =E60 | G58: =F60 | H58: =G60 | I58: =H60 | J58: =I60 | K58: =J60 | ... AL58: =AK60
A59: Flux de trésorerie du mois | B59: € | C59: =C31-C36-C39-C51-C55+C56+C57 | D59: =D31-D36-D39-D51-D55+D56+D57 | E59: =E31-E36-E39-E51-E55+E56+E57 | F59: =F31-F36-F39-F51-F55+F56+F57 | G59: =G31-G36-G39-G51-G55+G56+G57 | H59: =H31-H36-H39-H51-H55+H56+H57 | I59: =I31-I36-I39-I51-I55+I56+I57 | J59: =J31-J36-J39-J51-J55+J56+J57 | ... AL59: =AL31-AL36-AL39-AL51-AL55+AL56+AL57 | AN59: =SUM(C59:N59) | AO59: =SUM(O59:Z59) | AP59: =SUM(AA59:AL59)
A60: Trésorerie de clôture | B60: € | C60: =C58+C59 | D60: =D58+D59 | E60: =E58+E59 | F60: =F58+F59 | G60: =G58+G59 | H60: =H58+H59 | I60: =I58+I59 | J60: =J58+J59 | ... AL60: =AL58+AL59 | AN60: =N60 | AO60: =Z60 | AP60: =AL60
A61: Financement cumulé | B61: € | C61: =0+C57 | D61: =C61+D57 | E61: =D61+E57 | F61: =E61+F57 | G61: =F61+G57 | H61: =G61+H57 | I61: =H61+I57 | J61: =I61+J57 | K61: =J61+K57 | ... AL61: =AK61+AL57 | AN61: =N61 | AO61: =Z61 | AP61: =AL61
A62: Trésorerie cumulée hors financement | B62: € | C62: =C60-C61 | D62: =D60-D61 | E62: =E60-E61 | F62: =F60-F61 | G62: =G60-G61 | H62: =H60-H61 | I62: =I60-I61 | J62: =J60-J61 | ... AL62: =AL60-AL61 | AN62: =N62 | AO62: =Z62 | AP62: =AL62
A63: Point bas glissant hors financement | B63: € | C63: =C62 | D63: =MIN(C63,D62) | E63: =MIN(D63,E62) | F63: =MIN(E63,F62) | G63: =MIN(F63,G62) | H63: =MIN(G63,H62) | I63: =MIN(H63,I62) | J63: =MIN(I63,J62) | K63: =MIN(J63,K62) | ... AL63: =MIN(AK63,AL62) | AN63: =N63 | AO63: =Z63 | AP63: =AL63
A64: Trésorerie cumulée hors financement positive après lancement ? (1 = oui) | B64: 0/1 | C64: =IF(AND(C9=1,C62>0),1,0) | D64: =IF(AND(D9=1,D62>0),1,0) | E64: =IF(AND(E9=1,E62>0),1,0) | F64: =IF(AND(F9=1,F62>0),1,0) | G64: =IF(AND(G9=1,G62>0),1,0) | H64: =IF(AND(H9=1,H62>0),1,0) | I64: =IF(AND(I9=1,I62>0),1,0) | J64: =IF(AND(J9=1,J62>0),1,0) | ... AL64: =IF(AND(AL9=1,AL62>0),1,0)
A65: Indicateurs
A66: ARR HT instantané (CA HT × 12) | B66: € HT | C66: =C28*12 | D66: =D28*12 | E66: =E28*12 | F66: =F28*12 | G66: =G28*12 | H66: =H28*12 | I66: =I28*12 | J66: =J28*12 | ... AL66: =AL28*12 | AN66: =N66 | AO66: =Z66 | AP66: =AL66
A67: ARPA HT (CA HT / abonnés) | B67: € HT | C67: =IF(C18>0,C28/C18,0) | D67: =IF(D18>0,D28/D18,0) | E67: =IF(E18>0,E28/E18,0) | F67: =IF(F18>0,F28/F18,0) | G67: =IF(G18>0,G28/G18,0) | H67: =IF(H18>0,H28/H18,0) | I67: =IF(I18>0,I28/I18,0) | J67: =IF(J18>0,J28/J18,0) | ... AL67: =IF(AL18>0,AL28/AL18,0) | AN67: =N67 | AO67: =Z67 | AP67: =AL67
A68: Coût variable par abonné | B68: € HT | C68: =IF(C18>0,C36/C18,0) | D68: =IF(D18>0,D36/D18,0) | E68: =IF(E18>0,E36/E18,0) | F68: =IF(F18>0,F36/F18,0) | G68: =IF(G18>0,G36/G18,0) | H68: =IF(H18>0,H36/H18,0) | I68: =IF(I18>0,I36/I18,0) | J68: =IF(J18>0,J36/J18,0) | ... AL68: =IF(AL18>0,AL36/AL18,0) | AN68: =N68 | AO68: =Z68 | AP68: =AL68
A69: Contribution par abonné | B69: € HT | C69: =IF(C18>0,C37/C18,0) | D69: =IF(D18>0,D37/D18,0) | E69: =IF(E18>0,E37/E18,0) | F69: =IF(F18>0,F37/F18,0) | G69: =IF(G18>0,G37/G18,0) | H69: =IF(H18>0,H37/H18,0) | I69: =IF(I18>0,I37/I18,0) | J69: =IF(J18>0,J37/J18,0) | ... AL69: =IF(AL18>0,AL37/AL18,0) | AN69: =N69 | AO69: =Z69 | AP69: =AL69
A70: Marge variable (% du CA HT) | B70: % | C70: =IF(C28>0,C37/C28,0) | D70: =IF(D28>0,D37/D28,0) | E70: =IF(E28>0,E37/E28,0) | F70: =IF(F28>0,F37/F28,0) | G70: =IF(G28>0,G37/G28,0) | H70: =IF(H28>0,H37/H28,0) | I70: =IF(I28>0,I37/I28,0) | J70: =IF(J28>0,J37/J28,0) | ... AL70: =IF(AL28>0,AL37/AL28,0) | AN70: =N70 | AO70: =Z70 | AP70: =AL70
A71: CAC effectif | B71: € | C71: =IF(C14>0,C39/C14,0) | D71: =IF(D14>0,D39/D14,0) | E71: =IF(E14>0,E39/E14,0) | F71: =IF(F14>0,F39/F14,0) | G71: =IF(G14>0,G39/G14,0) | H71: =IF(H14>0,H39/H14,0) | I71: =IF(I14>0,I39/I14,0) | J71: =IF(J14>0,J39/J14,0) | ... AL71: =IF(AL14>0,AL39/AL14,0) | AN71: =N71 | AO71: =Z71 | AP71: =AL71
